Workbook

Sheet Res Semanal
A2: semana 1
A3: GRAL | B3: TEMM | C3: CUOTA DIA | D3: alcance | E3: GAP | F3: produc | G3: obj | H3: gap
A4: altas totales | B4: =+'Seg Diario'!M4 -> 0 | C4: =+'Seg Diario'!N4 -> 79.469291 | D4: =+B4/C4 -> 0 | E4: =+B4-C4 -> -79.469291 | F4: =+B4/J4/46 -> 0 | G4: =+C4/J4/J5 -> 0.20534701 | H4: =+F4-G4 -> -0.20534701 | I4: dia | J4: 9
A5: temm | B5: =+'Seg Diario'!Q4 -> 496 | C5: =+'Seg Diario'!R4 -> 39.826684 | D5: =+B5/C5 -> 12.453962 | E5: =+B5-C5 -> 456.17332 | F5: =+B5/J4/J5 -> 1.2816537 | G5: =+C5/J4/J5 -> 0.10291133 | H5: =+F5-G5 -> 1.1787424 | I5: PDV´s | J5: 43
A6: porta | B6: =+'Seg Diario'!U4 -> 0 | C6: =+'Seg Diario'!V4 -> 6.63289 | D6: =+B6/C6 -> 0 | E6: =+B6-C6 -> -6.63289 | F6: =+B6/J4/J5 -> 0 | G6: =+C6/J4/J5 -> 0.017139251 | H6: =+F6-G6 -> -0.017139251
A7: pp voz | B7: =+'Seg Diario'!Y4 -> -496 | C7: =+'Seg Diario'!Z4 -> 33.009717 | D7: =+B7/C7 -> -15.025879 | E7: =+B7-C7 -> -529.00972 | F7: =+B7/J4/J5 -> -1.2816537 | G7: =+C7/J4/J5 -> 0.085296426 | H7: =+F7-G7 -> -1.3669502
A8: semana 2
A9: PALANCA | B9: TEMM | C9: CUOTA DIA | D9: alcance | E9: GAP | F9: produc | G9: obj | H9: gap | I9: PDVS | J9: DIA
A10: MAXI FEST | B10: =SUMIFS('Seg Diario'!Q:Q,'Seg Diario'!D:D,"MAXI FEST") -> 0 | C10: =SUMIFS('Seg Diario'!R:R,'Seg Diario'!D:D,"MAXI FEST") -> 0 | D10: =+B10/C10 -> #DIV/0! | E10: =+B10-C10 -> 0 | F10: =+B10/I10/$J$10 -> 0 | G10: =+C10/I10/$J$10 -> 0 | H10: =+F10-G10 -> 0 | I10: 6 | J10: 9
A11: 10 PDVS | B11: =SUMIFS('Seg Diario'!Q:Q,'Seg Diario'!D:D,"10 TIENDAS EN ENFOQUE") -> 0 | C11: =SUMIFS('Seg Diario'!R:R,'Seg Diario'!D:D,"10 TIENDAS EN ENFOQUE") -> 0 | D11: =+B11/C11 -> #DIV/0! | E11: =+B11-C11 -> 0 | F11: =+B11/I11/$J$10 -> 0 | G11: =+C11/I11/$J$10 -> 0 | H11: =+F11-G11 -> 0 | I11: 10
A12: OPPO | B12: =SUMIFS('Seg Diario'!Q:Q,'Seg Diario'!D:D,"OPPO") -> 0 | C12: =SUMIFS('Seg Diario'!R:R,'Seg Diario'!D:D,"OPPO") -> 0 | D12: =+B12/C12 -> #DIV/0! | E12: =+B12-C12 -> 0 | F12: =+B12/I12/$J$10 -> 0 | G12: =+C12/I12/$J$10 -> 0 | H12: =+F12-G12 -> 0 | I12: 5
A13: MOTOROLA | B13: =SUMIFS('Seg Diario'!Q:Q,'Seg Diario'!D:D,"MOTOROLA") -> 0 | C13: =SUMIFS('Seg Diario'!R:R,'Seg Diario'!D:D,"MOTOROLA") -> 0 | D13: =+B13/C13 -> #DIV/0! | E13: =+B13-C13 -> 0 | F13: =+B13/I13/$J$10 -> 0 | G13: =+C13/I13/$J$10 -> 0 | H13: =+F13-G13 -> 0 | I13: 7
A15: MAXI FEST | B15: altas | C15: cuota | D15: alcance | E15: GAP | F15: produc | G15: obj | H15: gap
A16: altas totales | B16: =+'Seg Diario'!M16 -> 0 | C16: =+'Seg Diario'!N16 -> 2.0482154 | D16: =+B16/C16 -> 0 | E16: =+B16-C16 -> -2.0482154 | F16: =+B16/J16/46 -> 0 | G16: =+C16/J16/J17 -> 0.042671155 | H16: =+F16-G16 -> -0.042671155 | I16: dia | J16: 8
A17: temm | B17: =+'Seg Diario'!Q16 -> 0 | C17: =+'Seg Diario'!R16 -> 0.96380871 | D17: =+B17/C17 -> 0 | E17: =+B17-C17 -> -0.96380871 | F17: =+B17/J16/J17 -> 0 | G17: =+C17/J16/J17 -> 0.020079348 | H17: =+F17-G17 -> -0.020079348 | I17: PDV´s | J17: 6
A18: porta | B18: =+'Seg Diario'!U16 -> 0 | C18: =+'Seg Diario'!V16 -> 0.120598 | D18: =+B18/C18 -> 0 | E18: =+B18-C18 -> -0.120598 | F18: =+B18/J16/J17 -> 0 | G18: =+C18/J16/J17 -> 0.0025124584 | H18: =+F18-G18 -> -0.0025124584
A19: pp voz | B19: =+'Seg Diario'!Y16 -> 0 | C19: =+'Seg Diario'!Z16 -> 0.96380871 | D19: =+B19/C19 -> 0 | E19: =+B19-C19 -> -0.96380871 | F19: =+B19/J16/J17 -> 0 | G19: =+C19/J16/J17 -> 0.020079348 | H19: =+F19-G19 -> -0.020079348
A21: OPPO | B21: altas | C21: cuota | D21: alcance | E21: GAP | F21: produc | G21: obj | H21: gap
A22: altas totales | B22: =+'Seg Diario'!M22 -> 0 | C22: =+'Seg Diario'!N22 -> 1.9105285 | D22: =+B22/C22 -> 0 | E22: =+B22-C22 -> -1.9105285 | F22: =+B22/J22/46 -> 0 | G22: =+C22/J22/J23 -> #DIV/0! | H22: =+F22-G22 -> #DIV/0! | I22: dia | J22: 8
A23: temm | B23: =+'Seg Diario'!Q22 -> 0 | C23: =+'Seg Diario'!R22 -> 1.1014957 | D23: =+B23/C23 -> 0 | E23: =+B23-C23 -> -1.1014957 | F23: =+B23/J22/J23 -> #DIV/0! | G23: =+C23/J22/J23 -> #DIV/0! | H23: =+F23-G23 -> #DIV/0! | I23: PDV´s
A24: porta | B24: =+'Seg Diario'!U22 -> 0 | C24: =+'Seg Diario'!V22 -> 0.120598 | D24: =+B24/C24 -> 0 | E24: =+B24-C24 -> -0.120598 | F24: =+B24/J22/J23 -> #DIV/0! | G24: =+C24/J22/J23 -> #DIV/0! | H24: =+F24-G24 -> #DIV/0!
A25: pp voz | B25: =+'Seg Diario'!Y22 -> 0 | C25: =+'Seg Diario'!Z22 -> 0.68843479 | D25: =+B25/C25 -> 0 | E25: =+B25-C25 -> -0.68843479 | F25: =+B25/J22/J23 -> #DIV/0! | G25: =+C25/J22/J23 -> #DIV/0! | H25: =+F25-G25 -> #DIV/0!
A27: MOTOROLA | B27: altas | C27: cuota | D27: alcance | E27: GAP | F27: produc | G27: obj | H27: gap
A28: altas totales | B28: =+'Seg Diario'!M28 -> 0 | C28: =+'Seg Diario'!N28 -> 4.2341178 | D28: =+B28/C28 -> 0 | E28: =+B28-C28 -> -4.2341178 | F28: =+B28/J28/46 -> 0 | G28: =+C28/J28/J29 -> #DIV/0! | H28: =+F28-G28 -> #DIV/0! | I28: dia | J28: 8
A29: temm | B29: =+'Seg Diario'!Q28 -> 0 | C29: =+'Seg Diario'!R28 -> 2.3235893 | D29: =+B29/C29 -> 0 | E29: =+B29-C29 -> -2.3235893 | F29: =+B29/J28/J29 -> #DIV/0! | G29: =+C29/J28/J29 -> #DIV/0! | H29: =+F29-G29 -> #DIV/0! | I29: PDV´s
A30: porta | B30: =+'Seg Diario'!U28 -> 0 | C30: =+'Seg Diario'!V28 -> 0.241196 | D30: =+B30/C30 -> 0 | E30: =+B30-C30 -> -0.241196 | F30: =+B30/J28/J29 -> #DIV/0! | G30: =+C30/J28/J29 -> #DIV/0! | H30: =+F30-G30 -> #DIV/0!
A31: pp voz | B31: =+'Seg Diario'!Y28 -> 0 | C31: =+'Seg Diario'!Z28 -> 1.6693325 | D31: =+B31/C31 -> 0 | E31: =+B31-C31 -> -1.6693325 | F31: =+B31/J28/J29 -> #DIV/0! | G31: =+C31/J28/J29 -> #DIV/0! | H31: =+F31-G31 -> #DIV/0!
A32: GRAL | B32: TEMM | C32: CUOTA DIA | D32: alcance | E32: GAP | F32: produc | G32: obj | H32: gap
A33: altas totales | B33: =+'Seg Diario'!M33 -> 0 | C33: =+'Seg Diario'!N33 -> 1.7728415 | D33: =+B33/C33 -> 0 | E33: =+B33-C33 -> -1.7728415 | F33: =+B33/J33/46 -> 0 | G33: =+C33/J33/J34 -> 0.0045809858 | H33: =+F33-G33 -> -0.0045809858 | I33: dia | J33: 9
A34: temm | B34: =+'Seg Diario'!Q33 -> 0 | C34: =+'Seg Diario'!R33 -> 0.96380871 | D34: =+B34/C34 -> 0 | E34: =+B34-C34 -> -0.96380871 | F34: =+B34/J33/J34 -> 0 | G34: =+C34/J33/J34 -> 0.0024904618 | H34: =+F34-G34 -> -0.0024904618 | I34: PDV´s | J34: 43
A35: porta | B35: =+'Seg Diario'!U33 -> 0 | C35: =+'Seg Diario'!V33 -> 0.120598 | D35: =+B35/C35 -> 0 | E35: =+B35-C35 -> -0.120598 | F35: =+B35/J33/J34 -> 0 | G35: =+C35/J33/J34 -> 0.00031162274 | H35: =+F35-G35 -> -0.00031162274
A36: pp voz | B36: =+'Seg Diario'!Y33 -> 0 | C36: =+'Seg Diario'!Z33 -> 0.68843479 | D36: =+B36/C36 -> 0 | E36: =+B36-C36 -> -0.68843479 | F36: =+B36/J33/J34 -> 0 | G36: =+C36/J33/J34 -> 0.0017789013 | H36: =+F36-G36 -> -0.0017789013

Sheet Asistencia
I1: Lunes | J1: Martes | K1: Miercoles | L1: Jueves | M1: Viernes | N1: Sabado | O1: Domingo | P1: Lunes | Q1: Martes | R1: Miercoles | S1: Jueves | T1: Viernes | U1: Sabado | V1: Domingo | W1: Lunes | X1: Martes | Y1: Miercoles | Z1: Jueves | AA1: Viernes | AB1: Sabado | AC1: Domingo | AD1: Lunes | AE1: Martes | AF1: Miercoles | AG1: Jueves | AH1: Viernes | AI1: Sabado | AJ1: Domingo | AK1: Lunes | AL1: Martes | AN1: Lunes | AO1: Martes | AP1: Miercoles | AQ1: Jueves | AR1: Viernes | AS1: Sabado | AT1: Domingo | AU1: Lunes | AV1: Martes | AW1: Miercoles | AX1: Jueves | AY1: Viernes | AZ1: Sabado | BA1: Domingo | BB1: Lunes | BC1: Martes | BD1: Miercoles | BE1: Jueves | BF1: Viernes | BG1: Sabado | BH1: Domingo | BI1: Lunes | BJ1: Martes | BK1: Miercoles | BL1: Jueves | BM1: Viernes | BN1: Sabado | BO1: Domingo | BP1: Lunes | BQ1: Martes
D2: =+SUBTOTAL(9,D4:D109) -> 0 | I2: =+SUBTOTAL(9,I4:I109) -> 0 | J2: =+SUBTOTAL(9,J4:J109) -> 0 | K2: =+SUBTOTAL(9,K4:K109) -> 0 | L2: =+SUBTOTAL(9,L4:L109) -> 0 | M2: =+SUBTOTAL(9,M4:M109) -> 0 | N2: =+SUBTOTAL(9,N4:N109) -> 0 | O2: =+SUBTOTAL(9,O4:O109) -> 0 | P2: =+SUBTOTAL(9,P4:P109) -> 0 | ... BR2: =+SUBTOTAL(9,BR4:BR109) -> 0
A3: LIDER | B3: ESTADO | C3: SUPERVISOR | D3: Pos | E3: IDPV | F3: NOMBRE_IDPV | G3: PLAZA | H3: CADENA | I3: 46174 | J3: 46175 | K3: 46176 | L3: 46177 | M3: 46178 | N3: 46179 | O3: 46180 | P3: 46181 | Q3: 46182 | R3: 46183 | S3: 46184 | T3: 46185 | U3: 46186 | V3: 46187 | W3: 46188 | X3: 46189 | Y3: 46190 | Z3: 46191 | AA3: 46192 | AB3: 46193 | AC3: 46194 | AD3: 46195 | AE3: 46196 | AF3: 46197 | AG3: 46198 | AH3: 46199 | AI3: 46200 | AJ3: 46201 | AK3: 46202 | AL3: 46203 | AN3: 46174 | AO3: 46175 | AP3: 46176 | AQ3: 46177 | AR3: 46178 | AS3: 46179 | AT3: 46180 | AU3: 46181 | AV3: 46182 | AW3: 46183 | AX3: 46184 | AY3: 46185 | AZ3: 46186 | BA3: 46187 | BB3: 46188 | BC3: 46189 | BD3: 46190 | BE3: 46191 | BF3: 46192 | BG3: 46193 | BH3: 46194 | BI3: 46195 | BJ3: 46196 | BK3: 46197 | BL3: 46198 | BM3: 46199 | BN3: 46200 | BO3: 46201 | BP3: 46202 | BQ3: 46203
A4: REYES ZARRABAL CRISTOPHER | B4: HIDALGO | C4: DANIEL BENJAMIN MARQUEZ BACA | E4: 2090171 | F4: COPPEL PLAZA DEL VALLE (194) | G4: Pachuca de Soto | H4: COPPEL
A5: REYES ZARRABAL CRISTOPHER | B5: HIDALGO | C5: CESAR GARRIDO BADILLO | E5: 2090172 | F5: COPPEL-CANADA OCAMPO (574) | G5: Pachuca de Soto | H5: COPPEL
A6: CALDERON GRACIAN ISRAEL | B6: TOLUCA | C6: ERIK ALEJANDRO GARCIA | E6: 2090173 | F6: COPPEL PILARES (TOL) (208) | G6: Metepec | H6: COPPEL
A7: SANCHEZ MEZA JOB | B7: TOLUCA | C7: EDGAR RAUL HERNANDEZ CERVANTES | E7: 2090174 | F7: COPPEL-CANADA JUAREZ (582) | G7: Toluca de Lerdo | H7: COPPEL
A8: SANCHEZ MEZA JOB | B8: TOLUCA | C8: EDGAR RAUL HERNANDEZ CERVANTES | E8: 2090175 | F8: COPPEL - JUAREZ II (64) | G8: Toluca de Lerdo | H8: COPPEL
A9: SANCHEZ MEZA JOB | B9: TOLUCA | C9: EDGAR RAUL HERNANDEZ CERVANTES | E9: 2090176 | F9: COPPEL - 5 DE MAYO (159) | G9: Toluca de Lerdo | H9: COPPEL
A10: SANCHEZ MEZA JOB | B10: TOLUCA | C10: EDSON FERREYRA FFLORES | E10: 2090552 | F10: SUBURBIA - METEPEC | G10: Metepec | H10: SUBURBIA
A11: SANCHEZ MEZA JOB | B11: TOLUCA | C11: EDGAR RAUL HERNANDEZ CERVANTES | E11: 2090559 | F11: SUBURBIA - GRAN PLAZA | G11: Toluca de Lerdo | H11: SUBURBIA
A12: REYES ZARRABAL CRISTOPHER | B12: HIDALGO | C12: CESAR GARRIDO BADILLO | E12: 2090618 | F12: COPPEL UNIVERSIDAD | G12: Mineral de La Reforma | H12: COPPEL
A13: SANCHEZ MEZA JOB | B13: TOLUCA | C13: ERIK ALEJANDRO GARCIA | E13: 2090742 | F13: COPPEL SENDERO | G13: Lerma | H13: COPPEL
A14: REYES ZARRABAL CRISTOPHER | B14: HIDALGO | C14: CESAR GARRIDO BADILLO | E14: 2090749 | F14: COPPEL CARRANZA LA COLCHONERA | G14: Pachuca de Soto | H14: COPPEL
A15: SANCHEZ MEZA JOB | B15: TOLUCA | C15: ERIK ALEJANDRO GARCIA | E15: 2090826 | F15: COPPEL CANADA GUADALUPE VICTORIA | G15: Ocoyoacac | H15: COPPEL
... A109: SANCHEZ MEZA JOB | B109: TOLUCA | C109: EDSON FERREYRA FFLORES | E109: 209003847 | F109: MEGA PLAZA MIA SANTIAGO T | G109: Toluca de Lerdo | H109: ELEKTRA

Sheet Cuota
D1: 1 | E1: 2 | F1: 3 | G1: 4 | H1: 5 | I1: 6 | J1: 7 | K1: 8 | L1: 9 | M1: 10 | N1: 11 | O1: 12 | P1: 13 | Q1: 14 | R1: 15 | S1: 16 | T1: 17 | U1: 18 | V1: 19 | W1: 20 | X1: 21 | Y1: 22 | Z1: 23 | AA1: 24 | AB1: 25 | AC1: 26 | AD1: 27 | AE1: 28 | AF1: 29 | AG1: 30 | AH1: 31 | AI1: 32 | AJ1: 33 | AK1: 34 | AL1: 35 | AM1: 36 | AN1: 37 | AO1: 38 | AP1: 39 | AQ1: 40 | AR1: 41 | AS1: 42 | AT1: 43 | AU1: 44 | AV1: 45 | AW1: 46 | AX1: 47 | AY1: 48 | AZ1: 49 | BA1: 50 | BB1: 51 | BC1: 52 | BD1: 53 | BE1: 54 | BF1: 55 | BG1: 56 | BH1: 57 | BI1: 58 | BJ1: 59 | BK1: 60 | BL1: 61 | BM1: 62 | BN1: 63 | BO1: 64 | BP1: 65 | BQ1: 66 | BR1: 67 | BS1: 68 | BT1: 69 | BU1: 70 | BV1: 71 | BW1: 72 | BX1: 73 | BY1: 74 | BZ1: 75 | CA1: 76 | CB1: 77 | CC1: 78 | CD1: 79 | CE1: 80 | CF1: 81 | CG1: 82 | CH1: 83 | CI1: 84 | CJ1: 85 | CK1: 86 | CL1: 87 | CM1: 88 | CN1: 89 | CO1: 90 | CP1: 91 | CQ1: 92 | CR1: 93 | CS1: 94 | CT1: 95 | CU1: 96 | CV1: 97 | CW1: 98 | CX1: 99 | CY1: 100 | CZ1: 101 | DA1: 102 | DB1: 103 | DC1: 104 | DD1: 105 | DE1: 106 | DF1: 107 | DG1: 108 | DH1: 109 | DI1: 110 | DJ1: 111 | DK1: 112 | DL1: 113 | DM1: 114 | DN1: 115 | DO1: 116 | DP1: 117 | DQ1: 118 | DR1: 119 | DS1: 120 | DT1: 121 | DU1: 122
H2: =+H5/$AS$5 -> 0.024385625 | I2: =+I5/$AS$5 -> 0.03395006 | J2: =+J5/$AS$5 -> 0.031588748 | K2: =+K5/$AS$5 -> 0.030344941 | L2: =+L5/$AS$5 -> 0.033109365 | M2: =+M5/$AS$5 -> 0.029811415 | N2: =+N5/$AS$5 -> 0.019015727 | O2: =+O5/$AS$5 -> 0.028200071 | ... AL2: =+AL5/$AS$5 -> 0 | AT2: =+AT5/$CE$5 -> 0.033244311 | AU2: =+AU5/$CE$5 -> 0.027203224 | AV2: =+AV5/$CE$5 -> 0.025575652 | AW2: =+AW5/$CE$5 -> 0.0250467 | AX2: =+AX5/$CE$5 -> 0.028588745 | AY2: =+AY5/$CE$5 -> 0.043860652 | AZ2: =+AZ5/$CE$5 -> 0.058550833 | BA2: =+BA5/$CE$5 -> 0.029753592 | ... BX2: =+BX5/$CE$5 -> 0 | CF2: =+CF5/$DQ$5 -> 0.03287931 | CG2: =+CG5/$DQ$5 -> 0.02815953 | CH2: =+CH5/$DQ$5 -> 0.026445145 | CI2: =+CI5/$DQ$5 -> 0.025845261 | CJ2: =+CJ5/$DQ$5 -> 0.029363323 | CK2: =+CK5/$DQ$5 -> 0.043167329 | CL2: =+CL5/$DQ$5 -> 0.055761946 | CM2: =+CM5/$DQ$5 -> 0.03002118 | ... DJ2: =+DJ5/$DQ$5 -> 0 | DR2: AL DIA (SOLO ACTUALIZAR)
E3: Dia de la semana | H3: Lunes | I3: Martes | J3: Miércoles | K3: Jueves | L3: Viernes | M3: Sábado | N3: Domingo | O3: Lunes | P3: Martes | Q3: Miércoles | R3: Jueves | S3: Viernes | T3: Sábado | U3: Domingo | V3: Lunes | W3: Martes | X3: Miércoles | Y3: Jueves | Z3: Viernes | AA3: Sábado | AB3: Domingo | AC3: Lunes | AD3: Martes | AE3: Miércoles | AF3: Jueves | AG3: Viernes | AH3: Sabado | AI3: Domingo | AJ3: Lunes | AK3: Martes | AT3: Miércoles | AU3: Jueves | AV3: Viernes | AW3: Sábado | AX3: Domingo | AY3: Lunes | AZ3: Martes | BA3: Miércoles | BB3: Jueves | BC3: Viernes | BD3: Sábado | BE3: Domingo | BF3: Lunes | BG3: Martes | BH3: Miércoles | BI3: Jueves | BJ3: Viernes | BK3: Sábado | BL3: Domingo | BM3: Lunes | BN3: Martes | BO3: Miércoles | BP3: Jueves | BQ3: Viernes | BR3: Sábado | BS3: Domingo | BT3: Lunes | BU3: Martes | BV3: Miércoles | BW3: Jueves | BX3: Viernes | CF3: Miércoles | CG3: Jueves | CH3: Viernes | CI3: Sábado | CJ3: Domingo | CK3: Lunes | CL3: Martes | CM3: Miércoles | CN3: Jueves | CO3: Viernes | CP3: Sábado | CQ3: Domingo | CR3: Lunes | CS3: Martes | CT3: Miércoles | CU3: Jueves | CV3: Viernes | CW3: Sábado | CX3: Domingo | CY3: Lunes | CZ3: Martes | DA3: Miércoles | DB3: Jueves | DC3: Viernes | DD3: Sábado | DE3: Domingo | DF3: Lunes | DG3: Martes | DH3: Miércoles | DI3: Jueves | DJ3: Viernes
E4: Cuota acumulada | H4: =+H5 -> 6.63289 | I4: =+H4+I5 -> 15.867306 | J4: =+I4+J5 -> 24.459446 | K4: =+J4+K5 -> 32.71327 | L4: =+K4+L5 -> 41.719017 | M4: =+L4+M5 -> 49.827722 | N4: =+M4+N5 -> 55 | O4: =+N4+O5 -> 62.670419 | P4: =+O4+P5 -> 71.623939 | ... AK4: =+AJ4+AK5 -> 272 | AT4: =+AT5 -> 39.826684 | AU4: =+AT4+AU5 -> 72.416147 | AV4: =+AU4+AV5 -> 103.05578 | AW4: =+AV4+AW5 -> 133.06172 | AX4: =+AW4+AX5 -> 167.31104 | AY4: =+AX4+AY5 -> 219.8561 | AZ4: =+AY4+AZ5 -> 290 | BA4: =+AZ4+BA5 -> 325.6448 | BB4: =+BA4+BB5 -> 355.19364 | ... BX4: =+BW4+BX5 -> 1198 | CF4: =+CF5 -> 79.469291 | CG4: =+CF4+CG5 -> 147.53088 | CH4: =+CG4+CH5 -> 211.44879 | CI4: =+CH4+CI5 -> 273.91679 | CJ4: =+CI4+CJ5 -> 344.88794 | CK4: =+CJ4+CK5 -> 449.22338 | CL4: =+CK4+CL5 -> 584 | CM4: =+CL4+CM5 -> 656.56119 | CN4: =+CM4+CN5 -> 718.79909 | ... DJ4: =+DI4+DJ5 -> 2417
E5: Cuota por dia | H5: =+SUBTOTAL(9,H7:H112) -> 6.63289 | I5: =+SUBTOTAL(9,I7:I112) -> 9.2344162 | J5: =+SUBTOTAL(9,J7:J112) -> 8.5921396 | K5: =+SUBTOTAL(9,K7:K112) -> 8.253824 | L5: =+SUBTOTAL(9,L7:L112) -> 9.0057474 | M5: =+SUBTOTAL(9,M7:M112) -> 8.108705 | N5: =+SUBTOTAL(9,N7:N112) -> 5.1722778 | O5: =+SUBTOTAL(9,O7:O112) -> 7.6704192 | ... DU5: =+SUBTOTAL(9,DU7:DU112) -> 33.009717
A6: LIDER | B6: ESTADO | C6: SUPERVISOR | D6: IDPV | E6: NOMBRE_IDPV | F6: PLAZA | G6: CADENA | H6: 1 porta | I6: 2 porta | J6: 3 porta | K6: 4 porta | L6: 5 porta | M6: 6 porta | N6: 7 porta | O6: 8 porta | P6: 9 porta | Q6: 10 porta | R6: 11 porta | S6: 12 porta | T6: 13 porta | U6: 14 porta | V6: 15 porta | W6: 16 porta | X6: 17 porta | Y6: 18 porta | Z6: 19 porta | AA6: 20 porta | AB6: 21 porta | AC6: 22 porta | AD6: 23 porta | AE6: 24 porta | AF6: 25 porta | AG6: 26 porta | AH6: 27 porta | AI6: 28 porta | AJ6: 29 porta | AK6: 30 porta | AL6: 31 porta | AM6: S 1 - 5 | AN6: S 6 - 12 | AO6: S 13 - 19 | AP6: S 20 - 26 | AQ6: S 27 - 30 | AR6: S | AS6: PORTA | AT6: 1 temm | AU6: 2 temm | AV6: 3 temm | AW6: 4 temm | AX6: 5 temm | AY6: 6 temm | AZ6: 7 temm | BA6: 8 temm | BB6: 9 temm | BC6: 10 temm | BD6: 11 temm | BE6: 12 temm | BF6: 13 temm | BG6: 14 temm | BH6: 15 temm | BI6: 16 temm | BJ6: 17 temm | BK6: 18 temm | BL6: 19 temm | BM6: 20 temm | BN6: 21 temm | BO6: 22 temm | BP6: 23 temm | BQ6: 24 temm | BR6: 25 temm | BS6: 26 temm | BT6: 27 temm | BU6: 28 temm | BV6: 29 temm | BW6: 30 temm | BX6: 31 temm | BY6: S 1 - 52 | BZ6: S 6 - 123 | CA6: S 13 - 194 | CB6: S 20 - 265 | CC6: S 27 - 306 | CD6: S7 | CE6: TEMM | CF6: 1 gral | CG6: 2 gral | CH6: 3 gral | CI6: 4 gral | CJ6: 5 gral | CK6: 6 gral | CL6: 7 gral | CM6: 8 gral | CN6: 9 gral | CO6: 10 gral | CP6: 11 gral | CQ6: 12 gral | CR6: 13 gral | CS6: 14 gral | CT6: 15 gral | CU6: 16 gral | CV6: 17 gral | CW6: 18 gral | CX6: 19 gral | CY6: 20 gral | CZ6: 21 gral | DA6: 22 gral | DB6: 23 gral | DC6: 24 gral | DD6: 25 gral | DE6: 26 gral | DF6: 27 gral | DG6: 28 gral | DH6: 29 gral | DI6: 30 gral | DJ6: 31 gral | DK6: S 1 - 53 | DL6: S 6 - 124 | DM6: S 13 - 195 | DN6: S 20 - 266 | DO6: S 27 - 307 | DP6: S8 | DQ6: PREPAGO | DR6: GRAL | DS6: TEMM14 | DT6: PORTA15 | DU6: PP VOZ
A7: REYES ZARRABAL CRISTOPHER | B7: HIDALGO | C7: DANIEL BENJAMIN MARQUEZ BACA | D7: 2090171 | E7: COPPEL PLAZA DEL VALLE (194) | F7: Pachuca de Soto | G7: COPPEL | H7: 0.241196 | I7: 0.33579695 | J7: 0.31244144 | K7: 0.30013906 | L7: 0.32748172 | M7: 0.294862 | N7: 0.18808283 | O7: 0.26913752 | P7: 0.31415861 | Q7: 0.27333324 | R7: 0.30502428 | S7: 0.3228919 | T7: 0.34035535 | U7: 0.17509911 | V7: 0.27992708 | W7: 0.32816099 | X7: 0.29945373 | Y7: 0.29261705 | Z7: 0.30749537 | AA7: 0.32200675 | AB7: 0.17033904 | AC7: 0.28924212 | AD7: 0.31855761 | AE7: 0.30646963 | AF7: 0.27458904 | AG7: 0.31217939 | AH7: 0.32607529 | AI7: 0.17288692 | AJ7: 0.98121347 | AK7: 1.0187865 | AL7: 0 | AM7: 2 | AN7: 2 | AO7: 2 | AP7: 2 | AQ7: 2 | AR7: 0 | AS7: 10 | AT7: 1.9276174 | AU7: 1.5568627 | AV7: 1.4641982 | AW7: 1.4347796 | AX7: 1.6399162 | AY7: 2.5466431 | AZ7: 3.4299827 | BA7: 1.7173362 | BB7: 1.4101726 | BC7: 1.284791 | BD7: 1.261926 | BE7: 1.7379029 | BF7: 2.8776436 | BG7: 3.7102278 | BH7: 1.9987819 | BI7: 1.5488182 | BJ7: 1.3898206 | BK7: 1.2902258 | BL7: 1.5787361 | BM7: 2.8693738 | BN7: 3.3242437 | BO7: 1.6341138 | BP7: 1.3155649 | BQ7: 1.2208915 | BR7: 1.1652179 | BS7: 1.5229476 | BT7: 2.8324357 | BU7: 3.3088284 | BV7: 2.6939963 | BW7: 2.3060037 | BX7: 0 | BY7: 14 | BZ7: 14 | CA7: 14 | CB7: 13 | CC7: 5 | CD7: 0 | CE7: 60 | CF7: 3.545683 | CG7: 3.0047044 | CH7: 2.8224956 | CI7: 2.7597612 | CJ7: 3.1387667 | CK7: 4.6605359 | CL7: 6.0680532 | CM7: 3.2131424 | CN7: 2.7315974 | CO7: 2.4758321 | CP7: 2.468326 | CQ7: 3.302154 | CR7: 5.2734586 | CS7: 6.5354895 | CT7: 3.5636402 | CU7: 2.872648 | CV7: 2.5827304 | CW7: 2.4122737 | CX7: 2.9011332 | CY7: 5.035978 | CZ7: 5.6315966 | DA7: 3.0546655 | DB7: 2.5448982 | DC7: 2.3725937 | DD7: 2.2464963 | DE7: 2.8894754 | DF7: 5.1194281 | DG7: 5.7724427 | DH7: 4.8371453 | DI7: 4.1628547 | DK7: 26 | DL7: 26 | DM7: 25 | DN7: 24 | DO7: 9 | DQ7: 110 | DR7: =+SUM(Tabla2[[#This Row],[1 gral]:[1 gral]]) -> 3.545683 | DS7: =+SUM(Tabla2[[#This Row],[1 temm]:[1 temm]]) -> 1.9276174 | DT7: =+SUM(Tabla2[[#This Row],[1 porta]:[1 porta]]) -> 0.241196 | DU7: =+Tabla2[[#This Row],[GRAL]]-(Tabla2[[#This Row],[TEMM14]]+Tabla2[[#This Row],[PORTA15]]) -> 1.3768696
A8: REYES ZARRABAL CRISTOPHER | B8: HIDALGO | C8: VIRGINIA MIRANDA OSORIO | D8: 2090172 | E8: COPPEL-CANADA OCAMPO (574) | F8: Pachuca de Soto | G8: COPPEL | H8: 0.241196 | I8: 0.33579695 | J8: 0.31244144 | K8: 0.30013906 | L8: 0.32748172 | M8: 0.294862 | N8: 0.18808283 | O8: 0.26913752 | P8: 0.31415861 | Q8: 0.27333324 | R8: 0.30502428 | S8: 0.3228919 | T8: 0.34035535 | U8: 0.17509911 | V8: 0.27992708 | W8: 0.32816099 | X8: 0.29945373 | Y8: 0.29261705 | Z8: 0.30749537 | AA8: 0.32200675 | AB8: 0.17033904 | AC8: 0.28924212 | AD8: 0.31855761 | AE8: 0.30646963 | AF8: 0.27458904 | AG8: 0.31217939 | AH8: 0.32607529 | AI8: 0.17288692 | AJ8: 0.98121347 | AK8: 1.0187865 | AL8: 0 | AM8: 2 | AN8: 2 | AO8: 2 | AP8: 2 | AQ8: 2 | AR8: 0 | AS8: 10 | AT8: 1.6522435 | AU8: 1.3344537 | AV8: 1.2550271 | AW8: 1.2298111 | AX8: 1.4056425 | AY8: 2.182837 | AZ8: 2.9399852 | BA8: 1.4720024 | BB8: 1.2087194 | BC8: 1.1012494 | BD8: 1.0816509 | BE8: 1.489631 | BF8: 2.4665516 | BG8: 3.1801952 | BH8: 1.5704715 | BI8: 1.2169286 | BJ8: 1.0920019 | BK8: 1.0137488 | BL8: 1.2404355 | BM8: 2.254508 | BN8: 2.6119058 | BO8: 1.3827117 | BP8: 1.1131703 | BQ8: 1.033062 | BR8: 0.98595365 | BS8: 1.288648 | BT8: 2.3966764 | BU8: 2.7997779 | BV8: 1.1016948 | BW8: 0.8983052 | BX8: 0 | BY8: 12 | BZ8: 12 | CA8: 11 | CB8: 11 | CC8: 2 | CD8: 0 | CE8: 48 | CF8: 2.9949352 | CG8: 2.5598865 | CH8: 2.4041532 | CI8: 2.3498242 | CJ8: 2.6702192 | CK8: 3.9329236 | CL8: 5.0880581 | CM8: 2.7224749 | CN8: 2.3286909 | CO8: 2.108749 | CP8: 2.1077757 | CQ8: 2.8056103 | CR8: 4.4512748 | CS8: 5.4754245 | CT8: 2.8497895 | CU8: 2.3194986 | CV8: 2.0863659 | CW8: 1.9514788 | CX8: 2.3372989 | CY8: 4.0112016 | CZ8: 4.4443667 | DA8: 2.5518613 | DB8: 2.140109 | DC8: 1.9969348 | DD8: 1.8879677 | DE8: 2.4208761 | DF8: 4.2479094 | DG8: 4.7543417 | DH8: 3.1846031 | DI8: 2.8153969 | DK8: 22 | DL8: 22 | DM8: 20 | DN8: 20 | DO8: 6 | DQ8: 90 | DR8: =+SUM(Tabla2[[#This Row],[1 gral]:[1 gral]]) -> 2.9949352 | DS8: =+SUM(Tabla2[[#This Row],[1 temm]:[1 temm]]) -> 1.6522435 | DT8: =+SUM(Tabla2[[#This Row],[1 porta]:[1 porta]]) -> 0.241196 | DU8: =+Tabla2[[#This Row],[GRAL]]-(Tabla2[[#This Row],[TEMM14]]+Tabla2[[#This Row],[PORTA15]]) -> 1.1014957
A9: CALDERON GRACIAN ISRAEL | B9: TOLUCA | C9: ERIK ALEJANDRO GARCIA | D9: 2090173 | E9: COPPEL PILARES (TOL) (208) | F9: Metepec | G9: COPPEL | H9: 0 | I9: 0 | J9: 0 | K9: 0 | L9: 0 | M9: 0 | N9: 0 | O9: 0 | P9: 0 | Q9: 0 | R9: 0 | S9: 0 | T9: 0 | U9: 0 | V9: 0 | W9: 0 | X9: 0 | Y9: 0 | Z9: 0 | AA9: 0 | AB9: 0 | AC9: 0 | AD9: 0 | AE9: 0 | AF9: 0 | AG9: 0 | AH9: 0 | AI9: 0 | AJ9: 0.98121347 | AK9: 1.0187865 | AL9: 0 | AM9: 0 | AN9: 0 | AO9: 0 | AP9: 0 | AQ9: 2 | AR9: 0 | AS9: 2 | AT9: 0.96380871 | AU9: 0.77843134 | AV9: 0.73209912 | AW9: 0.71738981 | AX9: 0.81995811 | AY9: 1.2733216 | AZ9: 1.7149913 | BA9: 0.85866808 | BB9: 0.7050863 | BC9: 0.6423955 | BD9: 0.63096301 | BE9: 0.86895144 | BF9: 1.4388218 | BG9: 1.8551139 | BH9: 0.85662081 | BI9: 0.66377922 | BJ9: 0.59563738 | BK9: 0.5529539 | BL9: 0.67660118 | BM9: 1.2297316 | BN9: 1.4246759 | BO9: 0.75420638 | BP9: 0.6071838 | BQ9: 0.56348839 | BR9: 0.5377929 | BS9: 0.70289891 | BT9: 1.307278 | BU9: 1.5271516 | BV9: 0.5508474 | BW9: 0.4491526 | BX9: 0 | BY9: 7 | BZ9: 7 | CA9: 6 | CB9: 6 | CC9: 1 | CD9: 0 | CE9: 27 | CF9: 1.6522435 | CG9: 1.3344537 | CH9: 1.2550271 | CI9: 1.2298111 | CJ9: 1.4056425 | CK9: 2.182837 | CL9: 2.9399852 | CM9: 1.4720024 | CN9: 1.2087194 | CO9: 1.1012494 | CP9: 1.0816509 | CQ9: 1.489631 | CR9: 2.4665516 | CS9: 3.1801952 | CT9: 1.5704715 | CU9: 1.2169286 | CV9: 1.0920019 | CW9: 1.0137488 | CX9: 1.2404355 | CY9: 2.254508 | CZ9: 2.6119058 | DA9: 1.3827117 | DB9: 1.1131703 | DC9: 1.033062 | DD9: 0.98595365 | DE9: 1.288648 | DF9: 2.3966764 | DG9: 2.7997779 | DH9: 1.5320609 | DI9: 1.4679391 | DK9: 12 | DL9: 12 | DM9: 11 | DN9: 11 | DO9: 3 | DQ9: 49 | DR9: =+SUM(Tabla2[[#This Row],[1 gral]:[1 gral]]) -> 1.6522435 | DS9: =+SUM(Tabla2[[#This Row],[1 temm]:[1 temm]]) -> 0.96380871 | DT9: =+SUM(Tabla2[[#This Row],[1 porta]:[1 porta]]) -> 0 | DU9: =+Tabla2[[#This Row],[GRAL]]-(Tabla2[[#This Row],[TEMM14]]+Tabla2[[#This Row],[PORTA15]]) -> 0.68843479
A10: SANCHEZ MEZA JOB | B10: TOLUCA | C10: EDGAR RAUL HERNANDEZ CERVANTES | D10: 2090174 | E10: COPPEL-CANADA JUAREZ (582) | F10: Toluca de Lerdo | G10: COPPEL | H10: 0.120598 | I10: 0.16789848 | J10: 0.15622072 | K10: 0.15006953 | L10: 0.16374086 | M10: 0.147431 | N10: 0.094041414 | O10: 0.13456876 | P10: 0.1570793 | Q10: 0.13666662 | R10: 0.15251214 | S10: 0.16144595 | T10: 0.17017768 | U10: 0.087549554 | V10: 0.13996354 | W10: 0.16408049 | X10: 0.14972686 | Y10: 0.14630852 | Z10: 0.15374769 | AA10: 0.16100337 | AB10: 0.085169521 | AC10: 0.14462106 | AD10: 0.1592788 | AE10: 0.15323481 | AF10: 0.13729452 | AG10: 0.1560897 | AH10: 0.16303765 | AI10: 0.086443459 | AJ10: 0 | AK10: 0 | AL10: 0 | AM10: 1 | AN10: 1 | AO10: 1 | AP10: 1 | AQ10: 0 | AR10: 0 | AS10: 4 | AT10: 0.96380871 | AU10: 0.77843134 | AV10: 0.73209912 | AW10: 0.71738981 | AX10: 0.81995811 | AY10: 1.2733216 | AZ10: 1.7149913 | BA10: 0.85866808 | BB10: 0.7050863 | BC10: 0.6423955 | BD10: 0.63096301 | BE10: 0.86895144 | BF10: 1.4388218 | BG10: 1.8551139 | BH10: 0.99939094 | BI10: 0.77440909 | BJ10: 0.69491028 | BK10: 0.64511289 | BL10: 0.78936805 | BM10: 1.4346869 | BN10: 1.6621219 | BO10: 0.87990745 | BP10: 0.7083811 | BQ10: 0.65740312 | BR10: 0.62742505 | BS10: 0.82004872 | BT10: 1.5251577 | BU10: 1.7816769 | BV10: 0.5508474 | BW10: 0.4491526 | BX10: 0 | BY10: 7 | BZ10: 7 | CA10: 7 | CB10: 7 | CC10: 1 | CD10: 0 | CE10: 29 | CF10: 1.7728415 | CG10: 1.5023522 | CH10: 1.4112478 | CI10: 1.3798806 | CJ10: 1.5693833 | CK10: 2.330268 | CL10: 3.0340266 | CM10: 1.6065712 | CN10: 1.3657987 | CO10: 1.237916 | CP10: 1.234163 | CQ10: 1.651077 | CR10: 2.6367293 | CS10: 3.2677448 | CT10: 1.8532052 | CU10: 1.4916389 | CV10: 1.3410016 | CW10: 1.2522163 | CX10: 1.5069501 | CY10: 2.6204666 | CZ10: 2.9345213 | DA10: 1.6530338 | DB10: 1.3736464 | DC10: 1.2802116 | DD10: 1.2128803 | DE10: 1.5618875 | DF10: 2.7775937 | DG10: 3.1407466 | DH10: 1.6525422 | DI10: 1.3474578 | DK10: 13 | DL10: 13 | DM10: 13 | DN10: 13 | DO10: 3 | DQ10: 55 | DR10: =+SUM(Tabla2[[#This Row],[1 gral]:[1 gral]]) -> 1.7728415 | DS10: =+SUM(Tabla2[[#This Row],[1 temm]:[1 temm]]) -> 0.96380871 | DT10: =+SUM(Tabla2[[#This Row],[1 porta]:[1 porta]]) -> 0.120598 | DU10: =+Tabla2[[#This Row],[GRAL]]-(Tabla2[[#This Row],[TEMM14]]+Tabla2[[#This Row],[PORTA15]]) -> 0.68843479
A11: SANCHEZ MEZA JOB | B11: TOLUCA | C11: EDGAR RAUL HERNANDEZ CERVANTES | D11: 2090175 | E11: COPPEL - JUAREZ II (64) | F11: Toluca de Lerdo | G11: COPPEL | H11: 0.241196 | I11: 0.33579695 | J11: 0.31244144 | K11: 0.30013906 | L11: 0.32748172 | M11: 0.294862 | N11: 0.18808283 | O11: 0.26913752 | P11: 0.31415861 | Q11: 0.27333324 | R11: 0.30502428 | S11: 0.3228919 | T11: 0.34035535 | U11: 0.17509911 | V11: 0.27992708 | W11: 0.32816099 | X11: 0.29945373 | Y11: 0.29261705 | Z11: 0.30749537 | AA11: 0.32200675 | AB11: 0.17033904 | AC11: 0.28924212 | AD11: 0.31855761 | AE11: 0.30646963 | AF11: 0.27458904 | AG11: 0.31217939 | AH11: 0.32607529 | AI11: 0.17288692 | AJ11: 0.98121347 | AK11: 1.0187865 | AL11: 0 | AM11: 2 | AN11: 2 | AO11: 2 | AP11: 2 | AQ11: 2 | AR11: 0 | AS11: 10 | AT11: 2.6160522 | AU11: 2.1128851 | AV11: 1.9871262 | AW11: 1.9472009 | AX11: 2.2256006 | AY11: 3.4561585 | AZ11: 4.6549765 | BA11: 2.3306705 | BB11: 1.9138057 | BC11: 1.7436449 | BD11: 1.7126139 | BE11: 2.3585825 | BF11: 3.9053734 | BG11: 5.0353091 | BH11: 2.5698624 | BI11: 1.9913377 | BJ11: 1.7869121 | BK11: 1.6588617 | BL11: 2.0298036 | BM11: 3.6891949 | BN11: 4.2740277 | BO11: 2.2626192 | BP11: 1.8215514 | BQ11: 1.6904652 | BR11: 1.6133787 | BS11: 2.1086967 | BT11: 3.9218341 | BU11: 4.5814548 | BV11: 2.754237 | BW11: 2.245763 | BX11: 0 | BY11: 19 | BZ11: 19 | CA11: 18 | CB11: 18 | CC11: 5 | CD11: 0 | CE11: 79 | CF11: 4.0964308 | CG11: 3.4495223 | CH11: 3.2408379 | CI11: 3.1696983 | CJ11: 3.6073141 | CK11: 5.3881483 | CL11: 7.0480482 | CM11: 3.7038098 | CN11: 3.1345038 | CO11: 2.8429152 | CP11: 2.8288763 | CQ11: 3.7986977 | CR11: 6.0956425 | CS11: 7.5955546 | CT11: 3.9919506 | CU11: 3.2045376 | CV11: 2.8805491 | CW11: 2.6887506 | CX11: 3.2394338 | CY11: 5.6508438 | CZ11: 6.3439345 | DA11: 3.5574698 | DB11: 2.9496874 | DC11: 2.7482527 | DD11: 2.6050249 | DE11: 3.3580747 | DF11: 5.9909468 | DG11: 6.7905438 | DH11: 4.2862979 | DI11: 3.7137021 | DK11: 30 | DL11: 30 | DM11: 28 | DN11: 28 | DO11: 8 | DQ11: 124 | DR11: =+SUM(Tabla2[[#This Row],[1 gral]:[1 gral]]) -> 4.0964308 | DS11: =+SUM(Tabla2[[#This Row],[1 temm]:[1 temm]]) -> 2.6160522 | DT11: =+SUM(Tabla2[[#This Row],[1 porta]:[1 porta]]) -> 0.241196 | DU11: =+Tabla2[[#This Row],[GRAL]]-(Tabla2[[#This Row],[TEMM14]]+Tabla2[[#This Row],[PORTA15]]) -> 1.2391826
A12: SANCHEZ MEZA JOB | B12: TOLUCA | C12: EDGAR RAUL HERNANDEZ CERVANTES | D12: 2090176 | E12: COPPEL - 5 DE MAYO (159) | F12: Toluca de Lerdo | G12: COPPEL | H12: 0.120598 | I12: 0.16789848 | J12: 0.15622072 | K12: 0.15006953 | L12: 0.16374086 | M12: 0.147431 | N12: 0.094041414 | O12: 0.13456876 | P12: 0.1570793 | Q12: 0.13666662 | R12: 0.15251214 | S12: 0.16144595 | T12: 0.17017768 | U12: 0.087549554 | V12: 0.13996354 | W12: 0.16408049 | X12: 0.14972686 | Y12: 0.14630852 | Z12: 0.15374769 | AA12: 0.16100337 | AB12: 0.085169521 | AC12: 0.14462106 | AD12: 0.1592788 | AE12: 0.15323481 | AF12: 0.13729452 | AG12: 0.1560897 | AH12: 0.16303765 | AI12: 0.086443459 | AJ12: 0.98121347 | AK12: 1.0187865 | AL12: 0 | AM12: 1 | AN12: 1 | AO12: 1 | AP12: 1 | AQ12: 2 | AR12: 0 | AS12: 6 | AT12: 3.8552348 | AU12: 3.1137254 | AV12: 2.9283965 | AW12: 2.8695592 | AX12: 3.2798324 | AY12: 5.0932863 | AZ12: 6.8599654 | BA12: 3.4346723 | BB12: 2.8203452 | BC12: 2.569582 | BD12: 2.523852 | BE12: 3.4758058 | BF12: 5.7552872 | BG12: 7.4204555 | BH12: 3.7120235 | BI12: 2.8763766 | BJ12: 2.5810953 | BK12: 2.3961336 | BL12: 2.9319385 | BM12: 5.328837 | BN12: 6.1735955 | BO12: 3.2682277 | BP12: 2.6311298 | BQ12: 2.441783 | BR12: 2.3304359 | BS12: 3.0458953 | BT12: 5.6648715 | BU12: 6.6176569 | BV12: 3.3050844 | BW12: 2.6949156 | BX12: 0 | BY12: 28 | BZ12: 28 | CA12: 26 | CB12: 26 | CC12: 6 | CD12: 0 | CE12: 114 | CF12: 4.8019546 | CG12: 3.9488507 | CH12: 3.7121307 | CI12: 3.6345343 | CJ12: 4.1463945 | CK12: 6.3321358 | CL12: 8.4239994 | CM12: 4.3052423 | CN12: 3.5817842 | CO12: 3.2568733 | CP12: 3.2171896 | CQ12: 4.3820672 | CR12: 7.1587407 | CS12: 9.0981027 | CT12: 4.7086078 | CU12: 3.7042363 | CV12: 3.3264596 | CW12: 3.095396 | CX12: 3.7622873 | CY12: 6.719572 | CZ12: 7.6834409 | DA12: 4.1670551 | DB12: 3.3975924 | DC12: 3.1585062 | DD12: 3.0055233 | DE12: 3.9048839 | DF12: 7.1351872 | DG12: 8.2312519 | DH12: 4.8371453 | DI12: 4.1628547 | DK12: 35 | DL12: 35 | DM12: 33 | DN12: 33 | DO12: 9 | DQ12: 145 | DR12: =+SUM(Tabla2[[#This Row],[1 gral]:[1 gral]]) -> 4.8019546 | DS12: =+SUM(Tabla2[[#This Row],[1 temm]:[1 temm]]) -> 3.8552348 | DT12: =+SUM(Tabla2[[#This Row],[1 porta]:[1 porta]]) -> 0.120598 | DU12: =+Tabla2[[#This Row],[GRAL]]-(Tabla2[[#This Row],[TEMM14]]+Tabla2[[#This Row],[PORTA15]]) -> 0.82612175
A13: SANCHEZ MEZA JOB | B13: TOLUCA | C13: EDSON FERREYRA FFLORES | D13: 2090552 | E13: SUBURBIA - METEPEC | F13: Metepec | G13: SUBURBIA | H13: 0.120598 | I13: 0.16789848 | J13: 0.15622072 | K13: 0.15006953 | L13: 0.16374086 | M13: 0.147431 | N13: 0.094041414 | O13: 0.13456876 | P13: 0.1570793 | Q13: 0.13666662 | R13: 0.15251214 | S13: 0.16144595 | T13: 0.17017768 | U13: 0.087549554 | V13: 0.13996354 | W13: 0.16408049 | X13: 0.14972686 | Y13: 0.14630852 | Z13: 0.15374769 | AA13: 0.16100337 | AB13: 0.085169521 | AC13: 0.14462106 | AD13: 0.1592788 | AE13: 0.15323481 | AF13: 0.13729452 | AG13: 0.1560897 | AH13: 0.16303765 | AI13: 0.086443459 | AJ13: 0.49060674 | AK13: 0.50939326 | AL13: 0 | AM13: 1 | AN13: 1 | AO13: 1 | AP13: 1 | AQ13: 1 | AR13: 0 | AS13: 5 | AT13: 1.3768696 | AU13: 1.1120448 | AV13: 1.0458559 | AW13: 1.0248426 | AX13: 1.1713687 | AY13: 1.8190308 | AZ13: 2.4499876 | BA13: 1.2266687 | BB13: 1.0072661 | BC13: 0.91770786 | BD13: 0.90137573 | BE13: 1.2413592 | BF13: 2.0554597 | BG13: 2.6501627 | BH13: 1.2849312 | BI13: 0.99566883 | BJ13: 0.89345607 | BK13: 0.82943085 | BL13: 1.0149018 | BM13: 1.8445974 | BN13: 2.1370138 | BO13: 1.1313096 | BP13: 0.9107757 | BQ13: 0.84523258 | BR13: 0.80668935 | BS13: 1.0543484 | BT13: 1.9609171 | BU13: 2.2907274 | BV13: 0.5508474 | BW13: 0.4491526 | BX13: 0 | BY13: 10 | BZ13: 10 | CA13: 9 | CB13: 9 | CC13: 1 | CD13: 0 | CE13: 39 | CF13: 1.7728415 | CG13: 1.5023522 | CH13: 1.4112478 | CI13: 1.3798806 | CJ13: 1.5693833 | CK13: 2.330268 | CL13: 3.0340266 | CM13: 1.6065712 | CN13: 1.3657987 | CO13: 1.237916 | CP13: 1.234163 | CQ13: 1.651077 | CR13: 2.6367293 | CS13: 3.2677448 | CT13: 1.710435 | CU13: 1.3810091 | CV13: 1.2417287 | CW13: 1.1600573 | CX13: 1.3941832 | CY13: 2.4155113 | CZ13: 2.6970753 | DA13: 1.5273328 | DB13: 1.2724491 | DC13: 1.1862969 | DD13: 1.1232482 | DE13: 1.4447377 | DF13: 2.559714 | DG13: 2.8862214 | DH13: 1.5923015 | DI13: 1.4076985 | DK13: 13 | DL13: 13 | DM13: 12 | DN13: 12 | DO13: 3 | DQ13: 53 | DR13: =+SUM(Tabla2[[#This Row],[1 gral]:[1 gral]]) -> 1.7728415 | DS13: =+SUM(Tabla2[[#This Row],[1 temm]:[1 temm]]) -> 1.3768696 | DT13: =+SUM(Tabla2[[#This Row],[1 porta]:[1 porta]]) -> 0.120598 | DU13: =+Tabla2[[#This Row],[GRAL]]-(Tabla2[[#This Row],[TEMM14]]+Tabla2[[#This Row],[PORTA15]]) -> 0.27537392
A14: SANCHEZ MEZA JOB | B14: TOLUCA | C14: EDGAR RAUL HERNANDEZ CERVANTES | D14: 2090559 | E14: SUBURBIA - GRAN PLAZA | F14: Toluca de Lerdo | G14: SUBURBIA | H14: 0.120598 | I14: 0.16789848 | J14: 0.15622072 | K14: 0.15006953 | L14: 0.16374086 | M14: 0.147431 | N14: 0.094041414 | O14: 0.13456876 | P14: 0.1570793 | Q14: 0.13666662 | R14: 0.15251214 | S14: 0.16144595 | T14: 0.17017768 | U14: 0.087549554 | V14: 0.13996354 | W14: 0.16408049 | X14: 0.14972686 | Y14: 0.14630852 | Z14: 0.15374769 | AA14: 0.16100337 | AB14: 0.085169521 | AC14: 0.14462106 | AD14: 0.1592788 | AE14: 0.15323481 | AF14: 0.13729452 | AG14: 0.1560897 | AH14: 0.16303765 | AI14: 0.086443459 | AJ14: 0 | AK14: 0 | AL14: 0 | AM14: 1 | AN14: 1 | AO14: 1 | AP14: 1 | AQ14: 0 | AR14: 0 | AS14: 4 | AT14: 1.1014957 | AU14: 0.88963582 | AV14: 0.83668471 | AW14: 0.81987406 | AX14: 0.93709498 | AY14: 1.4552246 | AZ14: 1.9599901 | BA14: 0.98133495 | BB14: 0.80581292 | BC14: 0.73416629 | BD14: 0.72110058 | BE14: 0.99308736 | BF14: 1.6443678 | BG14: 2.1201301 | BH14: 0.99939094 | BI14: 0.77440909 | BJ14: 0.69491028 | BK14: 0.64511289 | BL14: 0.78936805 | BM14: 1.4346869 | BN14: 1.6621219 | BO14: 0.87990745 | BP14: 0.7083811 | BQ14: 0.65740312 | BR14: 0.62742505 | BS14: 0.82004872 | BT14: 1.5251577 | BU14: 1.7816769 | BV14: 0.5508474 | BW14: 0.4491526 | BX14: 0 | BY14: 8 | BZ14: 8 | CA14: 7 | CB14: 7 | CC14: 1 | CD14: 0 | CE14: 31 | CF14: 1.9105285 | CG14: 1.6135567 | CH14: 1.5158334 | CI14: 1.4823649 | CJ14: 1.6865202 | CK14: 2.5121711 | CL14: 3.2790253 | CM14: 1.729238 | CN14: 1.4665253 | CO14: 1.3296868 | CP14: 1.3243006 | CQ14: 1.7752129 | CR14: 2.8422753 | CS14: 3.532761 | CT14: 1.710435 | CU14: 1.3810091 | CV14: 1.2417287 | CW14: 1.1600573 | CX14: 1.3941832 | CY14: 2.4155113 | CZ14: 2.6970753 | DA14: 1.5273328 | DB14: 1.2724491 | DC14: 1.1862969 | DD14: 1.1232482 | DE14: 1.4447377 | DF14: 2.559714 | DG14: 2.8862214 | DH14: 1.1016948 | DI14: 0.8983052 | DK14: 14 | DL14: 14 | DM14: 12 | DN14: 12 | DO14: 2 | DQ14: 54 | DR14: =+SUM(Tabla2[[#This Row],[1 gral]:[1 gral]]) -> 1.9105285 | DS14: =+SUM(Tabla2[[#This Row],[1 temm]:[1 temm]]) -> 1.1014957 | DT14: =+SUM(Tabla2[[#This Row],[1 porta]:[1 porta]]) -> 0.120598 | DU14: =+Tabla2[[#This Row],[GRAL]]-(Tabla2[[#This Row],[TEMM14]]+Tabla2[[#This Row],[PORTA15]]) -> 0.68843479
A15: REYES ZARRABAL CRISTOPHER | B15: HIDALGO | C15: VIRGINIA MIRANDA OSORIO | D15: 2090618 | E15: COPPEL UNIVERSIDAD | F15: Mineral de La Reforma | G15: COPPEL | H15: 0.120598 | I15: 0.16789848 | J15: 0.15622072 | K15: 0.15006953 | L15: 0.16374086 | M15: 0.147431 | N15: 0.094041414 | O15: 0.13456876 | P15: 0.1570793 | Q15: 0.13666662 | R15: 0.15251214 | S15: 0.16144595 | T15: 0.17017768 | U15: 0.087549554 | V15: 0.13996354 | W15: 0.16408049 | X15: 0.14972686 | Y15: 0.14630852 | Z15: 0.15374769 | AA15: 0.16100337 | AB15: 0.085169521 | AC15: 0.14462106 | AD15: 0.1592788 | AE15: 0.15323481 | AF15: 0.13729452 | AG15: 0.1560897 | AH15: 0.16303765 | AI15: 0.086443459 | AJ15: 0.49060674 | AK15: 0.50939326 | AL15: 0 | AM15: 1 | AN15: 1 | AO15: 1 | AP15: 1 | AQ15: 1 | AR15: 0 | AS15: 5 | AT15: 1.1014957 | AU15: 0.88963582 | AV15: 0.83668471 | AW15: 0.81987406 | AX15: 0.93709498 | AY15: 1.4552246 | AZ15: 1.9599901 | BA15: 0.98133495 | BB15: 0.80581292 | BC15: 0.73416629 | BD15: 0.72110058 | BE15: 0.99308736 | BF15: 1.6443678 | BG15: 2.1201301 | BH15: 0.99939094 | BI15: 0.77440909 | BJ15: 0.69491028 | BK15: 0.64511289 | BL15: 0.78936805 | BM15: 1.4346869 | BN15: 1.6621219 | BO15: 0.87990745 | BP15: 0.7083811 | BQ15: 0.65740312 | BR15: 0.62742505 | BS15: 0.82004872 | BT15: 1.5251577 | BU15: 1.7816769 | BV15: 1.1016948 | BW15: 0.8983052 | BX15: 0 | BY15: 8 | BZ15: 8 | CA15: 7 | CB15: 7 | CC15: 2 | CD15: 0 | CE15: 32 | CF15: 2.3235893 | CG15: 1.9471701 | CH15: 1.8295901 | CI15: 1.7898177 | CJ15: 2.0379308 | CK15: 3.0578803 | CL15: 4.0140216 | CM15: 2.0972387 | CN15: 1.7687051 | CO15: 1.6049992 | CP15: 1.5947133 | CQ15: 2.1476207 | CR15: 3.4589132 | CS15: 4.3278098 | CT15: 2.2815156 | CU15: 1.8235285 | CV15: 1.6388203 | CW15: 1.5286933 | CX15: 1.8452506 | CY15: 3.2353324 | CZ15: 3.6468592 | DA15: 1.904436 | DB15: 1.576041 | DC15: 1.4680411 | DD15: 1.3921446 | DE15: 1.7961871 | DF15: 3.2133531 | DG15: 3.6497972 | DH15: 2.6939963 | DI15: 2.3060037 | DK15: 17 | DL15: 17 | DM15: 16 | DN15: 15 | DO15: 5 | DQ15: 70 | DR15: =+SUM(Tabla2[[#This Row],[1 gral]:[1 gral]]) -> 2.3235893 | DS15: =+SUM(Tabla2[[#This Row],[1 temm]:[1 temm]]) -> 1.1014957 | DT15: =+SUM(Tabla2[[#This Row],[1 porta]:[1 porta]]) -> 0.120598 | DU15: =+Tabla2[[#This Row],[GRAL]]-(Tabla2[[#This Row],[TEMM14]]+Tabla2[[#This Row],[PORTA15]]) -> 1.1014957
A16: SANCHEZ MEZA JOB | B16: TOLUCA | C16: ERIK ALEJANDRO GARCIA | D16: 2090742 | E16: COPPEL SENDERO | F16: Lerma | G16: COPPEL | H16: 0.241196 | I16: 0.33579695 | J16: 0.31244144 | K16: 0.30013906 | L16: 0.32748172 | M16: 0.294862 | N16: 0.18808283 | O16: 0.26913752 | P16: 0.31415861 | Q16: 0.27333324 | R16: 0.30502428 | S16: 0.3228919 | T16: 0.34035535 | U16: 0.17509911 | V16: 0.27992708 | W16: 0.32816099 | X16: 0.29945373 | Y16: 0.29261705 | Z16: 0.30749537 | AA16: 0.32200675 | AB16: 0.17033904 | AC16: 0.28924212 | AD16: 0.31855761 | AE16: 0.30646963 | AF16: 0.27458904 | AG16: 0.31217939 | AH16: 0.32607529 | AI16: 0.17288692 | AJ16: 0.98121347 | AK16: 1.0187865 | AL16: 0 | AM16: 2 | AN16: 2 | AO16: 2 | AP16: 2 | AQ16: 2 | AR16: 0 | AS16: 10 | AT16: 2.4783653 | AU16: 2.0016806 | AV16: 1.8825406 | AW16: 1.8447166 | AX16: 2.1084637 | AY16: 3.2742555 | AZ16: 4.4099778 | BA16: 2.2080036 | BB16: 1.8130791 | BC16: 1.6518741 | BD16: 1.6224763 | BE16: 2.2344466 | BF16: 3.6998275 | BG16: 4.7702928 | BH16: 2.4270923 | BI16: 1.8807078 | BJ16: 1.6876393 | BK16: 1.5667027 | BL16: 1.9170367 | BM16: 3.4842396 | BN16: 4.0365817 | BO16: 2.1369181 | BP16: 1.7203541 | BQ16: 1.5965504 | BR16: 1.5237465 | BS16: 1.9915469 | BT16: 3.7039544 | BU16: 4.3269295 | BV16: 2.754237 | BW16: 2.245763 | BX16: 0 | BY16: 18 | BZ16: 18 | CA16: 17 | CB16: 17 | CC16: 5 | CD16: 0 | CE16: 75 | CF16: 3.9587439 | CG16: 3.3383178 | CH16: 3.1362523 | CI16: 3.067214 | CJ16: 3.4901773 | CK16: 5.2062452 | CL16: 6.8030495 | CM16: 3.581143 | CN16: 3.0337772 | CO16: 2.7511445 | CP16: 2.7387387 | CQ16: 3.6745617 | CR16: 5.8900966 | CS16: 7.3305383 | CT16: 3.9919506 | CU16: 3.2045376 | CV16: 2.8805491 | CW16: 2.6887506 | CX16: 3.2394338 | CY16: 5.6508438 | CZ16: 6.3439345 | DA16: 3.5574698 | DB16: 2.9496874 | DC16: 2.7482527 | DD16: 2.6050249 | DE16: 3.3580747 | DF16: 5.9909468 | DG16: 6.7905438 | DH16: 4.8371453 | DI16: 4.1628547 | DK16: 29 | DL16: 29 | DM16: 28 | DN16: 28 | DO16: 9 | DQ16: 123 | DR16: =+SUM(Tabla2[[#This Row],[1 gral]:[1 gral]]) -> 3.9587439 | DS16: =+SUM(Tabla2[[#This Row],[1 temm]:[1 temm]]) -> 2.4783653 | DT16: =+SUM(Tabla2[[#This Row],[1 porta]:[1 porta]]) -> 0.241196 | DU16: =+Tabla2[[#This Row],[GRAL]]-(Tabla2[[#This Row],[TEMM14]]+Tabla2[[#This Row],[PORTA15]]) -> 1.2391826
A17: REYES ZARRABAL CRISTOPHER | B17: HIDALGO | C17: VIRGINIA MIRANDA OSORIO | D17: 2090749 | E17: COPPEL CARRANZA LA COLCHONERA | F17: Pachuca de Soto | G17: COPPEL | H17: 0.120598 | I17: 0.16789848 | J17: 0.15622072 | K17: 0.15006953 | L17: 0.16374086 | M17: 0.147431 | N17: 0.094041414 | O17: 0.13456876 | P17: 0.1570793 | Q17: 0.13666662 | R17: 0.15251214 | S17: 0.16144595 | T17: 0.17017768 | U17: 0.087549554 | V17: 0.13996354 | W17: 0.16408049 | X17: 0.14972686 | Y17: 0.14630852 | Z17: 0.15374769 | AA17: 0.16100337 | AB17: 0.085169521 | AC17: 0.14462106 | AD17: 0.1592788 | AE17: 0.15323481 | AF17: 0.13729452 | AG17: 0.1560897 | AH17: 0.16303765 | AI17: 0.086443459 | AJ17: 0.49060674 | AK17: 0.50939326 | AL17: 0 | AM17: 1 | AN17: 1 | AO17: 1 | AP17: 1 | AQ17: 1 | AR17: 0 | AS17: 5 | AT17: 0.96380871 | AU17: 0.77843134 | AV17: 0.73209912 | AW17: 0.71738981 | AX17: 0.81995811 | AY17: 1.2733216 | AZ17: 1.7149913 | BA17: 0.85866808 | BB17: 0.7050863 | BC17: 0.6423955 | BD17: 0.63096301 | BE17: 0.86895144 | BF17: 1.4388218 | BG17: 1.8551139 | BH17: 0.85662081 | BI17: 0.66377922 | BJ17: 0.59563738 | BK17: 0.5529539 | BL17: 0.67660118 | BM17: 1.2297316 | BN17: 1.4246759 | BO17: 0.75420638 | BP17: 0.6071838 | BQ17: 0.56348839 | BR17: 0.5377929 | BS17: 0.70289891 | BT17: 1.307278 | BU17: 1.5271516 | BV17: 1.1016948 | BW17: 0.8983052 | BX17: 0 | BY17: 7 | BZ17: 7 | CA17: 6 | CB17: 6 | CC17: 2 | CD17: 0 | CE17: 28 | CF17: 2.0482154 | CG17: 1.7247612 | CH17: 1.620419 | CI17: 1.5848491 | CJ17: 1.8036571 | CK17: 2.6940741 | CL17: 3.5240241 | CM17: 1.8519049 | CN17: 1.5672519 | CO17: 1.4214576 | CP17: 1.4144382 | CQ17: 1.8993488 | CR17: 3.0478213 | CS17: 3.7977773 | CT17: 1.8532052 | CU17: 1.4916389 | CV17: 1.3410016 | CW17: 1.2522163 | CX17: 1.5069501 | CY17: 2.6204666 | CZ17: 2.9345213 | DA17: 1.6530338 | DB17: 1.3736464 | DC17: 1.2802116 | DD17: 1.2128803 | DE17: 1.5618875 | DF17: 2.7775937 | DG17: 3.1407466 | DH17: 2.1431489 | DI17: 1.8568511 | DK17: 15 | DL17: 15 | DM17: 13 | DN17: 13 | DO17: 4 | DQ17: 60 | DR17: =+SUM(Tabla2[[#This Row],[1 gral]:[1 gral]]) -> 2.0482154 | DS17: =+SUM(Tabla2[[#This Row],[1 temm]:[1 temm]]) -> 0.96380871 | DT17: =+SUM(Tabla2[[#This Row],[1 porta]:[1 porta]]) -> 0.120598 | DU17: =+Tabla2[[#This Row],[GRAL]]-(Tabla2[[#This Row],[TEMM14]]+Tabla2[[#This Row],[PORTA15]]) -> 0.96380871
A18: SANCHEZ MEZA JOB | B18: TOLUCA | C18: ERIK ALEJANDRO GARCIA | D18: 2090826 | E18: COPPEL CANADA GUADALUPE VICTORIA | F18: Ocoyoacac | G18: COPPEL | H18: 0.120598 | I18: 0.16789848 | J18: 0.15622072 | K18: 0.15006953 | L18: 0.16374086 | M18: 0.147431 | N18: 0.094041414 | O18: 0.13456876 | P18: 0.1570793 | Q18: 0.13666662 | R18: 0.15251214 | S18: 0.16144595 | T18: 0.17017768 | U18: 0.087549554 | V18: 0.13996354 | W18: 0.16408049 | X18: 0.14972686 | Y18: 0.14630852 | Z18: 0.15374769 | AA18: 0.16100337 | AB18: 0.085169521 | AC18: 0.14462106 | AD18: 0.1592788 | AE18: 0.15323481 | AF18: 0.13729452 | AG18: 0.1560897 | AH18: 0.16303765 | AI18: 0.086443459 | AJ18: 0 | AK18: 0 | AL18: 0 | AM18: 1 | AN18: 1 | AO18: 1 | AP18: 1 | AQ18: 0 | AR18: 0 | AS18: 4 | AT18: 1.1014957 | AU18: 0.88963582 | AV18: 0.83668471 | AW18: 0.81987406 | AX18: 0.93709498 | AY18: 1.4552246 | AZ18: 1.9599901 | BA18: 0.98133495 | BB18: 0.80581292 | BC18: 0.73416629 | BD18: 0.72110058 | BE18: 0.99308736 | BF18: 1.6443678 | BG18: 2.1201301 | BH18: 1.1421611 | BI18: 0.88503896 | BJ18: 0.79418318 | BK18: 0.73727187 | BL18: 0.90213491 | BM18: 1.6396422 | BN18: 1.8995678 | BO18: 0.87990745 | BP18: 0.7083811 | BQ18: 0.65740312 | BR18: 0.62742505 | BS18: 0.82004872 | BT18: 1.5251577 | BU18: 1.7816769 | BV18: 1.1016948 | BW18: 0.8983052 | BX18: 0 | BY18: 8 | BZ18: 8 | CA18: 8 | CB18: 7 | CC18: 2 | CD18: 0 | CE18: 33 | CF18: 1.7728415 | CG18: 1.5023522 | CH18: 1.4112478 | CI18: 1.3798806 | CJ18: 1.5693833 | CK18: 2.330268 | CL18: 3.0340266 | CM18: 1.6065712 | CN18: 1.3657987 | CO18: 1.237916 | CP18: 1.234163 | CQ18: 1.651077 | CR18: 2.6367293 | CS18: 3.2677448 | CT18: 1.710435 | CU18: 1.3810091 | CV18: 1.2417287 | CW18: 1.1600573 | CX18: 1.3941832 | CY18: 2.4155113 | CZ18: 2.6970753 | DA18: 1.4016317 | DB18: 1.1712518 | DC18: 1.0923821 | DD18: 1.033616 | DE18: 1.3275879 | DF18: 2.3418344 | DG18: 2.6316961 | DH18: 1.6525422 | DI18: 1.3474578 | DK18: 13 | DL18: 13 | DM18: 12 | DN18: 11 | DO18: 3 | DQ18: 52 | DR18: =+SUM(Tabla2[[#This Row],[1 gral]:[1 gral]]) -> 1.7728415 | DS18: =+SUM(Tabla2[[#This Row],[1 temm]:[1 temm]]) -> 1.1014957 | DT18: =+SUM(Tabla2[[#This Row],[1 porta]:[1 porta]]) -> 0.120598 | DU18: =+Tabla2[[#This Row],[GRAL]]-(Tabla2[[#This Row],[TEMM14]]+Tabla2[[#This Row],[PORTA15]]) -> 0.55074783
... A112: SANCHEZ MEZA JOB | B112: TOLUCA | C112: EDSON FERREYRA FFLORES | D112: 209003847 | E112: MEGA PLAZA MIA SANTIAGO T | F112: Toluca de Lerdo | G112: ELEKTRA | H112: 0.120598 | I112: 0.16789848 | J112: 0.15622072 | K112: 0.15006953 | L112: 0.16374086 | M112: 0.147431 | N112: 0.094041414 | O112: 0.13456876 | P112: 0.1570793 | Q112: 0.13666662 | R112: 0.15251214 | S112: 0.16144595 | T112: 0.17017768 | U112: 0.087549554 | V112: 0.13996354 | W112: 0.16408049 | X112: 0.14972686 | Y112: 0.14630852 | Z112: 0.15374769 | AA112: 0.16100337 | AB112: 0.085169521 | AC112: 0.14462106 | AD112: 0.1592788 | AE112: 0.15323481 | AF112: 0.13729452 | AG112: 0.1560897 | AH112: 0.16303765 | AI112: 0.086443459 | AJ112: 0 | AK112: 0 | AL112: 0 | AM112: 1 | AN112: 1 | AO112: 1 | AP112: 1 | AQ112: 0 | AR112: 0 | AS112: 4 | AT112: 0.27537392 | AU112: 0.22240895 | AV112: 0.20917118 | AW112: 0.20496852 | AX112: 0.23427374 | AY112: 0.36380616 | AZ112: 0.48999753 | BA112: 0.24533374 | BB112: 0.20145323 | BC112: 0.18354157 | BD112: 0.18027515 | BE112: 0.24827184 | BF112: 0.41109194 | BG112: 0.53003254 | BH112: 0.28554027 | BI112: 0.22125974 | BJ112: 0.19854579 | BK112: 0.18431797 | BL112: 0.22553373 | BM112: 0.40991054 | BN112: 0.47489196 | BO112: 0.25140213 | BP112: 0.2023946 | BQ112: 0.18782946 | BR112: 0.1792643 | BS112: 0.23429964 | BT112: 0.43575935 | BU112: 0.50905053 | BV112: -0.5508474 | BW112: -0.4491526 | BX112: 0 | BY112: 2 | BZ112: 2 | CA112: 2 | CB112: 2 | CC112: -1 | CD112: 0 | CE112: 7 | CF112: 1.3597806 | CG112: 1.1687388 | CH112: 1.097491 | CI112: 1.0724278 | CJ112: 1.2179727 | CK112: 1.7845587 | CL112: 2.2990303 | CM112: 1.2385706 | CN112: 1.0636188 | CO112: 0.96260369 | CP112: 0.96375029 | CQ112: 1.2786692 | CR112: 2.0200914 | CS112: 2.472696 | CT112: 1.4248947 | CU112: 1.1597493 | CV112: 1.0431829 | CW112: 0.97573938 | CX112: 1.1686495 | CY112: 2.0056008 | CZ112: 2.2221834 | DA112: 1.2759306 | DB112: 1.0700545 | DC112: 0.9984674 | DD112: 0.94398387 | DE112: 1.2104381 | DF112: 2.1239547 | DG112: 2.3771708 | DH112: 0.5508474 | DI112: 0.4491526 | DK112: 10 | DL112: 10 | DM112: 10 | DN112: 10 | DO112: 1 | DQ112: 41 | DR112: =+SUM(Tabla2[[#This Row],[1 gral]:[1 gral]]) -> 1.3597806 | DS112: =+SUM(Tabla2[[#This Row],[1 temm]:[1 temm]]) -> 0.27537392 | DT112: =+SUM(Tabla2[[#This Row],[1 porta]:[1 porta]]) -> 0.120598 | DU112: =+Tabla2[[#This Row],[GRAL]]-(Tabla2[[#This Row],[TEMM14]]+Tabla2[[#This Row],[PORTA15]]) -> 0.96380871

Sheet Altas
A1: Total general | E1: =+SUBTOTAL(9,E3:E108) -> 0 | F1: =+SUBTOTAL(9,F3:F108) -> 0 | G1: =+SUBTOTAL(9,G3:G108) -> 0 | H1: =+SUBTOTAL(9,H3:H108) -> 0 | I1: =+SUBTOTAL(9,I3:I108) -> 0 | J1: =+SUBTOTAL(9,J3:J108) -> 0 | K1: =+SUBTOTAL(9,K3:K108) -> 0 | L1: =+SUBTOTAL(9,L3:L108) -> 0 | ... AI1: =+SUBTOTAL(9,AI3:AI108) -> 0
A2: Total general | B2: NOMBRE PDV | C2: SUPERVISOR | D2: CADENA | E2: 1 | F2: 2 | G2: 3 | H2: 4 | I2: 5 | J2: 6 | K2: 7 | L2: 8 | M2: 9 | N2: 10 | O2: 11 | P2: 12 | Q2: 13 | R2: 14 | S2: 15 | T2: 16 | U2: 17 | V2: 18 | W2: 19 | X2: 20 | Y2: 21 | Z2: 22 | AA2: 23 | AB2: 24 | AC2: 25 | AD2: 26 | AE2: 27 | AF2: 28 | AG2: 29 | AH2: 30 | AI2: 31
A3: 2090171 | B3: COPPEL PLAZA DEL VALLE (194) | C3: DANIEL BENJAMIN MARQUEZ BACA | D3: COPPEL
A4: 2090172 | B4: COPPEL-CANADA OCAMPO (574) | C4: VIRGINIA MIRANDA OSORIO | D4: COPPEL
A5: 2090173 | B5: COPPEL PILARES (TOL) (208) | C5: ERIK ALEJANDRO GARCIA | D5: COPPEL
A6: 2090174 | B6: COPPEL-CANADA JUAREZ (582) | C6: EDGAR RAUL HERNANDEZ CERVANTES | D6: COPPEL
A7: 2090175 | B7: COPPEL - JUAREZ II (64) | C7: EDGAR RAUL HERNANDEZ CERVANTES | D7: COPPEL
A8: 2090176 | B8: COPPEL - 5 DE MAYO (159) | C8: EDGAR RAUL HERNANDEZ CERVANTES | D8: COPPEL
A9: 2090552 | B9: SUBURBIA - METEPEC | C9: EDSON FERREYRA FFLORES | D9: SUBURBIA
A10: 2090559 | B10: SUBURBIA - GRAN PLAZA | C10: EDGAR RAUL HERNANDEZ CERVANTES | D10: SUBURBIA
A11: 2090618 | B11: COPPEL UNIVERSIDAD | C11: VIRGINIA MIRANDA OSORIO | D11: COPPEL
A12: 2090742 | B12: COPPEL SENDERO | C12: ERIK ALEJANDRO GARCIA | D12: COPPEL
A13: 2090749 | B13: COPPEL CARRANZA LA COLCHONERA | C13: VIRGINIA MIRANDA OSORIO | D13: COPPEL
A14: 2090826 | B14: COPPEL CANADA GUADALUPE VICTORIA | C14: ERIK ALEJANDRO GARCIA | D14: COPPEL
... A108: 209003847 | B108: MEGA PLAZA MIA SANTIAGO T | C108: EDSON FERREYRA FFLORES | D108: ELEKTRA
A110: TEMM | E110: =+SUBTOTAL(9,E112:E217) -> 0 | F110: =+SUBTOTAL(9,F112:F217) -> 0 | G110: =+SUBTOTAL(9,G112:G217) -> 0 | H110: =+SUBTOTAL(9,H112:H217) -> 0 | I110: =+SUBTOTAL(9,I112:I217) -> 0 | J110: =+SUBTOTAL(9,J112:J217) -> 0 | K110: =+SUBTOTAL(9,K112:K217) -> 0 | L110: =+SUBTOTAL(9,L112:L217) -> 0 | ... AI110: =+SUBTOTAL(9,AI112:AI217) -> 0
A111: Total general | B111: NOMBRE PDV | C111: SUPERVISOR | D111: CADENA | E111: 1 | F111: 2 | G111: 3 | H111: 4 | I111: 5 | J111: 6 | K111: 7 | L111: 8 | M111: 9 | N111: 10 | O111: 11 | P111: 12 | Q111: 13 | R111: 14 | S111: 15 | T111: 16 | U111: 17 | V111: 18 | W111: 19 | X111: 20 | Y111: 21 | Z111: 22 | AA111: 23 | AB111: 24 | AC111: 25 | AD111: 26 | AE111: 27 | AF111: 28 | AG111: 29 | AH111: 30 | AI111: 31
A112: 2090171 | B112: COPPEL PLAZA DEL VALLE (194) | C112: DANIEL BENJAMIN MARQUEZ BACA | D112: COPPEL
A113: 2090172 | B113: COPPEL-CANADA OCAMPO (574) | C113: VIRGINIA MIRANDA OSORIO | D113: COPPEL
A114: 2090173 | B114: COPPEL PILARES (TOL) (208) | C114: ERIK ALEJANDRO GARCIA | D114: COPPEL
A115: 2090174 | B115: COPPEL-CANADA JUAREZ (582) | C115: EDGAR RAUL HERNANDEZ CERVANTES | D115: COPPEL
A116: 2090175 | B116: COPPEL - JUAREZ II (64) | C116: EDGAR RAUL HERNANDEZ CERVANTES | D116: COPPEL
A117: 2090176 | B117: COPPEL - 5 DE MAYO (159) | C117: EDGAR RAUL HERNANDEZ CERVANTES | D117: COPPEL
A118: 2090552 | B118: SUBURBIA - METEPEC | C118: EDSON FERREYRA FFLORES | D118: SUBURBIA
A119: 2090559 | B119: SUBURBIA - GRAN PLAZA | C119: EDGAR RAUL HERNANDEZ CERVANTES | D119: SUBURBIA
A120: 2090618 | B120: COPPEL UNIVERSIDAD | C120: VIRGINIA MIRANDA OSORIO | D120: COPPEL
A121: 2090742 | B121: COPPEL SENDERO | C121: ERIK ALEJANDRO GARCIA | D121: COPPEL
A122: 2090749 | B122: COPPEL CARRANZA LA COLCHONERA | C122: VIRGINIA MIRANDA OSORIO | D122: COPPEL
A123: 2090826 | B123: COPPEL CANADA GUADALUPE VICTORIA | C123: ERIK ALEJANDRO GARCIA | D123: COPPEL
... A217: 209003847 | B217: MEGA PLAZA MIA SANTIAGO T | C217: EDSON FERREYRA FFLORES | D217: ELEKTRA
A219: PORTABILIDAD | E219: =+SUBTOTAL(9,E221:E326) -> 0 | F219: =+SUBTOTAL(9,F221:F326) -> 0 | G219: =+SUBTOTAL(9,G221:G326) -> 0 | H219: =+SUBTOTAL(9,H221:H326) -> 0 | I219: =+SUBTOTAL(9,I221:I326) -> 0 | J219: =+SUBTOTAL(9,J221:J326) -> 0 | K219: =+SUBTOTAL(9,K221:K326) -> 0 | L219: =+SUBTOTAL(9,L221:L326) -> 0 | ... AI219: =+SUBTOTAL(9,AI221:AI326) -> 0
A220: Total general | B220: NOMBRE PDV | C220: SUPERVISOR | D220: CADENA | E220: 1 | F220: 2 | G220: 3 | H220: 4 | I220: 5 | J220: 6 | K220: 7 | L220: 8 | M220: 9 | N220: 10 | O220: 11 | P220: 12 | Q220: 13 | R220: 14 | S220: 15 | T220: 16 | U220: 17 | V220: 18 | W220: 19 | X220: 20 | Y220: 21 | Z220: 22 | AA220: 23 | AB220: 24 | AC220: 25 | AD220: 26 | AE220: 27 | AF220: 28 | AG220: 29 | AH220: 30 | AI220: 31
A221: 2090171 | B221: COPPEL PLAZA DEL VALLE (194) | C221: DANIEL BENJAMIN MARQUEZ BACA | D221: COPPEL
A222: 2090172 | B222: COPPEL-CANADA OCAMPO (574) | C222: VIRGINIA MIRANDA OSORIO | D222: COPPEL
A223: 2090173 | B223: COPPEL PILARES (TOL) (208) | C223: ERIK ALEJANDRO GARCIA | D223: COPPEL
A224: 2090174 | B224: COPPEL-CANADA JUAREZ (582) | C224: EDGAR RAUL HERNANDEZ CERVANTES | D224: COPPEL
A225: 2090175 | B225: COPPEL - JUAREZ II (64) | C225: EDGAR RAUL HERNANDEZ CERVANTES | D225: COPPEL
A226: 2090176 | B226: COPPEL - 5 DE MAYO (159) | C226: EDGAR RAUL HERNANDEZ CERVANTES | D226: COPPEL
A227: 2090552 | B227: SUBURBIA - METEPEC | C227: EDSON FERREYRA FFLORES | D227: SUBURBIA
A228: 2090559 | B228: SUBURBIA - GRAN PLAZA | C228: EDGAR RAUL HERNANDEZ CERVANTES | D228: SUBURBIA
A229: 2090618 | B229: COPPEL UNIVERSIDAD | C229: VIRGINIA MIRANDA OSORIO | D229: COPPEL
A230: 2090742 | B230: COPPEL SENDERO | C230: ERIK ALEJANDRO GARCIA | D230: COPPEL
A231: 2090749 | B231: COPPEL CARRANZA LA COLCHONERA | C231: VIRGINIA MIRANDA OSORIO | D231: COPPEL
A232: 2090826 | B232: COPPEL CANADA GUADALUPE VICTORIA | C232: ERIK ALEJANDRO GARCIA | D232: COPPEL
... A326: 209003847 | B326: MEGA PLAZA MIA SANTIAGO T | C326: EDSON FERREYRA FFLORES | D326: ELEKTRA

Sheet FieldWy
A1: ID PDV | B1: Nombre PDV | C1: Di Atiende | D1: Nombre Atiende | E1: Di Propietario | F1: DN | G1: Canal | H1: Cadena | I1: Region | J1: Subdirector | K1: Lider Zonal | L1: Supervisor | M1: Usuario | N1: Nombre Usuario | O1: Rol de usuario | P1: EquipoClave | Q1: EquipoClaveIndisegno | R1: Fecha registro | S1: Hora registro | T1: Folio | U1: ID Usuario | V1: Di Patrón | W1: Patrón | X1: Producto | Y1: IMEI | Z1: ICC | AA1: Equipo TEMM | AB1: Monto Recarga | AC1: Costo Equipo | AD1: Rango | AE1: Observaciones

Sheet Resumen dia
E2: VIE | F2: SAB | G2: DOM | H2: LUN | I2: MAR | J2: MIE | K2: JUE | L2: VIE | M2: SAB | N2: DOM | O2: LUN | P2: MAR | Q2: MIE | R2: JUE | S2: VIE | T2: SAB | U2: DOM | V2: LUN | W2: MAR | X2: MIE | Y2: JUE | Z2: VIE | AA2: SAB | AB2: DOM | AC2: LUN | AD2: MAR | AE2: MIE | AF2: JUE | AG2: VIE | AH2: SAB | AI2: DOM
B3: ACUMULADO | C3: ALCANCE AL DIA | D3: GAP | E3: 1 | F3: 2 | G3: 3 | H3: 4 | I3: 5 | J3: 6 | K3: 7 | L3: 8 | M3: 9 | N3: 10 | O3: 11 | P3: 12 | Q3: 13 | R3: 14 | S3: 15 | T3: 16 | U3: 17 | V3: 18 | W3: 19 | X3: 20 | Y3: 21 | Z3: 22 | AA3: 23 | AB3: 24 | AC3: 25 | AD3: 26 | AE3: 27 | AF3: 28 | AG3: 29 | AH3: 30 | AI3: 31
A4: CUOTA TOTAL | B4: =+Cuota!DR5 -> 79.469291 | C4: =IFERROR(B5/B4,0) -> 0 | D4: =+B5-B4 -> -79.469291 | E4: 79.469291 | F4: 68.061585 | G4: 63.917916 | H4: 62.467996 | I4: 70.971153 | J4: 104.33543 | K4: 134.77662 | L4: 72.561193 | M4: 62.237899 | N4: 56.336743 | O4: 56.375968 | P4: 74.870321 | Q4: 118.43395 | R4: 145.18393 | S4: 78.220828 | T4: 63.782484 | U4: 57.376697 | V4: 53.681806 | W4: 64.244915 | X4: 110.01519 | Y4: 121.67809 | Z4: 68.202808 | AA4: 57.350004 | AB4: 53.531711 | AC4: 50.580323 | AD4: 64.777576 | AE4: 113.22175 | AF4: 126.33583 | AG4: 87.567903 | AH4: 76.432097 | AI4: 102.94226
A5: ALTAS TOTAL | B5: =+SUM(E5:AI5) -> 0 | E5: =+Altas!E1 -> 0 | F5: =+Altas!F1 -> 0 | G5: =+Altas!G1 -> 0 | H5: =+Altas!H1 -> 0 | I5: =+Altas!I1 -> 0 | J5: =+Altas!J1 -> 0 | K5: =+Altas!K1 -> 0 | L5: =+Altas!L1 -> 0 | ... AI5: =+Altas!AI1 -> 0
E6: =+E5/E4 -> 0 | F6: =+F5/F4 -> 0 | G6: =+G5/G4 -> 0 | H6: =+H5/H4 -> 0 | I6: =+I5/I4 -> 0 | J6: =+J5/J4 -> 0 | K6: =+K5/K4 -> 0 | L6: =+L5/L4 -> 0 | ... AI6: =+AI5/AI4 -> 0
A7: CUOTA TEMM | B7: =+Cuota!DS5 -> 39.826684 | C7: =IFERROR(B8/B7,0) -> 0 | D7: =+B8-B7 -> -39.826684 | E7: 39.826684 | F7: 32.589462 | G7: 30.639632 | H7: 30.005946 | I7: 34.249317 | J7: 52.545061 | K7: 70.143897 | L7: 35.644803 | M7: 29.548834 | N7: 26.882903 | O7: 26.514143 | P7: 36.223277 | Q7: 59.396122 | R7: 75.789917 | S7: 38.816637 | T7: 30.412028 | U7: 27.304952 | V7: 25.392141 | W7: 30.918472 | X7: 55.484122 | Y7: 63.671648 | Z7: 34.178508 | AA7: 27.772957 | AB7: 25.806813 | AC7: 24.576287 | AD7: 31.98124 | AE7: 58.716339 | AF7: 67.967856 | AG7: 41.132833 | AH7: 33.867167 | AI7: 51.544686
A8: ALTAS TEMM | B8: =+SUM(E8:AI8) -> 0 | E8: =+Altas!E48 -> 0 | F8: =+Altas!F48 -> 0 | G8: =+Altas!G48 -> 0 | H8: =+Altas!H48 -> 0 | I8: =+Altas!I48 -> 0 | J8: =+Altas!J48 -> 0 | K8: =+Altas!K48 -> 0 | L8: =+Altas!L48 -> 0 | ... AI8: =+Altas!AI48 -> 0
E9: =+E8/E7 -> 0 | F9: =+F8/F7 -> 0 | G9: =+G8/G7 -> 0 | H9: =+H8/H7 -> 0 | I9: =+I8/I7 -> 0 | J9: =+J8/J7 -> 0 | K9: =+K8/K7 -> 0 | L9: =+L8/L7 -> 0 | ... AI9: =+AI8/AI7 -> 0
A10: CUOTA PORTA | B10: =+Cuota!DT5 -> 6.63289 | C10: =IFERROR(B11/B10,0) -> 0 | D10: =+B11-B10 -> -6.63289 | E10: 6.63289 | F10: 9.2344162 | G10: 8.5921396 | H10: 8.253824 | I10: 9.0057474 | J10: 8.108705 | K10: 5.1722778 | L10: 7.6704192 | M10: 8.9535202 | N10: 7.7899973 | O10: 8.6931919 | P10: 9.2024193 | Q10: 9.7001276 | R10: 4.9903246 | S10: 7.9779216 | T10: 9.3525881 | U10: 8.5344312 | V10: 8.3395859 | W10: 8.7636181 | X10: 9.1771923 | Y10: 4.8546627 | Z10: 8.2434005 | AA10: 9.0788918 | AB10: 8.7343844 | AC10: 7.8257876 | AD10: 8.8971127 | AE10: 9.2931458 | AF10: 4.9272771 | AG10: 22.56791 | AH10: 23.43209 | AI10: 15.605898
A11: ALTAS PORTA | B11: =+SUM(E11:AI11) -> 0 | E11: =+Altas!E95 -> 0 | F11: =+Altas!F95 -> 0 | G11: =+Altas!G95 -> 0 | H11: =+Altas!H95 -> 0 | I11: =+Altas!I95 -> 0 | J11: =+Altas!J95 -> 0 | K11: =+Altas!K95 -> 0 | L11: =+Altas!L95 -> 0 | ... AI11: =+Altas!AI95 -> 0
E12: =+E11/E10 -> 0 | F12: =+F11/F10 -> 0 | G12: =+G11/G10 -> 0 | H12: =+H11/H10 -> 0 | I12: =+I11/I10 -> 0 | J12: =+J11/J10 -> 0 | K12: =+K11/K10 -> 0 | L12: =+L11/L10 -> 0 | ... AI12: =+AI11/AI10 -> 0
A13: CUOTA PP VOZ | B13: =+Cuota!DU5 -> 33.009717 | C13: =IFERROR(B14/B13,0) -> 0 | D13: =+B14-B13 -> -33.009717 | E13: =+E4-(E7+E10) -> 33.009717 | F13: =+F4-(F7+F10) -> 26.237706 | G13: =+G4-(G7+G10) -> 24.686145 | H13: =+H4-(H7+H10) -> 24.208226 | I13: =+I4-(I7+I10) -> 27.716089 | J13: =+J4-(J7+J10) -> 43.681669 | K13: =+K4-(K7+K10) -> 59.460449 | L13: =+L4-(L7+L10) -> 29.24597 | ... AI13: =+AI4-(AI7+AI10) -> 35.791672
A14: ALTAS PP VOZ | B14: =+SUM(E14:AI14) -> 0 | E14: =+E5-(E8+E11) -> 0 | F14: =+F5-(F8+F11) -> 0 | G14: =+G5-(G8+G11) -> 0 | H14: =+H5-(H8+H11) -> 0 | I14: =+I5-(I8+I11) -> 0 | J14: =+J5-(J8+J11) -> 0 | K14: =+K5-(K8+K11) -> 0 | L14: =+L5-(L8+L11) -> 0 | ... AI14: =+AI5-(AI8+AI11) -> 0
E15: =+E14/E13 -> 0 | F15: =+F14/F13 -> 0 | G15: =+G14/G13 -> 0 | H15: =+H14/H13 -> 0 | I15: =+I14/I13 -> 0 | J15: =+J14/J13 -> 0 | K15: =+K14/K13 -> 0 | L15: =+L14/L13 -> 0 | ... AI15: =+AI14/AI13 -> 0
B16: PROM COB | C16: AUTORIZADO | D16: % | E16: 1 | F16: 2 | G16: 3 | H16: 4 | I16: 5 | J16: 6 | K16: 7 | L16: 8 | M16: 9 | N16: 10 | O16: 11 | P16: 12 | Q16: 13 | R16: 14 | S16: 15 | T16: 16 | U16: 17 | V16: 18 | W16: 19 | X16: 20 | Y16: 21 | Z16: 22 | AA16: 23 | AB16: 24 | AC16: 25 | AD16: 26 | AE16: 27 | AF16: 28 | AG16: 29 | AH16: 30 | AI16: 31
A17: TIENDAS CUB | B17: =+AVERAGE(E17:N17) -> #DIV/0! | C17: 43 | D17: =+B17/C17 -> #DIV/0!
A18: PROM ACTIVOS | B18: =+AVERAGE(E18:N18) -> #DIV/0! | C18: 54 | D18: =+B18/C18 -> #DIV/0!
D19: COBERTURA | E19: =+E17/43 -> 0 | F19: =+F17/43 -> 0 | G19: =+G17/43 -> 0 | H19: =+H17/43 -> 0 | I19: =+I17/43 -> 0 | J19: =+J17/43 -> 0 | K19: =+K17/43 -> 0 | L19: =+L17/43 -> 0 | ... AI19: =+AI17/43 -> 0
D20: ASISTENCIA | E20: =+E18/54 -> 0 | F20: =+F18/54 -> 0 | G20: =+G18/54 -> 0 | H20: =+H18/54 -> 0 | I20: =+I18/54 -> 0 | J20: =+J18/54 -> 0 | K20: =+K18/54 -> 0 | L20: =+L18/54 -> 0 | ... AI20: =+AI18/54 -> 0
D21: SIN CUBRIR | E21: =+$C$17-E17 -> 43 | F21: =+$C$17-F17 -> 43 | G21: =+$C$17-G17 -> 43 | H21: =+$C$17-H17 -> 43 | I21: =+$C$17-I17 -> 43 | J21: =+$C$17-J17 -> 43 | K21: =+$C$17-K17 -> 43 | L21: =+$C$17-L17 -> 43 | ... AI21: =+$C$17-AI17 -> 43

Sheet Seg Diario
AM2: Tiendas en 0
E3: AVANCE AL DIA | F3: 1 | L3: TOTALES | P3: TEMM | T3: PORTABILIDAD | X3: PREPAGO VOZ | AB3: PRODUCTIVIDAD TOTAL | AE3: PRODUCTIVIDAD TEMM | AH3: PRODUCTIVIDAD PORTA | AK3: PRODUCTIVIDAD PREPAGO VOZ | AN3: REGISTROS FIELDWY | AV3: DIAS SIN VENTA
C4: =+SUBTOTAL(9,C6:C111) -> 43 | L4: =+IFERROR(M4/N4,0) -> 0 | M4: =+SUBTOTAL(9,M6:M111) -> 0 | N4: =+SUBTOTAL(9,N6:N111) -> 79.469291 | O4: =+SUBTOTAL(9,O6:O111) -> -79.469291 | P4: =+IFERROR(Q4/R4,0) -> 12.453962 | Q4: =+SUBTOTAL(9,Q6:Q111) -> 496 | R4: =+SUBTOTAL(9,R6:R111) -> 39.826684 | S4: =+SUBTOTAL(9,S6:S111) -> 456.17332 | T4: =+IFERROR(U4/V4,0) -> 0 | U4: =+SUBTOTAL(9,U6:U111) -> 0 | V4: =+SUBTOTAL(9,V6:V111) -> 6.63289 | W4: =+SUBTOTAL(9,W6:W111) -> -6.63289 | X4: =+IFERROR(Y4/Z4,0) -> -15.025879 | Y4: =+SUBTOTAL(9,Y6:Y111) -> -496 | Z4: =+SUBTOTAL(9,Z6:Z111) -> 33.009717 | AA4: =+SUBTOTAL(9,AA6:AA111) -> -529.00972 | AB4: =+SUBTOTAL(9,AB6:AB48)/$C$4 -> 0 | AC4: =+SUBTOTAL(9,AC6:AC48)/$C$4 -> 1.039533 | AD4: =+AB4-AC4 -> -1.039533 | AE4: =+SUBTOTAL(9,AE6:AE48)/$C$4 -> 0 | AF4: =+SUBTOTAL(9,AF6:AF48)/$C$4 -> 0.53635007 | AG4: =+AE4-AF4 -> -0.53635007 | AH4: =+SUBTOTAL(9,AH6:AH48)/$C$4 -> 0 | AI4: =+SUBTOTAL(9,AI6:AI48)/$C$4 -> 0.075724326 | AJ4: =+AH4-AI4 -> -0.075724326 | AN4: =+SUBTOTAL(9,AN6:AN111) -> 0 | AO4: =+SUBTOTAL(9,AO6:AO111) -> 0 | AP4: =+SUBTOTAL(9,AP6:AP111) -> 0 | AQ4: =+SUBTOTAL(9,AQ6:AQ111) -> 496 | AR4: =+SUBTOTAL(9,AR6:AR111) -> 0 | AS4: =+SUBTOTAL(9,AS6:AS111) -> 0 | AT4: =+SUBTOTAL(9,AT6:AT111) -> 0 | AU4: =+SUBTOTAL(9,AU6:AU111) -> -496 | AW4: =SUBTOTAL(1,AW6:AW111) -> #DIV/0! | AX4: =SUBTOTAL(1,AX6:AX111) -> #DIV/0! | AY4: =SUBTOTAL(1,AY6:AY111) -> #DIV/0! | AZ4: =SUBTOTAL(1,AZ6:AZ111) -> #DIV/0!
A5: LIDER | B5: SUPERVISOR | C5: PDVS | D5: PALANCA | E5: Categoria Palanca | F5: Pendiente | G5: ESTATUS | H5: IDPV | I5: NOMBRE_IDPV | J5: PLAZA | K5: CADENA | L5: ALCANCE | M5: ALTAS | N5: CUOTA | O5: GAP | P5: ALCANCE | Q5: ALTAS | R5: CUOTA | S5: GAP | T5: ALCANCE | U5: ALTAS | V5: CUOTA | W5: GAP | X5: ALCANCE | Y5: ALTAS | Z5: CUOTA | AA5: GAP | AB5: Prod Total | AC5: Prod Obj | AD5: GAP | AE5: Real | AF5: Prod Obj | AG5: GAP | AH5: Prod Total | AI5: Prod Obj | AJ5: GAP | AK5: Prod Total | AL5: Prod Obj | AM5: GAP | AN5: TOTAL | AO5: GAP | AP5: TEMM | AQ5: GAP | AR5: PORTA | AS5: GAP | AT5: PP VOZ | AU5: GAP | AV5: ASISTENCIA | AW5: TOTAL | AX5: TEMM | AY5: PORTA | AZ5: PP VOZ | BE5: 4
A6: REYES ZARRABAL CRISTOPHER | B6: DANIEL BENJAMIN MARQUEZ BACA | C6: 1 | D6: 10 Pdvs 20 y 21 Jun | E6: Mejorar cobertura | G6: Vacante | H6: 2090171 | I6: COPPEL PLAZA DEL VALLE (194) | J6: PACHUCA | K6: Coppel | L6: =+IFERROR(M6/N6,0) -> 0 | M6: =SUM(Altas!E3:AI3) -> 0 | N6: =VLOOKUP(H6,Cuota!$D:$DU,119,0) -> 3.545683 | O6: =+M6-N6 -> -3.545683 | P6: =+IFERROR(Q6/R6,0) -> 0 | Q6: =+SUM(Altas!E50:AI50) -> 0 | R6: =VLOOKUP(H6,Tabla2[[#All],[IDPV]:[PP VOZ]],120,0) -> 1.9276174 | S6: =+Q6-R6 -> -1.9276174 | T6: =+IFERROR(U6/V6,0) -> 0 | U6: =+SUM(Altas!E97:AI97) -> 0 | V6: =VLOOKUP(H6,Tabla2[[#All],[IDPV]:[PP VOZ]],121,0) -> 0.241196 | W6: =+U6-V6 -> -0.241196 | X6: =+IFERROR(Y6/Z6,0) -> 0 | Y6: =+M6-(Q6+U6) -> 0 | Z6: =VLOOKUP(H6,Tabla2[[#All],[IDPV]:[PP VOZ]],122,0) -> 1.3768696 | AA6: =+Y6-Z6 -> -1.3768696 | AB6: =+M6/$F$3 -> 0 | AC6: =+N6/$F$3 -> 3.545683 | AD6: =+AB6-AC6 -> -3.545683 | AE6: =+Q6/$F$3 -> 0 | AF6: =+R6/$F$3 -> 1.9276174 | AG6: =+AE6-AF6 -> -1.9276174 | AH6: =+U6/$F$3 -> 0 | AI6: =+V6/$F$3 -> 0.241196 | AJ6: =+AH6-AI6 -> -0.241196 | AK6: =+Y6/#REF! -> #REF! | AL6: =+Z6/#REF! -> #REF! | AM6: =+AK6-AL6 -> #REF! | AN6: =+COUNTIFS(FieldWy!A:A,H6,FieldWy!F:F,"<>") -> 0 | AO6: =+M6-AN6 -> 0 | AP6: =+COUNTIFS(FieldWy!A:A,H6,FieldWy!F:F,"<>",FieldWy!AA:AA,"true") -> 0 | AQ6: =+Q6-AP6 -> 0 | AR6: =+COUNTIFS(FieldWy!A:A,H6,FieldWy!F:F,"<>",FieldWy!X:X,"PORTABILIDAD") -> 0 | AS6: =+U6+AR6 -> 0 | AT6: =+AN6-(AP6+AR6) -> 0 | AU6: =+Y6-AT6 -> 0
A7: REYES ZARRABAL CRISTOPHER | B7: CESAR GARRIDO BADILLO | C7: 1 | D7: 10 tiendas 90 al 100% | G7: Estable | H7: 2090172 | I7: COPPEL-CANADA OCAMPO (574) | J7: PACHUCA | K7: Coppel | L7: =+IFERROR(M7/N7,0) -> 0 | M7: =SUM(Altas!E4:AI4) -> 0 | N7: =VLOOKUP(H7,Cuota!$D:$DU,119,0) -> 2.9949352 | O7: =+M7-N7 -> -2.9949352 | P7: =+IFERROR(Q7/R7,0) -> 0 | Q7: =+SUM(Altas!E51:AI51) -> 0 | R7: =VLOOKUP(H7,Tabla2[[#All],[IDPV]:[PP VOZ]],120,0) -> 1.6522435 | S7: =+Q7-R7 -> -1.6522435 | T7: =+IFERROR(U7/V7,0) -> 0 | U7: =+SUM(Altas!E98:AI98) -> 0 | V7: =VLOOKUP(H7,Tabla2[[#All],[IDPV]:[PP VOZ]],121,0) -> 0.241196 | W7: =+U7-V7 -> -0.241196 | X7: =+IFERROR(Y7/Z7,0) -> 0 | Y7: =+M7-(Q7+U7) -> 0 | Z7: =VLOOKUP(H7,Tabla2[[#All],[IDPV]:[PP VOZ]],122,0) -> 1.1014957 | AA7: =+Y7-Z7 -> -1.1014957 | AB7: =+M7/$F$3 -> 0 | AC7: =+N7/$F$3 -> 2.9949352 | AD7: =+AB7-AC7 -> -2.9949352 | AE7: =+Q7/$F$3 -> 0 | AF7: =+R7/$F$3 -> 1.6522435 | AG7: =+AE7-AF7 -> -1.6522435 | AH7: =+U7/$F$3 -> 0 | AI7: =+V7/$F$3 -> 0.241196 | AJ7: =+AH7-AI7 -> -0.241196 | AK7: =+Y7/#REF! -> #REF! | AL7: =+Z7/#REF! -> #REF! | AM7: =+AK7-AL7 -> #REF! | AN7: =+COUNTIFS(FieldWy!A:A,H7,FieldWy!F:F,"<>") -> 0 | AO7: =+M7-AN7 -> 0 | AP7: =+COUNTIFS(FieldWy!A:A,H7,FieldWy!F:F,"<>",FieldWy!AA:AA,"true") -> 0 | AQ7: =+Q7-AP7 -> 0 | AR7: =+COUNTIFS(FieldWy!A:A,H7,FieldWy!F:F,"<>",FieldWy!X:X,"PORTABILIDAD") -> 0 | AS7: =+U7+AR7 -> 0 | AT7: =+AN7-(AP7+AR7) -> 0 | AU7: =+Y7-AT7 -> 0
A8: CALDERON GRACIAN ISRAEL | B8: ERIK ALEJANDRO GARCIA | C8: 1 | H8: 2090173 | I8: COPPEL PILARES (TOL) (208) | J8: Metepec | K8: COPPEL | L8: =+IFERROR(M8/N8,0) -> 0 | M8: =SUM(Altas!E5:AI5) -> 0 | N8: =VLOOKUP(H8,Cuota!$D:$DU,119,0) -> 1.6522435 | O8: =+M8-N8 -> -1.6522435 | P8: =+IFERROR(Q8/R8,0) -> 0 | Q8: =+SUM(Altas!E52:AI52) -> 0 | R8: =VLOOKUP(H8,Tabla2[[#All],[IDPV]:[PP VOZ]],120,0) -> 0.96380871 | S8: =+Q8-R8 -> -0.96380871 | T8: =+IFERROR(U8/V8,0) -> 0 | U8: =+SUM(Altas!E99:AI99) -> 0 | V8: =VLOOKUP(H8,Tabla2[[#All],[IDPV]:[PP VOZ]],121,0) -> 0 | W8: =+U8-V8 -> 0 | X8: =+IFERROR(Y8/Z8,0) -> 0 | Y8: =+M8-(Q8+U8) -> 0 | Z8: =VLOOKUP(H8,Tabla2[[#All],[IDPV]:[PP VOZ]],122,0) -> 0.68843479 | AA8: =+Y8-Z8 -> -0.68843479 | AB8: =+M8/$F$3 -> 0 | AC8: =+N8/$F$3 -> 1.6522435 | AD8: =+AB8-AC8 -> -1.6522435 | AE8: =+Q8/$F$3 -> 0 | AF8: =+R8/$F$3 -> 0.96380871 | AG8: =+AE8-AF8 -> -0.96380871 | AH8: =+U8/$F$3 -> 0 | AI8: =+V8/$F$3 -> 0 | AJ8: =+AH8-AI8 -> 0 | AN8: =+COUNTIFS(FieldWy!A:A,H8,FieldWy!F:F,"<>") -> 0 | AO8: =+M8-AN8 -> 0 | AP8: =+COUNTIFS(FieldWy!A:A,H8,FieldWy!F:F,"<>",FieldWy!AA:AA,"true") -> 0 | AQ8: =+Q8-AP8 -> 0 | AR8: =+COUNTIFS(FieldWy!A:A,H8,FieldWy!F:F,"<>",FieldWy!X:X,"PORTABILIDAD") -> 0 | AS8: =+U8+AR8 -> 0 | AT8: =+AN8-(AP8+AR8) -> 0 | AU8: =+Y8-AT8 -> 0
A9: SANCHEZ MEZA JOB | B9: EDGAR RAUL HERNANDEZ CERVANTES | C9: 1 | H9: 2090174 | I9: COPPEL-CANADA JUAREZ (582) | J9: Toluca de Lerdo | K9: COPPEL | L9: =+IFERROR(M9/N9,0) -> 0 | M9: =SUM(Altas!E6:AI6) -> 0 | N9: =VLOOKUP(H9,Cuota!$D:$DU,119,0) -> 1.7728415 | O9: =+M9-N9 -> -1.7728415 | P9: =+IFERROR(Q9/R9,0) -> 0 | Q9: =+SUM(Altas!E53:AI53) -> 0 | R9: =VLOOKUP(H9,Tabla2[[#All],[IDPV]:[PP VOZ]],120,0) -> 0.96380871 | S9: =+Q9-R9 -> -0.96380871 | T9: =+IFERROR(U9/V9,0) -> 0 | U9: =+SUM(Altas!E100:AI100) -> 0 | V9: =VLOOKUP(H9,Tabla2[[#All],[IDPV]:[PP VOZ]],121,0) -> 0.120598 | W9: =+U9-V9 -> -0.120598 | X9: =+IFERROR(Y9/Z9,0) -> 0 | Y9: =+M9-(Q9+U9) -> 0 | Z9: =VLOOKUP(H9,Tabla2[[#All],[IDPV]:[PP VOZ]],122,0) -> 0.68843479 | AA9: =+Y9-Z9 -> -0.68843479 | AB9: =+M9/$F$3 -> 0 | AC9: =+N9/$F$3 -> 1.7728415 | AD9: =+AB9-AC9 -> -1.7728415 | AE9: =+Q9/$F$3 -> 0 | AF9: =+R9/$F$3 -> 0.96380871 | AG9: =+AE9-AF9 -> -0.96380871 | AH9: =+U9/$F$3 -> 0 | AI9: =+V9/$F$3 -> 0.120598 | AJ9: =+AH9-AI9 -> -0.120598 | AN9: =+COUNTIFS(FieldWy!A:A,H9,FieldWy!F:F,"<>") -> 0 | AO9: =+M9-AN9 -> 0 | AP9: =+COUNTIFS(FieldWy!A:A,H9,FieldWy!F:F,"<>",FieldWy!AA:AA,"true") -> 0 | AQ9: =+Q9-AP9 -> 0 | AR9: =+COUNTIFS(FieldWy!A:A,H9,FieldWy!F:F,"<>",FieldWy!X:X,"PORTABILIDAD") -> 0 | AS9: =+U9+AR9 -> 0 | AT9: =+AN9-(AP9+AR9) -> 0 | AU9: =+Y9-AT9 -> 0
A10: SANCHEZ MEZA JOB | B10: EDGAR RAUL HERNANDEZ CERVANTES | C10: 1 | H10: 2090175 | I10: COPPEL - JUAREZ II (64) | J10: Toluca de Lerdo | K10: COPPEL | L10: =+IFERROR(M10/N10,0) -> 0 | M10: =SUM(Altas!E7:AI7) -> 0 | N10: =VLOOKUP(H10,Cuota!$D:$DU,119,0) -> 4.0964308 | O10: =+M10-N10 -> -4.0964308 | P10: =+IFERROR(Q10/R10,0) -> 0 | Q10: =+SUM(Altas!E54:AI54) -> 0 | R10: =VLOOKUP(H10,Tabla2[[#All],[IDPV]:[PP VOZ]],120,0) -> 2.6160522 | S10: =+Q10-R10 -> -2.6160522 | T10: =+IFERROR(U10/V10,0) -> 0 | U10: =+SUM(Altas!E101:AI101) -> 0 | V10: =VLOOKUP(H10,Tabla2[[#All],[IDPV]:[PP VOZ]],121,0) -> 0.241196 | W10: =+U10-V10 -> -0.241196 | X10: =+IFERROR(Y10/Z10,0) -> 0 | Y10: =+M10-(Q10+U10) -> 0 | Z10: =VLOOKUP(H10,Tabla2[[#All],[IDPV]:[PP VOZ]],122,0) -> 1.2391826 | AA10: =+Y10-Z10 -> -1.2391826 | AB10: =+M10/$F$3 -> 0 | AC10: =+N10/$F$3 -> 4.0964308 | AD10: =+AB10-AC10 -> -4.0964308 | AE10: =+Q10/$F$3 -> 0 | AF10: =+R10/$F$3 -> 2.6160522 | AG10: =+AE10-AF10 -> -2.6160522 | AH10: =+U10/$F$3 -> 0 | AI10: =+V10/$F$3 -> 0.241196 | AJ10: =+AH10-AI10 -> -0.241196 | AN10: =+COUNTIFS(FieldWy!A:A,H10,FieldWy!F:F,"<>") -> 0 | AO10: =+M10-AN10 -> 0 | AP10: =+COUNTIFS(FieldWy!A:A,H10,FieldWy!F:F,"<>",FieldWy!AA:AA,"true") -> 0 | AQ10: =+Q10-AP10 -> 0 | AR10: =+COUNTIFS(FieldWy!A:A,H10,FieldWy!F:F,"<>",FieldWy!X:X,"PORTABILIDAD") -> 0 | AS10: =+U10+AR10 -> 0 | AT10: =+AN10-(AP10+AR10) -> 0 | AU10: =+Y10-AT10 -> 0
A11: SANCHEZ MEZA JOB | B11: EDGAR RAUL HERNANDEZ CERVANTES | C11: 1 | H11: 2090176 | I11: COPPEL - 5 DE MAYO (159) | J11: Toluca de Lerdo | K11: COPPEL | L11: =+IFERROR(M11/N11,0) -> 0 | M11: =SUM(Altas!E8:AI8) -> 0 | N11: =VLOOKUP(H11,Cuota!$D:$DU,119,0) -> 4.8019546 | O11: =+M11-N11 -> -4.8019546 | P11: =+IFERROR(Q11/R11,0) -> 0 | Q11: =+SUM(Altas!E55:AI55) -> 0 | R11: =VLOOKUP(H11,Tabla2[[#All],[IDPV]:[PP VOZ]],120,0) -> 3.8552348 | S11: =+Q11-R11 -> -3.8552348 | T11: =+IFERROR(U11/V11,0) -> 0 | U11: =+SUM(Altas!E102:AI102) -> 0 | V11: =VLOOKUP(H11,Tabla2[[#All],[IDPV]:[PP VOZ]],121,0) -> 0.120598 | W11: =+U11-V11 -> -0.120598 | X11: =+IFERROR(Y11/Z11,0) -> 0 | Y11: =+M11-(Q11+U11) -> 0 | Z11: =VLOOKUP(H11,Tabla2[[#All],[IDPV]:[PP VOZ]],122,0) -> 0.82612175 | AA11: =+Y11-Z11 -> -0.82612175 | AB11: =+M11/$F$3 -> 0 | AC11: =+N11/$F$3 -> 4.8019546 | AD11: =+AB11-AC11 -> -4.8019546 | AE11: =+Q11/$F$3 -> 0 | AF11: =+R11/$F$3 -> 3.8552348 | AG11: =+AE11-AF11 -> -3.8552348 | AH11: =+U11/$F$3 -> 0 | AI11: =+V11/$F$3 -> 0.120598 | AJ11: =+AH11-AI11 -> -0.120598 | AN11: =+COUNTIFS(FieldWy!A:A,H11,FieldWy!F:F,"<>") -> 0 | AO11: =+M11-AN11 -> 0 | AP11: =+COUNTIFS(FieldWy!A:A,H11,FieldWy!F:F,"<>",FieldWy!AA:AA,"true") -> 0 | AQ11: =+Q11-AP11 -> 0 | AR11: =+COUNTIFS(FieldWy!A:A,H11,FieldWy!F:F,"<>",FieldWy!X:X,"PORTABILIDAD") -> 0 | AS11: =+U11+AR11 -> 0 | AT11: =+AN11-(AP11+AR11) -> 0 | AU11: =+Y11-AT11 -> 0
A12: SANCHEZ MEZA JOB | B12: EDSON FERREYRA FFLORES | C12: 1 | H12: 2090552 | I12: SUBURBIA - METEPEC | J12: Metepec | K12: SUBURBIA | L12: =+IFERROR(M12/N12,0) -> 0 | M12: =SUM(Altas!E9:AI9) -> 0 | N12: =VLOOKUP(H12,Cuota!$D:$DU,119,0) -> 1.7728415 | O12: =+M12-N12 -> -1.7728415 | P12: =+IFERROR(Q12/R12,0) -> 0 | Q12: =+SUM(Altas!E56:AI56) -> 0 | R12: =VLOOKUP(H12,Tabla2[[#All],[IDPV]:[PP VOZ]],120,0) -> 1.3768696 | S12: =+Q12-R12 -> -1.3768696 | T12: =+IFERROR(U12/V12,0) -> 0 | U12: =+SUM(Altas!E103:AI103) -> 0 | V12: =VLOOKUP(H12,Tabla2[[#All],[IDPV]:[PP VOZ]],121,0) -> 0.120598 | W12: =+U12-V12 -> -0.120598 | X12: =+IFERROR(Y12/Z12,0) -> 0 | Y12: =+M12-(Q12+U12) -> 0 | Z12: =VLOOKUP(H12,Tabla2[[#All],[IDPV]:[PP VOZ]],122,0) -> 0.27537392 | AA12: =+Y12-Z12 -> -0.27537392 | AB12: =+M12/$F$3 -> 0 | AC12: =+N12/$F$3 -> 1.7728415 | AD12: =+AB12-AC12 -> -1.7728415 | AE12: =+Q12/$F$3 -> 0 | AF12: =+R12/$F$3 -> 1.3768696 | AG12: =+AE12-AF12 -> -1.3768696 | AH12: =+U12/$F$3 -> 0 | AI12: =+V12/$F$3 -> 0.120598 | AJ12: =+AH12-AI12 -> -0.120598 | AN12: =+COUNTIFS(FieldWy!A:A,H12,FieldWy!F:F,"<>") -> 0 | AO12: =+M12-AN12 -> 0 | AP12: =+COUNTIFS(FieldWy!A:A,H12,FieldWy!F:F,"<>",FieldWy!AA:AA,"true") -> 0 | AQ12: =+Q12-AP12 -> 0 | AR12: =+COUNTIFS(FieldWy!A:A,H12,FieldWy!F:F,"<>",FieldWy!X:X,"PORTABILIDAD") -> 0 | AS12: =+U12+AR12 -> 0 | AT12: =+AN12-(AP12+AR12) -> 0 | AU12: =+Y12-AT12 -> 0
A13: SANCHEZ MEZA JOB | B13: EDGAR RAUL HERNANDEZ CERVANTES | C13: 1 | H13: 2090559 | I13: SUBURBIA - GRAN PLAZA | J13: Toluca de Lerdo | K13: SUBURBIA | L13: =+IFERROR(M13/N13,0) -> 0 | M13: =SUM(Altas!E10:AI10) -> 0 | N13: =VLOOKUP(H13,Cuota!$D:$DU,119,0) -> 1.9105285 | O13: =+M13-N13 -> -1.9105285 | P13: =+IFERROR(Q13/R13,0) -> 0 | Q13: =+SUM(Altas!E57:AI57) -> 0 | R13: =VLOOKUP(H13,Tabla2[[#All],[IDPV]:[PP VOZ]],120,0) -> 1.1014957 | S13: =+Q13-R13 -> -1.1014957 | T13: =+IFERROR(U13/V13,0) -> 0 | U13: =+SUM(Altas!E104:AI104) -> 0 | V13: =VLOOKUP(H13,Tabla2[[#All],[IDPV]:[PP VOZ]],121,0) -> 0.120598 | W13: =+U13-V13 -> -0.120598 | X13: =+IFERROR(Y13/Z13,0) -> 0 | Y13: =+M13-(Q13+U13) -> 0 | Z13: =VLOOKUP(H13,Tabla2[[#All],[IDPV]:[PP VOZ]],122,0) -> 0.68843479 | AA13: =+Y13-Z13 -> -0.68843479 | AB13: =+M13/$F$3 -> 0 | AC13: =+N13/$F$3 -> 1.9105285 | AD13: =+AB13-AC13 -> -1.9105285 | AE13: =+Q13/$F$3 -> 0 | AF13: =+R13/$F$3 -> 1.1014957 | AG13: =+AE13-AF13 -> -1.1014957 | AH13: =+U13/$F$3 -> 0 | AI13: =+V13/$F$3 -> 0.120598 | AJ13: =+AH13-AI13 -> -0.120598 | AN13: =+COUNTIFS(FieldWy!A:A,H13,FieldWy!F:F,"<>") -> 0 | AO13: =+M13-AN13 -> 0 | AP13: =+COUNTIFS(FieldWy!A:A,H13,FieldWy!F:F,"<>",FieldWy!AA:AA,"true") -> 0 | AQ13: =+Q13-AP13 -> 0 | AR13: =+COUNTIFS(FieldWy!A:A,H13,FieldWy!F:F,"<>",FieldWy!X:X,"PORTABILIDAD") -> 0 | AS13: =+U13+AR13 -> 0 | AT13: =+AN13-(AP13+AR13) -> 0 | AU13: =+Y13-AT13 -> 0
A14: REYES ZARRABAL CRISTOPHER | B14: CESAR GARRIDO BADILLO | C14: 1 | D14: 10 Pdvs 20 y 21 Jun | E14: Aumento de productividad | F14: Mas de 100 dias Inv | G14: Estable | H14: 2090618 | I14: COPPEL UNIVERSIDAD | J14: PACHUCA | K14: Coppel | L14: =+IFERROR(M14/N14,0) -> 0 | M14: =SUM(Altas!E11:AI11) -> 0 | N14: =VLOOKUP(H14,Cuota!$D:$DU,119,0) -> 2.3235893 | O14: =+M14-N14 -> -2.3235893 | P14: =+IFERROR(Q14/R14,0) -> 0 | Q14: =+SUM(Altas!E58:AI58) -> 0 | R14: =VLOOKUP(H14,Tabla2[[#All],[IDPV]:[PP VOZ]],120,0) -> 1.1014957 | S14: =+Q14-R14 -> -1.1014957 | T14: =+IFERROR(U14/V14,0) -> 0 | U14: =+SUM(Altas!E105:AI105) -> 0 | V14: =VLOOKUP(H14,Tabla2[[#All],[IDPV]:[PP VOZ]],121,0) -> 0.120598 | W14: =+U14-V14 -> -0.120598 | X14: =+IFERROR(Y14/Z14,0) -> 0 | Y14: =+M14-(Q14+U14) -> 0 | Z14: =VLOOKUP(H14,Tabla2[[#All],[IDPV]:[PP VOZ]],122,0) -> 1.1014957 | AA14: =+Y14-Z14 -> -1.1014957 | AB14: =+M14/$F$3 -> 0 | AC14: =+N14/$F$3 -> 2.3235893 | AD14: =+AB14-AC14 -> -2.3235893 | AE14: =+Q14/$F$3 -> 0 | AF14: =+R14/$F$3 -> 1.1014957 | AG14: =+AE14-AF14 -> -1.1014957 | AH14: =+U14/$F$3 -> 0 | AI14: =+V14/$F$3 -> 0.120598 | AJ14: =+AH14-AI14 -> -0.120598 | AK14: =+Y14/#REF! -> #REF! | AL14: =+Z14/#REF! -> #REF! | AM14: =+AK14-AL14 -> #REF! | AN14: =+COUNTIFS(FieldWy!A:A,H14,FieldWy!F:F,"<>") -> 0 | AO14: =+M14-AN14 -> 0 | AP14: =+COUNTIFS(FieldWy!A:A,H14,FieldWy!F:F,"<>",FieldWy!AA:AA,"true") -> 0 | AQ14: =+Q14-AP14 -> 0 | AR14: =+COUNTIFS(FieldWy!A:A,H14,FieldWy!F:F,"<>",FieldWy!X:X,"PORTABILIDAD") -> 0 | AS14: =+U14+AR14 -> 0 | AT14: =+AN14-(AP14+AR14) -> 0 | AU14: =+Y14-AT14 -> 0
A15: SANCHEZ MEZA JOB | B15: ERIK ALEJANDRO GARCIA | C15: 1 | H15: 2090742 | I15: COPPEL SENDERO | J15: Lerma | K15: COPPEL | L15: =+IFERROR(M15/N15,0) -> 0 | M15: =SUM(Altas!E12:AI12) -> 0 | N15: =VLOOKUP(H15,Cuota!$D:$DU,119,0) -> 3.9587439 | O15: =+M15-N15 -> -3.9587439 | P15: =+IFERROR(Q15/R15,0) -> 0 | Q15: =+SUM(Altas!E59:AI59) -> 0 | R15: =VLOOKUP(H15,Tabla2[[#All],[IDPV]:[PP VOZ]],120,0) -> 2.4783653 | S15: =+Q15-R15 -> -2.4783653 | T15: =+IFERROR(U15/V15,0) -> 0 | U15: =+SUM(Altas!E106:AI106) -> 0 | V15: =VLOOKUP(H15,Tabla2[[#All],[IDPV]:[PP VOZ]],121,0) -> 0.241196 | W15: =+U15-V15 -> -0.241196 | X15: =+IFERROR(Y15/Z15,0) -> 0 | Y15: =+M15-(Q15+U15) -> 0 | Z15: =VLOOKUP(H15,Tabla2[[#All],[IDPV]:[PP VOZ]],122,0) -> 1.2391826 | AA15: =+Y15-Z15 -> -1.2391826 | AB15: =+M15/$F$3 -> 0 | AC15: =+N15/$F$3 -> 3.9587439 | AD15: =+AB15-AC15 -> -3.9587439 | AE15: =+Q15/$F$3 -> 0 | AF15: =+R15/$F$3 -> 2.4783653 | AG15: =+AE15-AF15 -> -2.4783653 | AH15: =+U15/$F$3 -> 0 | AI15: =+V15/$F$3 -> 0.241196 | AJ15: =+AH15-AI15 -> -0.241196 | AN15: =+COUNTIFS(FieldWy!A:A,H15,FieldWy!F:F,"<>") -> 0 | AO15: =+M15-AN15 -> 0 | AP15: =+COUNTIFS(FieldWy!A:A,H15,FieldWy!F:F,"<>",FieldWy!AA:AA,"true") -> 0 | AQ15: =+Q15-AP15 -> 0 | AR15: =+COUNTIFS(FieldWy!A:A,H15,FieldWy!F:F,"<>",FieldWy!X:X,"PORTABILIDAD") -> 0 | AS15: =+U15+AR15 -> 0 | AT15: =+AN15-(AP15+AR15) -> 0 | AU15: =+Y15-AT15 -> 0
A16: REYES ZARRABAL CRISTOPHER | B16: CESAR GARRIDO BADILLO | C16: 1 | D16: Tiendas criticas | G16: Nuevo promotor | H16: 2090749 | I16: COPPEL CARRANZA LA COLCHONERA | J16: PACHUCA | K16: Coppel | L16: =+IFERROR(M16/N16,0) -> 0 | M16: =SUM(Altas!E13:AI13) -> 0 | N16: =VLOOKUP(H16,Cuota!$D:$DU,119,0) -> 2.0482154 | O16: =+M16-N16 -> -2.0482154 | P16: =+IFERROR(Q16/R16,0) -> 0 | Q16: =+SUM(Altas!E60:AI60) -> 0 | R16: =VLOOKUP(H16,Tabla2[[#All],[IDPV]:[PP VOZ]],120,0) -> 0.96380871 | S16: =+Q16-R16 -> -0.96380871 | T16: =+IFERROR(U16/V16,0) -> 0 | U16: =+SUM(Altas!E107:AI107) -> 0 | V16: =VLOOKUP(H16,Tabla2[[#All],[IDPV]:[PP VOZ]],121,0) -> 0.120598 | W16: =+U16-V16 -> -0.120598 | X16: =+IFERROR(Y16/Z16,0) -> 0 | Y16: =+M16-(Q16+U16) -> 0 | Z16: =VLOOKUP(H16,Tabla2[[#All],[IDPV]:[PP VOZ]],122,0) -> 0.96380871 | AA16: =+Y16-Z16 -> -0.96380871 | AB16: =+M16/$F$3 -> 0 | AC16: =+N16/$F$3 -> 2.0482154 | AD16: =+AB16-AC16 -> -2.0482154 | AE16: =+Q16/$F$3 -> 0 | AF16: =+R16/$F$3 -> 0.96380871 | AG16: =+AE16-AF16 -> -0.96380871 | AH16: =+U16/$F$3 -> 0 | AI16: =+V16/$F$3 -> 0.120598 | AJ16: =+AH16-AI16 -> -0.120598 | AK16: =+Y16/#REF! -> #REF! | AL16: =+Z16/#REF! -> #REF! | AM16: =+AK16-AL16 -> #REF! | AN16: =+COUNTIFS(FieldWy!A:A,H16,FieldWy!F:F,"<>") -> 0 | AO16: =+M16-AN16 -> 0 | AP16: =+COUNTIFS(FieldWy!A:A,H16,FieldWy!F:F,"<>",FieldWy!AA:AA,"true") -> 0 | AQ16: =+Q16-AP16 -> 0 | AR16: =+COUNTIFS(FieldWy!A:A,H16,FieldWy!F:F,"<>",FieldWy!X:X,"PORTABILIDAD") -> 0 | AS16: =+U16+AR16 -> 0 | AT16: =+AN16-(AP16+AR16) -> 0 | AU16: =+Y16-AT16 -> 0
A17: SANCHEZ MEZA JOB | B17: ERIK ALEJANDRO GARCIA | C17: 1 | H17: 2090826 | I17: COPPEL CANADA GUADALUPE VICTORIA | J17: Ocoyoacac | K17: COPPEL | L17: =+IFERROR(M17/N17,0) -> 0 | M17: =SUM(Altas!E14:AI14) -> 0 | N17: =VLOOKUP(H17,Cuota!$D:$DU,119,0) -> 1.7728415 | O17: =+M17-N17 -> -1.7728415 | P17: =+IFERROR(Q17/R17,0) -> 0 | Q17: =+SUM(Altas!E61:AI61) -> 0 | R17: =VLOOKUP(H17,Tabla2[[#All],[IDPV]:[PP VOZ]],120,0) -> 1.1014957 | S17: =+Q17-R17 -> -1.1014957 | T17: =+IFERROR(U17/V17,0) -> 0 | U17: =+SUM(Altas!E108:AI108) -> 0 | V17: =VLOOKUP(H17,Tabla2[[#All],[IDPV]:[PP VOZ]],121,0) -> 0.120598 | W17: =+U17-V17 -> -0.120598 | X17: =+IFERROR(Y17/Z17,0) -> 0 | Y17: =+M17-(Q17+U17) -> 0 | Z17: =VLOOKUP(H17,Tabla2[[#All],[IDPV]:[PP VOZ]],122,0) -> 0.55074783 | AA17: =+Y17-Z17 -> -0.55074783 | AB17: =+M17/$F$3 -> 0 | AC17: =+N17/$F$3 -> 1.7728415 | AD17: =+AB17-AC17 -> -1.7728415 | AE17: =+Q17/$F$3 -> 0 | AF17: =+R17/$F$3 -> 1.1014957 | AG17: =+AE17-AF17 -> -1.1014957 | AH17: =+U17/$F$3 -> 0 | AI17: =+V17/$F$3 -> 0.120598 | AJ17: =+AH17-AI17 -> -0.120598 | AN17: =+COUNTIFS(FieldWy!A:A,H17,FieldWy!F:F,"<>") -> 0 | AO17: =+M17-AN17 -> 0 | AP17: =+COUNTIFS(FieldWy!A:A,H17,FieldWy!F:F,"<>",FieldWy!AA:AA,"true") -> 0 | AQ17: =+Q17-AP17 -> 0 | AR17: =+COUNTIFS(FieldWy!A:A,H17,FieldWy!F:F,"<>",FieldWy!X:X,"PORTABILIDAD") -> 0 | AS17: =+U17+AR17 -> 0 | AT17: =+AN17-(AP17+AR17) -> 0 | AU17: =+Y17-AT17 -> 0
A18: REYES ZARRABAL CRISTOPHER | B18: DANIEL BENJAMIN MARQUEZ BACA | C18: 1 | D18: Gestion con Marcas | G18: Nuevo promotor | H18: 2090839 | I18: COPPEL JUAREZ | J18: TIZAYUCA | K18: Coppel | L18: =+IFERROR(M18/N18,0) -> 0 | M18: =SUM(Altas!E15:AI15) -> 0 | N18: =VLOOKUP(H18,Cuota!$D:$DU,119,0) -> 3.68337 | O18: =+M18-N18 -> -3.68337 | P18: =+IFERROR(Q18/R18,0) -> 0 | Q18: =+SUM(Altas!E62:AI62) -> 0 | R18: =VLOOKUP(H18,Tabla2[[#All],[IDPV]:[PP VOZ]],120,0) -> 2.0482154 | S18: =+Q18-R18 -> -2.0482154 | T18: =+IFERROR(U18/V18,0) -> 0 | U18: =+SUM(Altas!E109:AI109) -> 0 | V18: =VLOOKUP(H18,Tabla2[[#All],[IDPV]:[PP VOZ]],121,0) -> 0.241196 | W18: =+U18-V18 -> -0.241196 | X18: =+IFERROR(Y18/Z18,0) -> 0 | Y18: =+M18-(Q18+U18) -> 0 | Z18: =VLOOKUP(H18,Tabla2[[#All],[IDPV]:[PP VOZ]],122,0) -> 1.3939585 | AA18: =+Y18-Z18 -> -1.3939585 | AB18: =+M18/$F$3 -> 0 | AC18: =+N18/$F$3 -> 3.68337 | AD18: =+AB18-AC18 -> -3.68337 | AE18: =+Q18/$F$3 -> 0 | AF18: =+R18/$F$3 -> 2.0482154 | AG18: =+AE18-AF18 -> -2.0482154 | AH18: =+U18/$F$3 -> 0 | AI18: =+V18/$F$3 -> 0.241196 | AJ18: =+AH18-AI18 -> -0.241196 | AK18: =+Y18/#REF! -> #REF! | AL18: =+Z18/#REF! -> #REF! | AM18: =+AK18-AL18 -> #REF! | AN18: =+COUNTIFS(FieldWy!A:A,H18,FieldWy!F:F,"<>") -> 0 | AO18: =+M18-AN18 -> 0 | AP18: =+COUNTIFS(FieldWy!A:A,H18,FieldWy!F:F,"<>",FieldWy!AA:AA,"true") -> 0 | AQ18: =+Q18-AP18 -> 0 | AR18: =+COUNTIFS(FieldWy!A:A,H18,FieldWy!F:F,"<>",FieldWy!X:X,"PORTABILIDAD") -> 0 | AS18: =+U18+AR18 -> 0 | AT18: =+AN18-(AP18+AR18) -> 0 | AU18: =+Y18-AT18 -> 0
A19: REYES ZARRABAL CRISTOPHER | B19: DANIEL BENJAMIN MARQUEZ BACA | C19: 1 | D19: Tiendas criticas | E19: Arranque rapido | F19: Mas de 100 dias Inv | G19: Nuevo promotor | H19: 2090872 | I19: COPPEL LAS VILLAS | J19: PACHUCA | K19: Coppel | L19: =+IFERROR(M19/N19,0) -> 0 | M19: =SUM(Altas!E16:AI16) -> 0 | N19: =VLOOKUP(H19,Cuota!$D:$DU,119,0) -> 2.0482154 | O19: =+M19-N19 -> -2.0482154 | P19: =+IFERROR(Q19/R19,0) -> 0 | Q19: =+SUM(Altas!E63:AI63) -> 0 | R19: =VLOOKUP(H19,Tabla2[[#All],[IDPV]:[PP VOZ]],120,0) -> 1.1014957 | S19: =+Q19-R19 -> -1.1014957 | T19: =+IFERROR(U19/V19,0) -> 0 | U19: =+SUM(Altas!E110:AI110) -> 0 | V19: =VLOOKUP(H19,Tabla2[[#All],[IDPV]:[PP VOZ]],121,0) -> 0.120598 | W19: =+U19-V19 -> -0.120598 | X19: =+IFERROR(Y19/Z19,0) -> 0 | Y19: =+M19-(Q19+U19) -> 0 | Z19: =VLOOKUP(H19,Tabla2[[#All],[IDPV]:[PP VOZ]],122,0) -> 0.82612175 | AA19: =+Y19-Z19 -> -0.82612175 | AB19: =+M19/$F$3 -> 0 | AC19: =+N19/$F$3 -> 2.0482154 | AD19: =+AB19-AC19 -> -2.0482154 | AE19: =+Q19/$F$3 -> 0 | AF19: =+R19/$F$3 -> 1.1014957 | AG19: =+AE19-AF19 -> -1.1014957 | AH19: =+U19/$F$3 -> 0 | AI19: =+V19/$F$3 -> 0.120598 | AJ19: =+AH19-AI19 -> -0.120598 | AK19: =+Y19/#REF! -> #REF! | AL19: =+Z19/#REF! -> #REF! | AM19: =+AK19-AL19 -> #REF! | AN19: =+COUNTIFS(FieldWy!A:A,H19,FieldWy!F:F,"<>") -> 0 | AO19: =+M19-AN19 -> 0 | AP19: =+COUNTIFS(FieldWy!A:A,H19,FieldWy!F:F,"<>",FieldWy!AA:AA,"true") -> 0 | AQ19: =+Q19-AP19 -> 0 | AR19: =+COUNTIFS(FieldWy!A:A,H19,FieldWy!F:F,"<>",FieldWy!X:X,"PORTABILIDAD") -> 0 | AS19: =+U19+AR19 -> 0 | AT19: =+AN19-(AP19+AR19) -> 0 | AU19: =+Y19-AT19 -> 0
A20: CUEVAS OCAÑA ALMA ROSA | B20: JOSE JAEN OSORIO PAGUIA | C20: 1 | H20: 2090875 | I20: COPPEL JUAREZ (IXTLAHUCA) | J20: Ixtlahuaca | K20: COPPEL | L20: =+IFERROR(M20/N20,0) -> 0 | M20: =SUM(Altas!E17:AI17) -> 0 | N20: =VLOOKUP(H20,Cuota!$D:$DU,119,0) -> 3.442174 | O20: =+M20-N20 -> -3.442174 | P20: =+IFERROR(Q20/R20,0) -> 0 | Q20: =+SUM(Altas!E64:AI64) -> 0 | R20: =VLOOKUP(H20,Tabla2[[#All],[IDPV]:[PP VOZ]],120,0) -> 2.2029913 | S20: =+Q20-R20 -> -2.2029913 | T20: =+IFERROR(U20/V20,0) -> 0 | U20: =+SUM(Altas!E111:AI111) -> 496 | V20: =VLOOKUP(H20,Tabla2[[#All],[IDPV]:[PP VOZ]],121,0) -> 0 | W20: =+U20-V20 -> 496 | X20: =+IFERROR(Y20/Z20,0) -> -400.26384 | Y20: =+M20-(Q20+U20) -> -496 | Z20: =VLOOKUP(H20,Tabla2[[#All],[IDPV]:[PP VOZ]],122,0) -> 1.2391826 | AA20: =+Y20-Z20 -> -497.23918 | AB20: =+M20/$F$3 -> 0 | AC20: =+N20/$F$3 -> 3.442174 | AD20: =+AB20-AC20 -> -3.442174 | AE20: =+Q20/$F$3 -> 0 | AF20: =+R20/$F$3 -> 2.2029913 | AG20: =+AE20-AF20 -> -2.2029913 | AH20: =+U20/$F$3 -> 496 | AI20: =+V20/$F$3 -> 0 | AJ20: =+AH20-AI20 -> 496 | AN20: =+COUNTIFS(FieldWy!A:A,H20,FieldWy!F:F,"<>") -> 0 | AO20: =+M20-AN20 -> 0 | AP20: =+COUNTIFS(FieldWy!A:A,H20,FieldWy!F:F,"<>",FieldWy!AA:AA,"true") -> 0 | AQ20: =+Q20-AP20 -> 0 | AR20: =+COUNTIFS(FieldWy!A:A,H20,FieldWy!F:F,"<>",FieldWy!X:X,"PORTABILIDAD") -> 0 | AS20: =+U20+AR20 -> 496 | AT20: =+AN20-(AP20+AR20) -> 0 | AU20: =+Y20-AT20 -> -496
A21: SANCHEZ MEZA JOB | B21: EDGAR RAUL HERNANDEZ CERVANTES | C21: 1 | H21: 2090892 | I21: COPPEL CANADA RAYÓN | J21: Toluca de Lerdo | K21: COPPEL | L21: =+IFERROR(M21/N21,0) -> 0 | M21: =SUM(Altas!E18:AI18) -> 0 | N21: =VLOOKUP(H21,Cuota!$D:$DU,119,0) -> 1.9105285 | O21: =+M21-N21 -> -1.9105285 | P21: =+IFERROR(Q21/R21,0) -> 0 | Q21: =+SUM(Altas!E65:AI65) -> 0 | R21: =VLOOKUP(H21,Tabla2[[#All],[IDPV]:[PP VOZ]],120,0) -> 1.1014957 | S21: =+Q21-R21 -> -1.1014957 | T21: =+IFERROR(U21/V21,0) -> 0 | U21: =+SUM(Altas!E112:AI112) -> 0 | V21: =VLOOKUP(H21,Tabla2[[#All],[IDPV]:[PP VOZ]],121,0) -> 0.120598 | W21: =+U21-V21 -> -0.120598 | X21: =+IFERROR(Y21/Z21,0) -> 0 | Y21: =+M21-(Q21+U21) -> 0 | Z21: =VLOOKUP(H21,Tabla2[[#All],[IDPV]:[PP VOZ]],122,0) -> 0.68843479 | AA21: =+Y21-Z21 -> -0.68843479 | AB21: =+M21/$F$3 -> 0 | AC21: =+N21/$F$3 -> 1.9105285 | AD21: =+AB21-AC21 -> -1.9105285 | AE21: =+Q21/$F$3 -> 0 | AF21: =+R21/$F$3 -> 1.1014957 | AG21: =+AE21-AF21 -> -1.1014957 | AH21: =+U21/$F$3 -> 0 | AI21: =+V21/$F$3 -> 0.120598 | AJ21: =+AH21-AI21 -> -0.120598 | AN21: =+COUNTIFS(FieldWy!A:A,H21,FieldWy!F:F,"<>") -> 0 | AO21: =+M21-AN21 -> 0 | AP21: =+COUNTIFS(FieldWy!A:A,H21,FieldWy!F:F,"<>",FieldWy!AA:AA,"true") -> 0 | AQ21: =+Q21-AP21 -> 0 | AR21: =+COUNTIFS(FieldWy!A:A,H21,FieldWy!F:F,"<>",FieldWy!X:X,"PORTABILIDAD") -> 0 | AS21: =+U21+AR21 -> 0 | AT21: =+AN21-(AP21+AR21) -> 0 | AU21: =+Y21-AT21 -> 0
A22: SANCHEZ MEZA JOB | B22: EDGAR RAUL HERNANDEZ CERVANTES | C22: 1 | H22: 2090893 | I22: COPPEL PLAZA HIDALGO | J22: Toluca de Lerdo | K22: COPPEL | L22: =+IFERROR(M22/N22,0) -> 0 | M22: =SUM(Altas!E19:AI19) -> 0 | N22: =VLOOKUP(H22,Cuota!$D:$DU,119,0) -> 1.9105285 | O22: =+M22-N22 -> -1.9105285 | P22: =+IFERROR(Q22/R22,0) -> 0 | Q22: =+SUM(Altas!E66:AI66) -> 0 | R22: =VLOOKUP(H22,Tabla2[[#All],[IDPV]:[PP VOZ]],120,0) -> 1.1014957 | S22: =+Q22-R22 -> -1.1014957 | T22: =+IFERROR(U22/V22,0) -> 0 | U22: =+SUM(Altas!E113:AI113) -> 0 | V22: =VLOOKUP(H22,Tabla2[[#All],[IDPV]:[PP VOZ]],121,0) -> 0.120598 | W22: =+U22-V22 -> -0.120598 | X22: =+IFERROR(Y22/Z22,0) -> 0 | Y22: =+M22-(Q22+U22) -> 0 | Z22: =VLOOKUP(H22,Tabla2[[#All],[IDPV]:[PP VOZ]],122,0) -> 0.68843479 | AA22: =+Y22-Z22 -> -0.68843479 | AB22: =+M22/$F$3 -> 0 | AC22: =+N22/$F$3 -> 1.9105285 | AD22: =+AB22-AC22 -> -1.9105285 | AE22: =+Q22/$F$3 -> 0 | AF22: =+R22/$F$3 -> 1.1014957 | AG22: =+AE22-AF22 -> -1.1014957 | AH22: =+U22/$F$3 -> 0 | AI22: =+V22/$F$3 -> 0.120598 | AJ22: =+AH22-AI22 -> -0.120598 | AN22: =+COUNTIFS(FieldWy!A:A,H22,FieldWy!F:F,"<>") -> 0 | AO22: =+M22-AN22 -> 0 | AP22: =+COUNTIFS(FieldWy!A:A,H22,FieldWy!F:F,"<>",FieldWy!AA:AA,"true") -> 0 | AQ22: =+Q22-AP22 -> 0 | AR22: =+COUNTIFS(FieldWy!A:A,H22,FieldWy!F:F,"<>",FieldWy!X:X,"PORTABILIDAD") -> 0 | AS22: =+U22+AR22 -> 0 | AT22: =+AN22-(AP22+AR22) -> 0 | AU22: =+Y22-AT22 -> 0
A23: REYES ZARRABAL CRISTOPHER | B23: JIOBANI MARIN BUENDIA BARCENAS | C23: 1 | D23: 10 tiendas 90 al 100% | E23: Motorola | G23: Estable | H23: 2090912 | I23: COPPEL PLAZA TULA | J23: TULA DE ALLENDE | K23: Coppel | L23: =+IFERROR(M23/N23,0) -> 0 | M23: =SUM(Altas!E20:AI20) -> 0 | N23: =VLOOKUP(H23,Cuota!$D:$DU,119,0) -> 3.2703091 | O23: =+M23-N23 -> -3.2703091 | P23: =+IFERROR(Q23/R23,0) -> 0 | Q23: =+SUM(Altas!E67:AI67) -> 0 | R23: =VLOOKUP(H23,Tabla2[[#All],[IDPV]:[PP VOZ]],120,0) -> 1.3768696 | S23: =+Q23-R23 -> -1.3768696 | T23: =+IFERROR(U23/V23,0) -> 0 | U23: =+SUM(Altas!E114:AI114) -> 0 | V23: =VLOOKUP(H23,Tabla2[[#All],[IDPV]:[PP VOZ]],121,0) -> 0.241196 | W23: =+U23-V23 -> -0.241196 | X23: =+IFERROR(Y23/Z23,0) -> 0 | Y23: =+M23-(Q23+U23) -> 0 | Z23: =VLOOKUP(H23,Tabla2[[#All],[IDPV]:[PP VOZ]],122,0) -> 1.6522435 | AA23: =+Y23-Z23 -> -1.6522435 | AB23: =+M23/$F$3 -> 0 | AC23: =+N23/$F$3 -> 3.2703091 | AD23: =+AB23-AC23 -> -3.2703091 | AE23: =+Q23/$F$3 -> 0 | AF23: =+R23/$F$3 -> 1.3768696 | AG23: =+AE23-AF23 -> -1.3768696 | AH23: =+U23/$F$3 -> 0 | AI23: =+V23/$F$3 -> 0.241196 | AJ23: =+AH23-AI23 -> -0.241196 | AK23: =+Y23/#REF! -> #REF! | AL23: =+Z23/#REF! -> #REF! | AM23: =+AK23-AL23 -> #REF! | AN23: =+COUNTIFS(FieldWy!A:A,H23,FieldWy!F:F,"<>") -> 0 | AO23: =+M23-AN23 -> 0 | AP23: =+COUNTIFS(FieldWy!A:A,H23,FieldWy!F:F,"<>",FieldWy!AA:AA,"true") -> 0 | AQ23: =+Q23-AP23 -> 0 | AR23: =+COUNTIFS(FieldWy!A:A,H23,FieldWy!F:F,"<>",FieldWy!X:X,"PORTABILIDAD") -> 0 | AS23: =+U23+AR23 -> 0 | AT23: =+AN23-(AP23+AR23) -> 0 | AU23: =+Y23-AT23 -> 0
A24: REYES ZARRABAL CRISTOPHER | B24: DANIEL BENJAMIN MARQUEZ BACA | C24: 1 | D24: 10 Pdvs 20 y 21 Jun | E24: Aumento de productividad | G24: Estable | H24: 2090913 | I24: COPPEL CANADA PLAZA BONITA | J24: TIZAYUCA | K24: Coppel | L24: =+IFERROR(M24/N24,0) -> 0 | M24: =SUM(Altas!E21:AI21) -> 0 | N24: =VLOOKUP(H24,Cuota!$D:$DU,119,0) -> 3.2703091 | O24: =+M24-N24 -> -3.2703091 | P24: =+IFERROR(Q24/R24,0) -> 0 | Q24: =+SUM(Altas!E68:AI68) -> 0 | R24: =VLOOKUP(H24,Tabla2[[#All],[IDPV]:[PP VOZ]],120,0) -> 2.0482154 | S24: =+Q24-R24 -> -2.0482154 | T24: =+IFERROR(U24/V24,0) -> 0 | U24: =+SUM(Altas!E115:AI115) -> 0 | V24: =VLOOKUP(H24,Tabla2[[#All],[IDPV]:[PP VOZ]],121,0) -> 0.241196 | W24: =+U24-V24 -> -0.241196 | X24: =+IFERROR(Y24/Z24,0) -> 0 | Y24: =+M24-(Q24+U24) -> 0 | Z24: =VLOOKUP(H24,Tabla2[[#All],[IDPV]:[PP VOZ]],122,0) -> 0.98089767 | AA24: =+Y24-Z24 -> -0.98089767 | AB24: =+M24/$F$3 -> 0 | AC24: =+N24/$F$3 -> 3.2703091 | AD24: =+AB24-AC24 -> -3.2703091 | AE24: =+Q24/$F$3 -> 0 | AF24: =+R24/$F$3 -> 2.0482154 | AG24: =+AE24-AF24 -> -2.0482154 | AH24: =+U24/$F$3 -> 0 | AI24: =+V24/$F$3 -> 0.241196 | AJ24: =+AH24-AI24 -> -0.241196 | AK24: =+Y24/#REF! -> #REF! | AL24: =+Z24/#REF! -> #REF! | AM24: =+AK24-AL24 -> #REF! | AN24: =+COUNTIFS(FieldWy!A:A,H24,FieldWy!F:F,"<>") -> 0 | AO24: =+M24-AN24 -> 0 | AP24: =+COUNTIFS(FieldWy!A:A,H24,FieldWy!F:F,"<>",FieldWy!AA:AA,"true") -> 0 | AQ24: =+Q24-AP24 -> 0 | AR24: =+COUNTIFS(FieldWy!A:A,H24,FieldWy!F:F,"<>",FieldWy!X:X,"PORTABILIDAD") -> 0 | AS24: =+U24+AR24 -> 0 | AT24: =+AN24-(AP24+AR24) -> 0 | AU24: =+Y24-AT24 -> 0
A25: REYES ZARRABAL CRISTOPHER | B25: DANIEL BENJAMIN MARQUEZ BACA | C25: 1 | D25: Tiendas criticas | G25: Vacante | H25: 2090932 | I25: ELEKTRA ACTOPAN HIDALGO | J25: ACTOPAN | K25: Elektra | L25: =+IFERROR(M25/N25,0) -> 0 | M25: =SUM(Altas!E22:AI22) -> 0 | N25: =VLOOKUP(H25,Cuota!$D:$DU,119,0) -> 0.94671975 | O25: =+M25-N25 -> -0.94671975 | P25: =+IFERROR(Q25/R25,0) -> 0 | Q25: =+SUM(Altas!E69:AI69) -> 0 | R25: =VLOOKUP(H25,Tabla2[[#All],[IDPV]:[PP VOZ]],120,0) -> 0.41306088 | S25: =+Q25-R25 -> -0.41306088 | T25: =+IFERROR(U25/V25,0) -> 0 | U25: =+SUM(Altas!E116:AI116) -> 0 | V25: =VLOOKUP(H25,Tabla2[[#All],[IDPV]:[PP VOZ]],121,0) -> 0.120598 | W25: =+U25-V25 -> -0.120598 | X25: =+IFERROR(Y25/Z25,0) -> 0 | Y25: =+M25-(Q25+U25) -> 0 | Z25: =VLOOKUP(H25,Tabla2[[#All],[IDPV]:[PP VOZ]],122,0) -> 0.41306088 | AA25: =+Y25-Z25 -> -0.41306088 | AB25: =+M25/$F$3 -> 0 | AC25: =+N25/$F$3 -> 0.94671975 | AD25: =+AB25-AC25 -> -0.94671975 | AE25: =+Q25/$F$3 -> 0 | AF25: =+R25/$F$3 -> 0.41306088 | AG25: =+AE25-AF25 -> -0.41306088 | AH25: =+U25/$F$3 -> 0 | AI25: =+V25/$F$3 -> 0.120598 | AJ25: =+AH25-AI25 -> -0.120598 | AK25: =+Y25/#REF! -> #REF! | AL25: =+Z25/#REF! -> #REF! | AM25: =+AK25-AL25 -> #REF! | AN25: =+COUNTIFS(FieldWy!A:A,H25,FieldWy!F:F,"<>") -> 0 | AO25: =+M25-AN25 -> 0 | AP25: =+COUNTIFS(FieldWy!A:A,H25,FieldWy!F:F,"<>",FieldWy!AA:AA,"true") -> 0 | AQ25: =+Q25-AP25 -> 0 | AR25: =+COUNTIFS(FieldWy!A:A,H25,FieldWy!F:F,"<>",FieldWy!X:X,"PORTABILIDAD") -> 0 | AS25: =+U25+AR25 -> 0 | AT25: =+AN25-(AP25+AR25) -> 0 | AU25: =+Y25-AT25 -> 0
A26: REYES ZARRABAL CRISTOPHER | B26: JIOBANI MARIN BUENDIA BARCENAS | C26: 1 | D26: 10 Pdvs 20 y 21 Jun | E26: Mejorar cobertura | G26: Vacante | H26: 2090937 | I26: COPPEL CANADA TULA | J26: TULA DE ALLENDE | K26: Coppel | L26: =+IFERROR(M26/N26,0) -> 0 | M26: =SUM(Altas!E23:AI23) -> 0 | N26: =VLOOKUP(H26,Cuota!$D:$DU,119,0) -> 2.9949352 | O26: =+M26-N26 -> -2.9949352 | P26: =+IFERROR(Q26/R26,0) -> 0 | Q26: =+SUM(Altas!E70:AI70) -> 0 | R26: =VLOOKUP(H26,Tabla2[[#All],[IDPV]:[PP VOZ]],120,0) -> 1.6522435 | S26: =+Q26-R26 -> -1.6522435 | T26: =+IFERROR(U26/V26,0) -> 0 | U26: =+SUM(Altas!E117:AI117) -> 0 | V26: =VLOOKUP(H26,Tabla2[[#All],[IDPV]:[PP VOZ]],121,0) -> 0.241196 | W26: =+U26-V26 -> -0.241196 | X26: =+IFERROR(Y26/Z26,0) -> 0 | Y26: =+M26-(Q26+U26) -> 0 | Z26: =VLOOKUP(H26,Tabla2[[#All],[IDPV]:[PP VOZ]],122,0) -> 1.1014957 | AA26: =+Y26-Z26 -> -1.1014957 | AB26: =+M26/$F$3 -> 0 | AC26: =+N26/$F$3 -> 2.9949352 | AD26: =+AB26-AC26 -> -2.9949352 | AE26: =+Q26/$F$3 -> 0 | AF26: =+R26/$F$3 -> 1.6522435 | AG26: =+AE26-AF26 -> -1.6522435 | AH26: =+U26/$F$3 -> 0 | AI26: =+V26/$F$3 -> 0.241196 | AJ26: =+AH26-AI26 -> -0.241196 | AK26: =+Y26/#REF! -> #REF! | AL26: =+Z26/#REF! -> #REF! | AM26: =+AK26-AL26 -> #REF! | AN26: =+COUNTIFS(FieldWy!A:A,H26,FieldWy!F:F,"<>") -> 0 | AO26: =+M26-AN26 -> 0 | AP26: =+COUNTIFS(FieldWy!A:A,H26,FieldWy!F:F,"<>",FieldWy!AA:AA,"true") -> 0 | AQ26: =+Q26-AP26 -> 0 | AR26: =+COUNTIFS(FieldWy!A:A,H26,FieldWy!F:F,"<>",FieldWy!X:X,"PORTABILIDAD") -> 0 | AS26: =+U26+AR26 -> 0 | AT26: =+AN26-(AP26+AR26) -> 0 | AU26: =+Y26-AT26 -> 0
A27: REYES ZARRABAL CRISTOPHER | B27: JIOBANI MARIN BUENDIA BARCENAS | C27: 1 | D27: Gestion con Marcas | G27: Nuevo promotor | H27: 2090947 | I27: COPPEL REVOLUCIÓN | J27: TULA DE ALLENDE | K27: Coppel | L27: =+IFERROR(M27/N27,0) -> 0 | M27: =SUM(Altas!E24:AI24) -> 0 | N27: =VLOOKUP(H27,Cuota!$D:$DU,119,0) -> 3.666281 | O27: =+M27-N27 -> -3.666281 | P27: =+IFERROR(Q27/R27,0) -> 0 | Q27: =+SUM(Altas!E71:AI71) -> 0 | R27: =VLOOKUP(H27,Tabla2[[#All],[IDPV]:[PP VOZ]],120,0) -> 2.0653044 | S27: =+Q27-R27 -> -2.0653044 | T27: =+IFERROR(U27/V27,0) -> 0 | U27: =+SUM(Altas!E118:AI118) -> 0 | V27: =VLOOKUP(H27,Tabla2[[#All],[IDPV]:[PP VOZ]],121,0) -> 0.361794 | W27: =+U27-V27 -> -0.361794 | X27: =+IFERROR(Y27/Z27,0) -> 0 | Y27: =+M27-(Q27+U27) -> 0 | Z27: =VLOOKUP(H27,Tabla2[[#All],[IDPV]:[PP VOZ]],122,0) -> 1.2391826 | AA27: =+Y27-Z27 -> -1.2391826 | AB27: =+M27/$F$3 -> 0 | AC27: =+N27/$F$3 -> 3.666281 | AD27: =+AB27-AC27 -> -3.666281 | AE27: =+Q27/$F$3 -> 0 | AF27: =+R27/$F$3 -> 2.0653044 | AG27: =+AE27-AF27 -> -2.0653044 | AH27: =+U27/$F$3 -> 0 | AI27: =+V27/$F$3 -> 0.361794 | AJ27: =+AH27-AI27 -> -0.361794 | AK27: =+Y27/#REF! -> #REF! | AL27: =+Z27/#REF! -> #REF! | AM27: =+AK27-AL27 -> #REF! | AN27: =+COUNTIFS(FieldWy!A:A,H27,FieldWy!F:F,"<>") -> 0 | AO27: =+M27-AN27 -> 0 | AP27: =+COUNTIFS(FieldWy!A:A,H27,FieldWy!F:F,"<>",FieldWy!AA:AA,"true") -> 0 | AQ27: =+Q27-AP27 -> 0 | AR27: =+COUNTIFS(FieldWy!A:A,H27,FieldWy!F:F,"<>",FieldWy!X:X,"PORTABILIDAD") -> 0 | AS27: =+U27+AR27 -> 0 | AT27: =+AN27-(AP27+AR27) -> 0 | AU27: =+Y27-AT27 -> 0
A28: BARRIENTOS CONTRERAS ILEANA | B28: CESAR GARRIDO BADILLO | C28: 1 | D28: 10 Pdvs 20 y 21 Jun | E28: Mejorar cobertura | G28: Vacante | H28: 2090997 | I28: COPPEL 21 DE MARZO | J28: PACHUCA | K28: Coppel | L28: =+IFERROR(M28/N28,0) -> 0 | M28: =SUM(Altas!E25:AI25) -> 0 | N28: =VLOOKUP(H28,Cuota!$D:$DU,119,0) -> 4.2341178 | O28: =+M28-N28 -> -4.2341178 | P28: =+IFERROR(Q28/R28,0) -> 0 | Q28: =+SUM(Altas!E72:AI72) -> 0 | R28: =VLOOKUP(H28,Tabla2[[#All],[IDPV]:[PP VOZ]],120,0) -> 2.3235893 | S28: =+Q28-R28 -> -2.3235893 | T28: =+IFERROR(U28/V28,0) -> 0 | U28: =+SUM(Altas!E119:AI119) -> 0 | V28: =VLOOKUP(H28,Tabla2[[#All],[IDPV]:[PP VOZ]],121,0) -> 0.241196 | W28: =+U28-V28 -> -0.241196 | X28: =+IFERROR(Y28/Z28,0) -> 0 | Y28: =+M28-(Q28+U28) -> 0 | Z28: =VLOOKUP(H28,Tabla2[[#All],[IDPV]:[PP VOZ]],122,0) -> 1.6693325 | AA28: =+Y28-Z28 -> -1.6693325 | AB28: =+M28/$F$3 -> 0 | AC28: =+N28/$F$3 -> 4.2341178 | AD28: =+AB28-AC28 -> -4.2341178 | AE28: =+Q28/$F$3 -> 0 | AF28: =+R28/$F$3 -> 2.3235893 | AG28: =+AE28-AF28 -> -2.3235893 | AH28: =+U28/$F$3 -> 0 | AI28: =+V28/$F$3 -> 0.241196 | AJ28: =+AH28-AI28 -> -0.241196 | AK28: =+Y28/#REF! -> #REF! | AL28: =+Z28/#REF! -> #REF! | AM28: =+AK28-AL28 -> #REF! | AN28: =+COUNTIFS(FieldWy!A:A,H28,FieldWy!F:F,"<>") -> 0 | AO28: =+M28-AN28 -> 0 | AP28: =+COUNTIFS(FieldWy!A:A,H28,FieldWy!F:F,"<>",FieldWy!AA:AA,"true") -> 0 | AQ28: =+Q28-AP28 -> 0 | AR28: =+COUNTIFS(FieldWy!A:A,H28,FieldWy!F:F,"<>",FieldWy!X:X,"PORTABILIDAD") -> 0 | AS28: =+U28+AR28 -> 0 | AT28: =+AN28-(AP28+AR28) -> 0 | AU28: =+Y28-AT28 -> 0
A29: REYES ZARRABAL CRISTOPHER | B29: DANIEL BENJAMIN MARQUEZ BACA | C29: 1 | G29: Nuevo promotor | H29: 2091007 | I29: COPPEL CANADA ACTOPAN | J29: ACTOPAN | K29: Coppel | L29: =+IFERROR(M29/N29,0) -> 0 | M29: =SUM(Altas!E26:AI26) -> 0 | N29: =VLOOKUP(H29,Cuota!$D:$DU,119,0) -> 2.9949352 | O29: =+M29-N29 -> -2.9949352 | P29: =+IFERROR(Q29/R29,0) -> 0 | Q29: =+SUM(Altas!E73:AI73) -> 0 | R29: =VLOOKUP(H29,Tabla2[[#All],[IDPV]:[PP VOZ]],120,0) -> 1.6351545 | S29: =+Q29-R29 -> -1.6351545 | T29: =+IFERROR(U29/V29,0) -> 0 | U29: =+SUM(Altas!E120:AI120) -> 0 | V29: =VLOOKUP(H29,Tabla2[[#All],[IDPV]:[PP VOZ]],121,0) -> 0.241196 | W29: =+U29-V29 -> -0.241196 | X29: =+IFERROR(Y29/Z29,0) -> 0 | Y29: =+M29-(Q29+U29) -> 0 | Z29: =VLOOKUP(H29,Tabla2[[#All],[IDPV]:[PP VOZ]],122,0) -> 1.1185846 | AA29: =+Y29-Z29 -> -1.1185846 | AB29: =+M29/$F$3 -> 0 | AC29: =+N29/$F$3 -> 2.9949352 | AD29: =+AB29-AC29 -> -2.9949352 | AE29: =+Q29/$F$3 -> 0 | AF29: =+R29/$F$3 -> 1.6351545 | AG29: =+AE29-AF29 -> -1.6351545 | AH29: =+U29/$F$3 -> 0 | AI29: =+V29/$F$3 -> 0.241196 | AJ29: =+AH29-AI29 -> -0.241196 | AK29: =+Y29/#REF! -> #REF! | AL29: =+Z29/#REF! -> #REF! | AM29: =+AK29-AL29 -> #REF! | AN29: =+COUNTIFS(FieldWy!A:A,H29,FieldWy!F:F,"<>") -> 0 | AO29: =+M29-AN29 -> 0 | AP29: =+COUNTIFS(FieldWy!A:A,H29,FieldWy!F:F,"<>",FieldWy!AA:AA,"true") -> 0 | AQ29: =+Q29-AP29 -> 0 | AR29: =+COUNTIFS(FieldWy!A:A,H29,FieldWy!F:F,"<>",FieldWy!X:X,"PORTABILIDAD") -> 0 | AS29: =+U29+AR29 -> 0 | AT29: =+AN29-(AP29+AR29) -> 0 | AU29: =+Y29-AT29 -> 0
A30: SANCHEZ MEZA JOB | B30: EDSON FERREYRA FFLORES | C30: 1 | H30: 2091016 | I30: COPPEL ENRIQUEZ | J30: Toluca de Lerdo | K30: COPPEL | L30: =+IFERROR(M30/N30,0) -> 0 | M30: =SUM(Altas!E27:AI27) -> 0 | N30: =VLOOKUP(H30,Cuota!$D:$DU,119,0) -> 3.3909071 | O30: =+M30-N30 -> -3.3909071 | P30: =+IFERROR(Q30/R30,0) -> 0 | Q30: =+SUM(Altas!E74:AI74) -> 0 | R30: =VLOOKUP(H30,Tabla2[[#All],[IDPV]:[PP VOZ]],120,0) -> 2.3406783 | S30: =+Q30-R30 -> -2.3406783 | T30: =+IFERROR(U30/V30,0) -> 0 | U30: =+SUM(Altas!E121:AI121) -> 0 | V30: =VLOOKUP(H30,Tabla2[[#All],[IDPV]:[PP VOZ]],121,0) -> 0.361794 | W30: =+U30-V30 -> -0.361794 | X30: =+IFERROR(Y30/Z30,0) -> 0 | Y30: =+M30-(Q30+U30) -> 0 | Z30: =VLOOKUP(H30,Tabla2[[#All],[IDPV]:[PP VOZ]],122,0) -> 0.68843479 | AA30: =+Y30-Z30 -> -0.68843479 | AB30: =+M30/$F$3 -> 0 | AC30: =+N30/$F$3 -> 3.3909071 | AD30: =+AB30-AC30 -> -3.3909071 | AE30: =+Q30/$F$3 -> 0 | AF30: =+R30/$F$3 -> 2.3406783 | AG30: =+AE30-AF30 -> -2.3406783 | AH30: =+U30/$F$3 -> 0 | AI30: =+V30/$F$3 -> 0.361794 | AJ30: =+AH30-AI30 -> -0.361794 | AN30: =+COUNTIFS(FieldWy!A:A,H30,FieldWy!F:F,"<>") -> 0 | AO30: =+M30-AN30 -> 0 | AP30: =+COUNTIFS(FieldWy!A:A,H30,FieldWy!F:F,"<>",FieldWy!AA:AA,"true") -> 0 | AQ30: =+Q30-AP30 -> 0 | AR30: =+COUNTIFS(FieldWy!A:A,H30,FieldWy!F:F,"<>",FieldWy!X:X,"PORTABILIDAD") -> 0 | AS30: =+U30+AR30 -> 0 | AT30: =+AN30-(AP30+AR30) -> 0 | AU30: =+Y30-AT30 -> 0
A31: CALDERON GRACIAN ISRAEL | B31: ERIK ALEJANDRO GARCIA | C31: 1 | H31: 2091032 | I31: COPPEL TOTOLTEPEC | J31: Toluca de Lerdo | K31: COPPEL | L31: =+IFERROR(M31/N31,0) -> 0 | M31: =SUM(Altas!E28:AI28) -> 0 | N31: =VLOOKUP(H31,Cuota!$D:$DU,119,0) -> 3.8552348 | O31: =+M31-N31 -> -3.8552348 | P31: =+IFERROR(Q31/R31,0) -> 0 | Q31: =+SUM(Altas!E75:AI75) -> 0 | R31: =VLOOKUP(H31,Tabla2[[#All],[IDPV]:[PP VOZ]],120,0) -> 1.6522435 | S31: =+Q31-R31 -> -1.6522435 | T31: =+IFERROR(U31/V31,0) -> 0 | U31: =+SUM(Altas!E122:AI122) -> 0 | V31: =VLOOKUP(H31,Tabla2[[#All],[IDPV]:[PP VOZ]],121,0) -> 0 | W31: =+U31-V31 -> 0 | X31: =+IFERROR(Y31/Z31,0) -> 0 | Y31: =+M31-(Q31+U31) -> 0 | Z31: =VLOOKUP(H31,Tabla2[[#All],[IDPV]:[PP VOZ]],122,0) -> 2.2029913 | AA31: =+Y31-Z31 -> -2.2029913 | AB31: =+M31/$F$3 -> 0 | AC31: =+N31/$F$3 -> 3.8552348 | AD31: =+AB31-AC31 -> -3.8552348 | AE31: =+Q31/$F$3 -> 0 | AF31: =+R31/$F$3 -> 1.6522435 | AG31: =+AE31-AF31 -> -1.6522435 | AH31: =+U31/$F$3 -> 0 | AI31: =+V31/$F$3 -> 0 | AJ31: =+AH31-AI31 -> 0 | AN31: =+COUNTIFS(FieldWy!A:A,H31,FieldWy!F:F,"<>") -> 0 | AO31: =+M31-AN31 -> 0 | AP31: =+COUNTIFS(FieldWy!A:A,H31,FieldWy!F:F,"<>",FieldWy!AA:AA,"true") -> 0 | AQ31: =+Q31-AP31 -> 0 | AR31: =+COUNTIFS(FieldWy!A:A,H31,FieldWy!F:F,"<>",FieldWy!X:X,"PORTABILIDAD") -> 0 | AS31: =+U31+AR31 -> 0 | AT31: =+AN31-(AP31+AR31) -> 0 | AU31: =+Y31-AT31 -> 0
A32: SANCHEZ MEZA JOB | B32: EDSON FERREYRA FFLORES | C32: 1 | H32: 2091046 | I32: COPPEL HIDALGO | J32: Tenango Del Valle | K32: COPPEL | L32: =+IFERROR(M32/N32,0) -> 0 | M32: =SUM(Altas!E29:AI29) -> 0 | N32: =VLOOKUP(H32,Cuota!$D:$DU,119,0) -> 3.9416549 | O32: =+M32-N32 -> -3.9416549 | P32: =+IFERROR(Q32/R32,0) -> 0 | Q32: =+SUM(Altas!E76:AI76) -> 0 | R32: =VLOOKUP(H32,Tabla2[[#All],[IDPV]:[PP VOZ]],120,0) -> 2.3406783 | S32: =+Q32-R32 -> -2.3406783 | T32: =+IFERROR(U32/V32,0) -> 0 | U32: =+SUM(Altas!E123:AI123) -> 0 | V32: =VLOOKUP(H32,Tabla2[[#All],[IDPV]:[PP VOZ]],121,0) -> 0.361794 | W32: =+U32-V32 -> -0.361794 | X32: =+IFERROR(Y32/Z32,0) -> 0 | Y32: =+M32-(Q32+U32) -> 0 | Z32: =VLOOKUP(H32,Tabla2[[#All],[IDPV]:[PP VOZ]],122,0) -> 1.2391826 | AA32: =+Y32-Z32 -> -1.2391826 | AB32: =+M32/$F$3 -> 0 | AC32: =+N32/$F$3 -> 3.9416549 | AD32: =+AB32-AC32 -> -3.9416549 | AE32: =+Q32/$F$3 -> 0 | AF32: =+R32/$F$3 -> 2.3406783 | AG32: =+AE32-AF32 -> -2.3406783 | AH32: =+U32/$F$3 -> 0 | AI32: =+V32/$F$3 -> 0.361794 | AJ32: =+AH32-AI32 -> -0.361794 | AN32: =+COUNTIFS(FieldWy!A:A,H32,FieldWy!F:F,"<>") -> 0 | AO32: =+M32-AN32 -> 0 | AP32: =+COUNTIFS(FieldWy!A:A,H32,FieldWy!F:F,"<>",FieldWy!AA:AA,"true") -> 0 | AQ32: =+Q32-AP32 -> 0 | AR32: =+COUNTIFS(FieldWy!A:A,H32,FieldWy!F:F,"<>",FieldWy!X:X,"PORTABILIDAD") -> 0 | AS32: =+U32+AR32 -> 0 | AT32: =+AN32-(AP32+AR32) -> 0 | AU32: =+Y32-AT32 -> 0
A33: SANCHEZ MEZA JOB | B33: ERIK ALEJANDRO GARCIA | C33: 1 | H33: 2091151 | I33: COPPEL CANADA REOLIN | J33: Lerma | K33: COPPEL | L33: =+IFERROR(M33/N33,0) -> 0 | M33: =SUM(Altas!E30:AI30) -> 0 | N33: =VLOOKUP(H33,Cuota!$D:$DU,119,0) -> 1.7728415 | O33: =+M33-N33 -> -1.7728415 | P33: =+IFERROR(Q33/R33,0) -> 0 | Q33: =+SUM(Altas!E77:AI77) -> 0 | R33: =VLOOKUP(H33,Tabla2[[#All],[IDPV]:[PP VOZ]],120,0) -> 0.96380871 | S33: =+Q33-R33 -> -0.96380871 | T33: =+IFERROR(U33/V33,0) -> 0 | U33: =+SUM(Altas!E124:AI124) -> 0 | V33: =VLOOKUP(H33,Tabla2[[#All],[IDPV]:[PP VOZ]],121,0) -> 0.120598 | W33: =+U33-V33 -> -0.120598 | X33: =+IFERROR(Y33/Z33,0) -> 0 | Y33: =+M33-(Q33+U33) -> 0 | Z33: =VLOOKUP(H33,Tabla2[[#All],[IDPV]:[PP VOZ]],122,0) -> 0.68843479 | AA33: =+Y33-Z33 -> -0.68843479 | AB33: =+M33/$F$3 -> 0 | AC33: =+N33/$F$3 -> 1.7728415 | AD33: =+AB33-AC33 -> -1.7728415 | AE33: =+Q33/$F$3 -> 0 | AF33: =+R33/$F$3 -> 0.96380871 | AG33: =+AE33-AF33 -> -0.96380871 | AH33: =+U33/$F$3 -> 0 | AI33: =+V33/$F$3 -> 0.120598 | AJ33: =+AH33-AI33 -> -0.120598 | AN33: =+COUNTIFS(FieldWy!A:A,H33,FieldWy!F:F,"<>") -> 0 | AO33: =+M33-AN33 -> 0 | AP33: =+COUNTIFS(FieldWy!A:A,H33,FieldWy!F:F,"<>",FieldWy!AA:AA,"true") -> 0 | AQ33: =+Q33-AP33 -> 0 | AR33: =+COUNTIFS(FieldWy!A:A,H33,FieldWy!F:F,"<>",FieldWy!X:X,"PORTABILIDAD") -> 0 | AS33: =+U33+AR33 -> 0 | AT33: =+AN33-(AP33+AR33) -> 0 | AU33: =+Y33-AT33 -> 0
A34: SANCHEZ MEZA JOB | B34: EDGAR RAUL HERNANDEZ CERVANTES | C34: 1 | H34: 2091192 | I34: EKT JUAREZ | J34: Toluca de Lerdo | K34: ELEKTRA | L34: =+IFERROR(M34/N34,0) -> 0 | M34: =SUM(Altas!E31:AI31) -> 0 | N34: =VLOOKUP(H34,Cuota!$D:$DU,119,0) -> 1.3597806 | O34: =+M34-N34 -> -1.3597806 | P34: =+IFERROR(Q34/R34,0) -> 0 | Q34: =+SUM(Altas!E78:AI78) -> 0 | R34: =VLOOKUP(H34,Tabla2[[#All],[IDPV]:[PP VOZ]],120,0) -> 0.55074783 | S34: =+Q34-R34 -> -0.55074783 | T34: =+IFERROR(U34/V34,0) -> 0 | U34: =+SUM(Altas!E125:AI125) -> 0 | V34: =VLOOKUP(H34,Tabla2[[#All],[IDPV]:[PP VOZ]],121,0) -> 0.120598 | W34: =+U34-V34 -> -0.120598 | X34: =+IFERROR(Y34/Z34,0) -> 0 | Y34: =+M34-(Q34+U34) -> 0 | Z34: =VLOOKUP(H34,Tabla2[[#All],[IDPV]:[PP VOZ]],122,0) -> 0.68843479 | AA34: =+Y34-Z34 -> -0.68843479 | AB34: =+M34/$F$3 -> 0 | AC34: =+N34/$F$3 -> 1.3597806 | AD34: =+AB34-AC34 -> -1.3597806 | AE34: =+Q34/$F$3 -> 0 | AF34: =+R34/$F$3 -> 0.55074783 | AG34: =+AE34-AF34 -> -0.55074783 | AH34: =+U34/$F$3 -> 0 | AI34: =+V34/$F$3 -> 0.120598 | AJ34: =+AH34-AI34 -> -0.120598 | AN34: =+COUNTIFS(FieldWy!A:A,H34,FieldWy!F:F,"<>") -> 0 | AO34: =+M34-AN34 -> 0 | AP34: =+COUNTIFS(FieldWy!A:A,H34,FieldWy!F:F,"<>",FieldWy!AA:AA,"true") -> 0 | AQ34: =+Q34-AP34 -> 0 | AR34: =+COUNTIFS(FieldWy!A:A,H34,FieldWy!F:F,"<>",FieldWy!X:X,"PORTABILIDAD") -> 0 | AS34: =+U34+AR34 -> 0 | AT34: =+AN34-(AP34+AR34) -> 0 | AU34: =+Y34-AT34 -> 0
A35: SANCHEZ MEZA JOB | B35: ERIK ALEJANDRO GARCIA | C35: 1 | H35: 2091194 | I35: EKT SAN MATEO | J35: San Mateo Atenco | K35: ELEKTRA | L35: =+IFERROR(M35/N35,0) -> 0 | M35: =SUM(Altas!E32:AI32) -> 0 | N35: =VLOOKUP(H35,Cuota!$D:$DU,119,0) -> 1.3597806 | O35: =+M35-N35 -> -1.3597806 | P35: =+IFERROR(Q35/R35,0) -> 0 | Q35: =+SUM(Altas!E79:AI79) -> 0 | R35: =VLOOKUP(H35,Tabla2[[#All],[IDPV]:[PP VOZ]],120,0) -> 0.27537392 | S35: =+Q35-R35 -> -0.27537392 | T35: =+IFERROR(U35/V35,0) -> 0 | U35: =+SUM(Altas!E126:AI126) -> 0 | V35: =VLOOKUP(H35,Tabla2[[#All],[IDPV]:[PP VOZ]],121,0) -> 0.120598 | W35: =+U35-V35 -> -0.120598 | X35: =+IFERROR(Y35/Z35,0) -> 0 | Y35: =+M35-(Q35+U35) -> 0 | Z35: =VLOOKUP(H35,Tabla2[[#All],[IDPV]:[PP VOZ]],122,0) -> 0.96380871 | AA35: =+Y35-Z35 -> -0.96380871 | AB35: =+M35/$F$3 -> 0 | AC35: =+N35/$F$3 -> 1.3597806 | AD35: =+AB35-AC35 -> -1.3597806 | AE35: =+Q35/$F$3 -> 0 | AF35: =+R35/$F$3 -> 0.27537392 | AG35: =+AE35-AF35 -> -0.27537392 | AH35: =+U35/$F$3 -> 0 | AI35: =+V35/$F$3 -> 0.120598 | AJ35: =+AH35-AI35 -> -0.120598 | AN35: =+COUNTIFS(FieldWy!A:A,H35,FieldWy!F:F,"<>") -> 0 | AO35: =+M35-AN35 -> 0 | AP35: =+COUNTIFS(FieldWy!A:A,H35,FieldWy!F:F,"<>",FieldWy!AA:AA,"true") -> 0 | AQ35: =+Q35-AP35 -> 0 | AR35: =+COUNTIFS(FieldWy!A:A,H35,FieldWy!F:F,"<>",FieldWy!X:X,"PORTABILIDAD") -> 0 | AS35: =+U35+AR35 -> 0 | AT35: =+AN35-(AP35+AR35) -> 0 | AU35: =+Y35-AT35 -> 0
A36: SANCHEZ MEZA JOB | B36: EDGAR RAUL HERNANDEZ CERVANTES | C36: 1 | H36: 2091206 | I36: EKT ZINACANTEPEC | J36: Zinacantepec | K36: ELEKTRA | L36: =+IFERROR(M36/N36,0) -> 0 | M36: =SUM(Altas!E33:AI33) -> 0 | N36: =VLOOKUP(H36,Cuota!$D:$DU,119,0) -> 1.3597806 | O36: =+M36-N36 -> -1.3597806 | P36: =+IFERROR(Q36/R36,0) -> 0 | Q36: =+SUM(Altas!E80:AI80) -> 0 | R36: =VLOOKUP(H36,Tabla2[[#All],[IDPV]:[PP VOZ]],120,0) -> 0.68843479 | S36: =+Q36-R36 -> -0.68843479 | T36: =+IFERROR(U36/V36,0) -> 0 | U36: =+SUM(Altas!E127:AI127) -> 0 | V36: =VLOOKUP(H36,Tabla2[[#All],[IDPV]:[PP VOZ]],121,0) -> 0.120598 | W36: =+U36-V36 -> -0.120598 | X36: =+IFERROR(Y36/Z36,0) -> 0 | Y36: =+M36-(Q36+U36) -> 0 | Z36: =VLOOKUP(H36,Tabla2[[#All],[IDPV]:[PP VOZ]],122,0) -> 0.55074783 | AA36: =+Y36-Z36 -> -0.55074783 | AB36: =+M36/$F$3 -> 0 | AC36: =+N36/$F$3 -> 1.3597806 | AD36: =+AB36-AC36 -> -1.3597806 | AE36: =+Q36/$F$3 -> 0 | AF36: =+R36/$F$3 -> 0.68843479 | AG36: =+AE36-AF36 -> -0.68843479 | AH36: =+U36/$F$3 -> 0 | AI36: =+V36/$F$3 -> 0.120598 | AJ36: =+AH36-AI36 -> -0.120598 | AN36: =+COUNTIFS(FieldWy!A:A,H36,FieldWy!F:F,"<>") -> 0 | AO36: =+M36-AN36 -> 0 | AP36: =+COUNTIFS(FieldWy!A:A,H36,FieldWy!F:F,"<>",FieldWy!AA:AA,"true") -> 0 | AQ36: =+Q36-AP36 -> 0 | AR36: =+COUNTIFS(FieldWy!A:A,H36,FieldWy!F:F,"<>",FieldWy!X:X,"PORTABILIDAD") -> 0 | AS36: =+U36+AR36 -> 0 | AT36: =+AN36-(AP36+AR36) -> 0 | AU36: =+Y36-AT36 -> 0
A37: CUEVAS OCAÑA ALMA ROSA | B37: JOSE JAEN OSORIO PAGUIA | C37: 1 | H37: 2091207 | I37: BA MEGA IXTLAHUACA | J37: Atlacomulco | K37: ELEKTRA | L37: =+IFERROR(M37/N37,0) -> 0 | M37: =SUM(Altas!E34:AI34) -> 0 | N37: =VLOOKUP(H37,Cuota!$D:$DU,119,0) -> 1.3597806 | O37: =+M37-N37 -> -1.3597806 | P37: =+IFERROR(Q37/R37,0) -> 0 | Q37: =+SUM(Altas!E81:AI81) -> 0 | R37: =VLOOKUP(H37,Tabla2[[#All],[IDPV]:[PP VOZ]],120,0) -> 0.68843479 | S37: =+Q37-R37 -> -0.68843479 | T37: =+IFERROR(U37/V37,0) -> 0 | U37: =+SUM(Altas!E128:AI128) -> 0 | V37: =VLOOKUP(H37,Tabla2[[#All],[IDPV]:[PP VOZ]],121,0) -> 0.120598 | W37: =+U37-V37 -> -0.120598 | X37: =+IFERROR(Y37/Z37,0) -> 0 | Y37: =+M37-(Q37+U37) -> 0 | Z37: =VLOOKUP(H37,Tabla2[[#All],[IDPV]:[PP VOZ]],122,0) -> 0.55074783 | AA37: =+Y37-Z37 -> -0.55074783 | AB37: =+M37/$F$3 -> 0 | AC37: =+N37/$F$3 -> 1.3597806 | AD37: =+AB37-AC37 -> -1.3597806 | AE37: =+Q37/$F$3 -> 0 | AF37: =+R37/$F$3 -> 0.68843479 | AG37: =+AE37-AF37 -> -0.68843479 | AH37: =+U37/$F$3 -> 0 | AI37: =+V37/$F$3 -> 0.120598 | AJ37: =+AH37-AI37 -> -0.120598 | AN37: =+COUNTIFS(FieldWy!A:A,H37,FieldWy!F:F,"<>") -> 0 | AO37: =+M37-AN37 -> 0 | AP37: =+COUNTIFS(FieldWy!A:A,H37,FieldWy!F:F,"<>",FieldWy!AA:AA,"true") -> 0 | AQ37: =+Q37-AP37 -> 0 | AR37: =+COUNTIFS(FieldWy!A:A,H37,FieldWy!F:F,"<>",FieldWy!X:X,"PORTABILIDAD") -> 0 | AS37: =+U37+AR37 -> 0 | AT37: =+AN37-(AP37+AR37) -> 0 | AU37: =+Y37-AT37 -> 0
A38: SANCHEZ MEZA JOB | B38: EDGAR RAUL HERNANDEZ CERVANTES | C38: 1 | H38: 2091209 | I38: EKT ADOLFO LOPEZ MATEOS | J38: Toluca de Lerdo | K38: ELEKTRA | L38: =+IFERROR(M38/N38,0) -> 0 | M38: =SUM(Altas!E35:AI35) -> 0 | N38: =VLOOKUP(H38,Cuota!$D:$DU,119,0) -> 1.3597806 | O38: =+M38-N38 -> -1.3597806 | P38: =+IFERROR(Q38/R38,0) -> 0 | Q38: =+SUM(Altas!E82:AI82) -> 0 | R38: =VLOOKUP(H38,Tabla2[[#All],[IDPV]:[PP VOZ]],120,0) -> 0.68843479 | S38: =+Q38-R38 -> -0.68843479 | T38: =+IFERROR(U38/V38,0) -> 0 | U38: =+SUM(Altas!E129:AI129) -> 0 | V38: =VLOOKUP(H38,Tabla2[[#All],[IDPV]:[PP VOZ]],121,0) -> 0.120598 | W38: =+U38-V38 -> -0.120598 | X38: =+IFERROR(Y38/Z38,0) -> 0 | Y38: =+M38-(Q38+U38) -> 0 | Z38: =VLOOKUP(H38,Tabla2[[#All],[IDPV]:[PP VOZ]],122,0) -> 0.55074783 | AA38: =+Y38-Z38 -> -0.55074783 | AB38: =+M38/$F$3 -> 0 | AC38: =+N38/$F$3 -> 1.3597806 | AD38: =+AB38-AC38 -> -1.3597806 | AE38: =+Q38/$F$3 -> 0 | AF38: =+R38/$F$3 -> 0.68843479 | AG38: =+AE38-AF38 -> -0.68843479 | AH38: =+U38/$F$3 -> 0 | AI38: =+V38/$F$3 -> 0.120598 | AJ38: =+AH38-AI38 -> -0.120598 | AN38: =+COUNTIFS(FieldWy!A:A,H38,FieldWy!F:F,"<>") -> 0 | AO38: =+M38-AN38 -> 0 | AP38: =+COUNTIFS(FieldWy!A:A,H38,FieldWy!F:F,"<>",FieldWy!AA:AA,"true") -> 0 | AQ38: =+Q38-AP38 -> 0 | AR38: =+COUNTIFS(FieldWy!A:A,H38,FieldWy!F:F,"<>",FieldWy!X:X,"PORTABILIDAD") -> 0 | AS38: =+U38+AR38 -> 0 | AT38: =+AN38-(AP38+AR38) -> 0 | AU38: =+Y38-AT38 -> 0
A39: SANCHEZ MEZA JOB | B39: EDSON FERREYRA FFLORES | C39: 1 | H39: 2091238 | I39: EKT SANTIAGO TIANGUISTENGO | J39: Tianguistenco | K39: ELEKTRA | L39: =+IFERROR(M39/N39,0) -> 0 | M39: =SUM(Altas!E36:AI36) -> 0 | N39: =VLOOKUP(H39,Cuota!$D:$DU,119,0) -> 1.6351545 | O39: =+M39-N39 -> -1.6351545 | P39: =+IFERROR(Q39/R39,0) -> 0 | Q39: =+SUM(Altas!E83:AI83) -> 0 | R39: =VLOOKUP(H39,Tabla2[[#All],[IDPV]:[PP VOZ]],120,0) -> 0.94671975 | S39: =+Q39-R39 -> -0.94671975 | T39: =+IFERROR(U39/V39,0) -> 0 | U39: =+SUM(Altas!E130:AI130) -> 0 | V39: =VLOOKUP(H39,Tabla2[[#All],[IDPV]:[PP VOZ]],121,0) -> 0.120598 | W39: =+U39-V39 -> -0.120598 | X39: =+IFERROR(Y39/Z39,0) -> 0 | Y39: =+M39-(Q39+U39) -> 0 | Z39: =VLOOKUP(H39,Tabla2[[#All],[IDPV]:[PP VOZ]],122,0) -> 0.56783679 | AA39: =+Y39-Z39 -> -0.56783679 | AB39: =+M39/$F$3 -> 0 | AC39: =+N39/$F$3 -> 1.6351545 | AD39: =+AB39-AC39 -> -1.6351545 | AE39: =+Q39/$F$3 -> 0 | AF39: =+R39/$F$3 -> 0.94671975 | AG39: =+AE39-AF39 -> -0.94671975 | AH39: =+U39/$F$3 -> 0 | AI39: =+V39/$F$3 -> 0.120598 | AJ39: =+AH39-AI39 -> -0.120598 | AN39: =+COUNTIFS(FieldWy!A:A,H39,FieldWy!F:F,"<>") -> 0 | AO39: =+M39-AN39 -> 0 | AP39: =+COUNTIFS(FieldWy!A:A,H39,FieldWy!F:F,"<>",FieldWy!AA:AA,"true") -> 0 | AQ39: =+Q39-AP39 -> 0 | AR39: =+COUNTIFS(FieldWy!A:A,H39,FieldWy!F:F,"<>",FieldWy!X:X,"PORTABILIDAD") -> 0 | AS39: =+U39+AR39 -> 0 | AT39: =+AN39-(AP39+AR39) -> 0 | AU39: =+Y39-AT39 -> 0
A40: CUEVAS OCAÑA ALMA ROSA | B40: JOSE JAEN OSORIO PAGUIA | C40: 1 | H40: 2091244 | I40: EKT ATLACOMULCO (5306) | J40: Atlacomulco | K40: ELEKTRA | L40: =+IFERROR(M40/N40,0) -> 0 | M40: =SUM(Altas!E37:AI37) -> 0 | N40: =VLOOKUP(H40,Cuota!$D:$DU,119,0) -> 1.2391826 | O40: =+M40-N40 -> -1.2391826 | P40: =+IFERROR(Q40/R40,0) -> 0 | Q40: =+SUM(Altas!E84:AI84) -> 0 | R40: =VLOOKUP(H40,Tabla2[[#All],[IDPV]:[PP VOZ]],120,0) -> 0.13768696 | S40: =+Q40-R40 -> -0.13768696 | T40: =+IFERROR(U40/V40,0) -> 0 | U40: =+SUM(Altas!E131:AI131) -> 0 | V40: =VLOOKUP(H40,Tabla2[[#All],[IDPV]:[PP VOZ]],121,0) -> 0 | W40: =+U40-V40 -> 0 | X40: =+IFERROR(Y40/Z40,0) -> 0 | Y40: =+M40-(Q40+U40) -> 0 | Z40: =VLOOKUP(H40,Tabla2[[#All],[IDPV]:[PP VOZ]],122,0) -> 1.1014957 | AA40: =+Y40-Z40 -> -1.1014957 | AB40: =+M40/$F$3 -> 0 | AC40: =+N40/$F$3 -> 1.2391826 | AD40: =+AB40-AC40 -> -1.2391826 | AE40: =+Q40/$F$3 -> 0 | AF40: =+R40/$F$3 -> 0.13768696 | AG40: =+AE40-AF40 -> -0.13768696 | AH40: =+U40/$F$3 -> 0 | AI40: =+V40/$F$3 -> 0 | AJ40: =+AH40-AI40 -> 0 | AN40: =+COUNTIFS(FieldWy!A:A,H40,FieldWy!F:F,"<>") -> 0 | AO40: =+M40-AN40 -> 0 | AP40: =+COUNTIFS(FieldWy!A:A,H40,FieldWy!F:F,"<>",FieldWy!AA:AA,"true") -> 0 | AQ40: =+Q40-AP40 -> 0 | AR40: =+COUNTIFS(FieldWy!A:A,H40,FieldWy!F:F,"<>",FieldWy!X:X,"PORTABILIDAD") -> 0 | AS40: =+U40+AR40 -> 0 | AT40: =+AN40-(AP40+AR40) -> 0 | AU40: =+Y40-AT40 -> 0
A41: SANCHEZ MEZA JOB | B41: EDSON FERREYRA FFLORES | C41: 1 | H41: 2091372 | I41: COPPEL CANADA MORELOS (TIANGUISTENCO) | J41: Tianguistenco | K41: COPPEL | L41: =+IFERROR(M41/N41,0) -> 0 | M41: =SUM(Altas!E38:AI38) -> 0 | N41: =VLOOKUP(H41,Cuota!$D:$DU,119,0) -> 1.6351545 | O41: =+M41-N41 -> -1.6351545 | P41: =+IFERROR(Q41/R41,0) -> 0 | Q41: =+SUM(Altas!E85:AI85) -> 0 | R41: =VLOOKUP(H41,Tabla2[[#All],[IDPV]:[PP VOZ]],120,0) -> 0.68843479 | S41: =+Q41-R41 -> -0.68843479 | T41: =+IFERROR(U41/V41,0) -> 0 | U41: =+SUM(Altas!E132:AI132) -> 0 | V41: =VLOOKUP(H41,Tabla2[[#All],[IDPV]:[PP VOZ]],121,0) -> 0.120598 | W41: =+U41-V41 -> -0.120598 | X41: =+IFERROR(Y41/Z41,0) -> 0 | Y41: =+M41-(Q41+U41) -> 0 | Z41: =VLOOKUP(H41,Tabla2[[#All],[IDPV]:[PP VOZ]],122,0) -> 0.82612175 | AA41: =+Y41-Z41 -> -0.82612175 | AB41: =+M41/$F$3 -> 0 | AC41: =+N41/$F$3 -> 1.6351545 | AD41: =+AB41-AC41 -> -1.6351545 | AE41: =+Q41/$F$3 -> 0 | AF41: =+R41/$F$3 -> 0.68843479 | AG41: =+AE41-AF41 -> -0.68843479 | AH41: =+U41/$F$3 -> 0 | AI41: =+V41/$F$3 -> 0.120598 | AJ41: =+AH41-AI41 -> -0.120598 | AN41: =+COUNTIFS(FieldWy!A:A,H41,FieldWy!F:F,"<>") -> 0 | AO41: =+M41-AN41 -> 0 | AP41: =+COUNTIFS(FieldWy!A:A,H41,FieldWy!F:F,"<>",FieldWy!AA:AA,"true") -> 0 | AQ41: =+Q41-AP41 -> 0 | AR41: =+COUNTIFS(FieldWy!A:A,H41,FieldWy!F:F,"<>",FieldWy!X:X,"PORTABILIDAD") -> 0 | AS41: =+U41+AR41 -> 0 | AT41: =+AN41-(AP41+AR41) -> 0 | AU41: =+Y41-AT41 -> 0
A42: REYES ZARRABAL CRISTOPHER | B42: JIOBANI MARIN BUENDIA BARCENAS | C42: 1 | D42: 10 tiendas 90 al 100% | G42: Estable | H42: 2091438 | I42: COPPEL DEL ROSAL | J42: IXMIQUILPAN | K42: Coppel | L42: =+IFERROR(M42/N42,0) -> 0 | M42: =SUM(Altas!E39:AI39) -> 0 | N42: =VLOOKUP(H42,Cuota!$D:$DU,119,0) -> 2.0482154 | O42: =+M42-N42 -> -2.0482154 | P42: =+IFERROR(Q42/R42,0) -> 0 | Q42: =+SUM(Altas!E86:AI86) -> 0 | R42: =VLOOKUP(H42,Tabla2[[#All],[IDPV]:[PP VOZ]],120,0) -> 0.68843479 | S42: =+Q42-R42 -> -0.68843479 | T42: =+IFERROR(U42/V42,0) -> 0 | U42: =+SUM(Altas!E133:AI133) -> 0 | V42: =VLOOKUP(H42,Tabla2[[#All],[IDPV]:[PP VOZ]],121,0) -> 0.120598 | W42: =+U42-V42 -> -0.120598 | X42: =+IFERROR(Y42/Z42,0) -> 0 | Y42: =+M42-(Q42+U42) -> 0 | Z42: =VLOOKUP(H42,Tabla2[[#All],[IDPV]:[PP VOZ]],122,0) -> 1.2391826 | AA42: =+Y42-Z42 -> -1.2391826 | AB42: =+M42/$F$3 -> 0 | AC42: =+N42/$F$3 -> 2.0482154 | AD42: =+AB42-AC42 -> -2.0482154 | AE42: =+Q42/$F$3 -> 0 | AF42: =+R42/$F$3 -> 0.68843479 | AG42: =+AE42-AF42 -> -0.68843479 | AH42: =+U42/$F$3 -> 0 | AI42: =+V42/$F$3 -> 0.120598 | AJ42: =+AH42-AI42 -> -0.120598 | AK42: =+Y42/#REF! -> #REF! | AL42: =+Z42/#REF! -> #REF! | AM42: =+AK42-AL42 -> #REF! | AN42: =+COUNTIFS(FieldWy!A:A,H42,FieldWy!F:F,"<>") -> 0 | AO42: =+M42-AN42 -> 0 | AP42: =+COUNTIFS(FieldWy!A:A,H42,FieldWy!F:F,"<>",FieldWy!AA:AA,"true") -> 0 | AQ42: =+Q42-AP42 -> 0 | AR42: =+COUNTIFS(FieldWy!A:A,H42,FieldWy!F:F,"<>",FieldWy!X:X,"PORTABILIDAD") -> 0 | AS42: =+U42+AR42 -> 0 | AT42: =+AN42-(AP42+AR42) -> 0 | AU42: =+Y42-AT42 -> 0
A43: SANCHEZ MEZA JOB | B43: ERIK ALEJANDRO GARCIA | C43: 1 | H43: 2091496 | I43: EKT PLAZA LERMA | J43: Lerma | K43: ELEKTRA | L43: =+IFERROR(M43/N43,0) -> 0 | M43: =SUM(Altas!E40:AI40) -> 0 | N43: =VLOOKUP(H43,Cuota!$D:$DU,119,0) -> 1.3597806 | O43: =+M43-N43 -> -1.3597806 | P43: =+IFERROR(Q43/R43,0) -> 0 | Q43: =+SUM(Altas!E87:AI87) -> 0 | R43: =VLOOKUP(H43,Tabla2[[#All],[IDPV]:[PP VOZ]],120,0) -> 0.27537392 | S43: =+Q43-R43 -> -0.27537392 | T43: =+IFERROR(U43/V43,0) -> 0 | U43: =+SUM(Altas!E134:AI134) -> 0 | V43: =VLOOKUP(H43,Tabla2[[#All],[IDPV]:[PP VOZ]],121,0) -> 0.120598 | W43: =+U43-V43 -> -0.120598 | X43: =+IFERROR(Y43/Z43,0) -> 0 | Y43: =+M43-(Q43+U43) -> 0 | Z43: =VLOOKUP(H43,Tabla2[[#All],[IDPV]:[PP VOZ]],122,0) -> 0.96380871 | AA43: =+Y43-Z43 -> -0.96380871 | AB43: =+M43/$F$3 -> 0 | AC43: =+N43/$F$3 -> 1.3597806 | AD43: =+AB43-AC43 -> -1.3597806 | AE43: =+Q43/$F$3 -> 0 | AF43: =+R43/$F$3 -> 0.27537392 | AG43: =+AE43-AF43 -> -0.27537392 | AH43: =+U43/$F$3 -> 0 | AI43: =+V43/$F$3 -> 0.120598 | AJ43: =+AH43-AI43 -> -0.120598 | AN43: =+COUNTIFS(FieldWy!A:A,H43,FieldWy!F:F,"<>") -> 0 | AO43: =+M43-AN43 -> 0 | AP43: =+COUNTIFS(FieldWy!A:A,H43,FieldWy!F:F,"<>",FieldWy!AA:AA,"true") -> 0 | AQ43: =+Q43-AP43 -> 0 | AR43: =+COUNTIFS(FieldWy!A:A,H43,FieldWy!F:F,"<>",FieldWy!X:X,"PORTABILIDAD") -> 0 | AS43: =+U43+AR43 -> 0 | AT43: =+AN43-(AP43+AR43) -> 0 | AU43: =+Y43-AT43 -> 0
A44: SANCHEZ MEZA JOB | B44: ERIK ALEJANDRO GARCIA | C44: 1 | H44: 2091551 | I44: COPPEL PLAZA SANTIN | J44: Toluca de Lerdo | K44: COPPEL | L44: =+IFERROR(M44/N44,0) -> 0 | M44: =SUM(Altas!E41:AI41) -> 0 | N44: =VLOOKUP(H44,Cuota!$D:$DU,119,0) -> 4.3547158 | O44: =+M44-N44 -> -4.3547158 | P44: =+IFERROR(Q44/R44,0) -> 0 | Q44: =+SUM(Altas!E88:AI88) -> 0 | R44: =VLOOKUP(H44,Tabla2[[#All],[IDPV]:[PP VOZ]],120,0) -> 2.6160522 | S44: =+Q44-R44 -> -2.6160522 | T44: =+IFERROR(U44/V44,0) -> 0 | U44: =+SUM(Altas!E135:AI135) -> 0 | V44: =VLOOKUP(H44,Tabla2[[#All],[IDPV]:[PP VOZ]],121,0) -> 0.361794 | W44: =+U44-V44 -> -0.361794 | X44: =+IFERROR(Y44/Z44,0) -> 0 | Y44: =+M44-(Q44+U44) -> 0 | Z44: =VLOOKUP(H44,Tabla2[[#All],[IDPV]:[PP VOZ]],122,0) -> 1.3768696 | AA44: =+Y44-Z44 -> -1.3768696 | AB44: =+M44/$F$3 -> 0 | AC44: =+N44/$F$3 -> 4.3547158 | AD44: =+AB44-AC44 -> -4.3547158 | AE44: =+Q44/$F$3 -> 0 | AF44: =+R44/$F$3 -> 2.6160522 | AG44: =+AE44-AF44 -> -2.6160522 | AH44: =+U44/$F$3 -> 0 | AI44: =+V44/$F$3 -> 0.361794 | AJ44: =+AH44-AI44 -> -0.361794 | AN44: =+COUNTIFS(FieldWy!A:A,H44,FieldWy!F:F,"<>") -> 0 | AO44: =+M44-AN44 -> 0 | AP44: =+COUNTIFS(FieldWy!A:A,H44,FieldWy!F:F,"<>",FieldWy!AA:AA,"true") -> 0 | AQ44: =+Q44-AP44 -> 0 | AR44: =+COUNTIFS(FieldWy!A:A,H44,FieldWy!F:F,"<>",FieldWy!X:X,"PORTABILIDAD") -> 0 | AS44: =+U44+AR44 -> 0 | AT44: =+AN44-(AP44+AR44) -> 0 | AU44: =+Y44-AT44 -> 0
A45: SANCHEZ MEZA JOB | B45: EDGAR RAUL HERNANDEZ CERVANTES | C45: 1 | H45: 2091565 | I45: COPPEL 16 DE SEPTIEMBRE (ZINACANTEPEC) | J45: Zinacantepec | K45: COPPEL | L45: =+IFERROR(M45/N45,0) -> 0 | M45: =SUM(Altas!E42:AI42) -> 0 | N45: =VLOOKUP(H45,Cuota!$D:$DU,119,0) -> 3.9416549 | O45: =+M45-N45 -> -3.9416549 | P45: =+IFERROR(Q45/R45,0) -> 0 | Q45: =+SUM(Altas!E89:AI89) -> 0 | R45: =VLOOKUP(H45,Tabla2[[#All],[IDPV]:[PP VOZ]],120,0) -> 2.6160522 | S45: =+Q45-R45 -> -2.6160522 | T45: =+IFERROR(U45/V45,0) -> 0 | U45: =+SUM(Altas!E136:AI136) -> 0 | V45: =VLOOKUP(H45,Tabla2[[#All],[IDPV]:[PP VOZ]],121,0) -> 0.361794 | W45: =+U45-V45 -> -0.361794 | X45: =+IFERROR(Y45/Z45,0) -> 0 | Y45: =+M45-(Q45+U45) -> 0 | Z45: =VLOOKUP(H45,Tabla2[[#All],[IDPV]:[PP VOZ]],122,0) -> 0.96380871 | AA45: =+Y45-Z45 -> -0.96380871 | AB45: =+M45/$F$3 -> 0 | AC45: =+N45/$F$3 -> 3.9416549 | AD45: =+AB45-AC45 -> -3.9416549 | AE45: =+Q45/$F$3 -> 0 | AF45: =+R45/$F$3 -> 2.6160522 | AG45: =+AE45-AF45 -> -2.6160522 | AH45: =+U45/$F$3 -> 0 | AI45: =+V45/$F$3 -> 0.361794 | AJ45: =+AH45-AI45 -> -0.361794 | AN45: =+COUNTIFS(FieldWy!A:A,H45,FieldWy!F:F,"<>") -> 0 | AO45: =+M45-AN45 -> 0 | AP45: =+COUNTIFS(FieldWy!A:A,H45,FieldWy!F:F,"<>",FieldWy!AA:AA,"true") -> 0 | AQ45: =+Q45-AP45 -> 0 | AR45: =+COUNTIFS(FieldWy!A:A,H45,FieldWy!F:F,"<>",FieldWy!X:X,"PORTABILIDAD") -> 0 | AS45: =+U45+AR45 -> 0 | AT45: =+AN45-(AP45+AR45) -> 0 | AU45: =+Y45-AT45 -> 0
A46: REYES ZARRABAL CRISTOPHER | B46: JIOBANI MARIN BUENDIA BARCENAS | C46: 1 | D46: 10 tiendas 90 al 100% | G46: Estable | H46: 2091586 | I46: COPPEL CONSTITUCIÓN | J46: MIXQUIHUALA | K46: Coppel | L46: =+IFERROR(M46/N46,0) -> 0 | M46: =SUM(Altas!E43:AI43) -> 0 | N46: =VLOOKUP(H46,Cuota!$D:$DU,119,0) -> 1.3597806 | O46: =+M46-N46 -> -1.3597806 | P46: =+IFERROR(Q46/R46,0) -> 0 | Q46: =+SUM(Altas!E90:AI90) -> 0 | R46: =VLOOKUP(H46,Tabla2[[#All],[IDPV]:[PP VOZ]],120,0) -> 0.68843479 | S46: =+Q46-R46 -> -0.68843479 | T46: =+IFERROR(U46/V46,0) -> 0 | U46: =+SUM(Altas!E137:AI137) -> 0 | V46: =VLOOKUP(H46,Tabla2[[#All],[IDPV]:[PP VOZ]],121,0) -> 0.120598 | W46: =+U46-V46 -> -0.120598 | X46: =+IFERROR(Y46/Z46,0) -> 0 | Y46: =+M46-(Q46+U46) -> 0 | Z46: =VLOOKUP(H46,Tabla2[[#All],[IDPV]:[PP VOZ]],122,0) -> 0.55074783 | AA46: =+Y46-Z46 -> -0.55074783 | AB46: =+M46/$F$3 -> 0 | AC46: =+N46/$F$3 -> 1.3597806 | AD46: =+AB46-AC46 -> -1.3597806 | AE46: =+Q46/$F$3 -> 0 | AF46: =+R46/$F$3 -> 0.68843479 | AG46: =+AE46-AF46 -> -0.68843479 | AH46: =+U46/$F$3 -> 0 | AI46: =+V46/$F$3 -> 0.120598 | AJ46: =+AH46-AI46 -> -0.120598 | AK46: =+Y46/#REF! -> #REF! | AL46: =+Z46/#REF! -> #REF! | AM46: =+AK46-AL46 -> #REF! | AN46: =+COUNTIFS(FieldWy!A:A,H46,FieldWy!F:F,"<>") -> 0 | AO46: =+M46-AN46 -> 0 | AP46: =+COUNTIFS(FieldWy!A:A,H46,FieldWy!F:F,"<>",FieldWy!AA:AA,"true") -> 0 | AQ46: =+Q46-AP46 -> 0 | AR46: =+COUNTIFS(FieldWy!A:A,H46,FieldWy!F:F,"<>",FieldWy!X:X,"PORTABILIDAD") -> 0 | AS46: =+U46+AR46 -> 0 | AT46: =+AN46-(AP46+AR46) -> 0 | AU46: =+Y46-AT46 -> 0
A47: REYES ZARRABAL CRISTOPHER | B47: JIOBANI MARIN BUENDIA BARCENAS | C47: 1 | G47: Nuevo promotor | H47: 2091587 | I47: COPPEL MADERO | J47: TLAXCOAPAN | K47: Coppel | L47: =+IFERROR(M47/N47,0) -> 0 | M47: =SUM(Altas!E44:AI44) -> 0 | N47: =VLOOKUP(H47,Cuota!$D:$DU,119,0) -> 3.2703091 | O47: =+M47-N47 -> -3.2703091 | P47: =+IFERROR(Q47/R47,0) -> 0 | Q47: =+SUM(Altas!E91:AI91) -> 0 | R47: =VLOOKUP(H47,Tabla2[[#All],[IDPV]:[PP VOZ]],120,0) -> 1.3768696 | S47: =+Q47-R47 -> -1.3768696 | T47: =+IFERROR(U47/V47,0) -> 0 | U47: =+SUM(Altas!E138:AI138) -> 0 | V47: =VLOOKUP(H47,Tabla2[[#All],[IDPV]:[PP VOZ]],121,0) -> 0.241196 | W47: =+U47-V47 -> -0.241196 | X47: =+IFERROR(Y47/Z47,0) -> 0 | Y47: =+M47-(Q47+U47) -> 0 | Z47: =VLOOKUP(H47,Tabla2[[#All],[IDPV]:[PP VOZ]],122,0) -> 1.6522435 | AA47: =+Y47-Z47 -> -1.6522435 | AB47: =+M47/$F$3 -> 0 | AC47: =+N47/$F$3 -> 3.2703091 | AD47: =+AB47-AC47 -> -3.2703091 | AE47: =+Q47/$F$3 -> 0 | AF47: =+R47/$F$3 -> 1.3768696 | AG47: =+AE47-AF47 -> -1.3768696 | AH47: =+U47/$F$3 -> 0 | AI47: =+V47/$F$3 -> 0.241196 | AJ47: =+AH47-AI47 -> -0.241196 | AK47: =+Y47/#REF! -> #REF! | AL47: =+Z47/#REF! -> #REF! | AM47: =+AK47-AL47 -> #REF! | AN47: =+COUNTIFS(FieldWy!A:A,H47,FieldWy!F:F,"<>") -> 0 | AO47: =+M47-AN47 -> 0 | AP47: =+COUNTIFS(FieldWy!A:A,H47,FieldWy!F:F,"<>",FieldWy!AA:AA,"true") -> 0 | AQ47: =+Q47-AP47 -> 0 | AR47: =+COUNTIFS(FieldWy!A:A,H47,FieldWy!F:F,"<>",FieldWy!X:X,"PORTABILIDAD") -> 0 | AS47: =+U47+AR47 -> 0 | AT47: =+AN47-(AP47+AR47) -> 0 | AU47: =+Y47-AT47 -> 0
A48: CALDERON GRACIAN ISRAEL | B48: ERIK ALEJANDRO GARCIA | C48: 1 | H48: 2091588 | I48: COPPEL PLAZA SAN FRANCISCO | J48: Metepec | K48: COPPEL | L48: =+IFERROR(M48/N48,0) -> 0 | M48: =SUM(Altas!E45:AI45) -> 0 | N48: =VLOOKUP(H48,Cuota!$D:$DU,119,0) -> 1.7899305 | O48: =+M48-N48 -> -1.7899305 | P48: =+IFERROR(Q48/R48,0) -> 0 | Q48: =+SUM(Altas!E92:AI92) -> 0 | R48: =VLOOKUP(H48,Tabla2[[#All],[IDPV]:[PP VOZ]],120,0) -> 1.2391826 | S48: =+Q48-R48 -> -1.2391826 | T48: =+IFERROR(U48/V48,0) -> 0 | U48: =+SUM(Altas!E139:AI139) -> 0 | V48: =VLOOKUP(H48,Tabla2[[#All],[IDPV]:[PP VOZ]],121,0) -> 0 | W48: =+U48-V48 -> 0 | X48: =+IFERROR(Y48/Z48,0) -> 0 | Y48: =+M48-(Q48+U48) -> 0 | Z48: =VLOOKUP(H48,Tabla2[[#All],[IDPV]:[PP VOZ]],122,0) -> 0.55074783 | AA48: =+Y48-Z48 -> -0.55074783 | AB48: =+M48/$F$3 -> 0 | AC48: =+N48/$F$3 -> 1.7899305 | AD48: =+AB48-AC48 -> -1.7899305 | AE48: =+Q48/$F$3 -> 0 | AF48: =+R48/$F$3 -> 1.2391826 | AG48: =+AE48-AF48 -> -1.2391826 | AH48: =+U48/$F$3 -> 0 | AI48: =+V48/$F$3 -> 0 | AJ48: =+AH48-AI48 -> 0 | AN48: =+COUNTIFS(FieldWy!A:A,H48,FieldWy!F:F,"<>") -> 0 | AO48: =+M48-AN48 -> 0 | AP48: =+COUNTIFS(FieldWy!A:A,H48,FieldWy!F:F,"<>",FieldWy!AA:AA,"true") -> 0 | AQ48: =+Q48-AP48 -> 0 | AR48: =+COUNTIFS(FieldWy!A:A,H48,FieldWy!F:F,"<>",FieldWy!X:X,"PORTABILIDAD") -> 0 | AS48: =+U48+AR48 -> 0 | AT48: =+AN48-(AP48+AR48) -> 0 | AU48: =+Y48-AT48 -> 0
A49: GARCIA GUZMAN JESUS | B49: JOSE JAEN OSORIO PAGUIA | C49: 1 | H49: 2091708 | I49: EKT SAN FELIPE DEL PROGRESO | J49: San Felipe Del Progreso | K49: ELEKTRA | L49: =+IFERROR(M49/N49,0) -> 0 | M49: =SUM(Altas!E46:AI46) -> 0 | N49: =VLOOKUP(H49,Cuota!$D:$DU,119,0) -> 1.3597806 | O49: =+M49-N49 -> -1.3597806 | P49: =+IFERROR(Q49/R49,0) -> 0 | Q49: =+SUM(Altas!E93:AI93) -> 0 | R49: =VLOOKUP(H49,Tabla2[[#All],[IDPV]:[PP VOZ]],120,0) -> 0.27537392 | S49: =+Q49-R49 -> -0.27537392 | T49: =+IFERROR(U49/V49,0) -> 0 | U49: =+SUM(Altas!E140:AI140) -> 0 | V49: =VLOOKUP(H49,Tabla2[[#All],[IDPV]:[PP VOZ]],121,0) -> 0.120598 | W49: =+U49-V49 -> -0.120598 | X49: =+IFERROR(Y49/Z49,0) -> 0 | Y49: =+M49-(Q49+U49) -> 0 | Z49: =VLOOKUP(H49,Tabla2[[#All],[IDPV]:[PP VOZ]],122,0) -> 0.96380871 | AA49: =+Y49-Z49 -> -0.96380871 | AB49: =+M49/$F$3 -> 0 | AC49: =+N49/$F$3 -> 1.3597806 | AD49: =+AB49-AC49 -> -1.3597806 | AE49: =+Q49/$F$3 -> 0 | AF49: =+R49/$F$3 -> 0.27537392 | AG49: =+AE49-AF49 -> -0.27537392 | AH49: =+U49/$F$3 -> 0 | AI49: =+V49/$F$3 -> 0.120598 | AJ49: =+AH49-AI49 -> -0.120598 | AN49: =+COUNTIFS(FieldWy!A:A,H49,FieldWy!F:F,"<>") -> 0 | AO49: =+M49-AN49 -> 0 | AP49: =+COUNTIFS(FieldWy!A:A,H49,FieldWy!F:F,"<>",FieldWy!AA:AA,"true") -> 0 | AQ49: =+Q49-AP49 -> 0 | AR49: =+COUNTIFS(FieldWy!A:A,H49,FieldWy!F:F,"<>",FieldWy!X:X,"PORTABILIDAD") -> 0 | AS49: =+U49+AR49 -> 0 | AT49: =+AN49-(AP49+AR49) -> 0 | AU49: =+Y49-AT49 -> 0
A50: SANCHEZ MEZA JOB | B50: EDSON FERREYRA FFLORES | C50: 1 | H50: 2091711 | I50: Coppel Nicolás Bravo Tianguistenco | J50: Tianguistenco | K50: COPPEL | L50: =+IFERROR(M50/N50,0) -> 0 | M50: =SUM(Altas!E47:AI47) -> 0 | N50: =VLOOKUP(H50,Cuota!$D:$DU,119,0) -> 4.0793419 | O50: =+M50-N50 -> -4.0793419 | P50: =+IFERROR(Q50/R50,0) -> 0 | Q50: =+SUM(Altas!E94:AI94) -> 0 | R50: =VLOOKUP(H50,Tabla2[[#All],[IDPV]:[PP VOZ]],120,0) -> 2.3406783 | S50: =+Q50-R50 -> -2.3406783 | T50: =+IFERROR(U50/V50,0) -> 0 | U50: =+SUM(Altas!E141:AI141) -> 0 | V50: =VLOOKUP(H50,Tabla2[[#All],[IDPV]:[PP VOZ]],121,0) -> 0.361794 | W50: =+U50-V50 -> -0.361794 | X50: =+IFERROR(Y50/Z50,0) -> 0 | Y50: =+M50-(Q50+U50) -> 0 | Z50: =VLOOKUP(H50,Tabla2[[#All],[IDPV]:[PP VOZ]],122,0) -> 1.3768696 | AA50: =+Y50-Z50 -> -1.3768696 | AB50: =+M50/$F$3 -> 0 | AC50: =+N50/$F$3 -> 4.0793419 | AD50: =+AB50-AC50 -> -4.0793419 | AE50: =+Q50/$F$3 -> 0 | AF50: =+R50/$F$3 -> 2.3406783 | AG50: =+AE50-AF50 -> -2.3406783 | AH50: =+U50/$F$3 -> 0 | AI50: =+V50/$F$3 -> 0.361794 | AJ50: =+AH50-AI50 -> -0.361794 | AN50: =+COUNTIFS(FieldWy!A:A,H50,FieldWy!F:F,"<>") -> 0 | AO50: =+M50-AN50 -> 0 | AP50: =+COUNTIFS(FieldWy!A:A,H50,FieldWy!F:F,"<>",FieldWy!AA:AA,"true") -> 0 | AQ50: =+Q50-AP50 -> 0 | AR50: =+COUNTIFS(FieldWy!A:A,H50,FieldWy!F:F,"<>",FieldWy!X:X,"PORTABILIDAD") -> 0 | AS50: =+U50+AR50 -> 0 | AT50: =+AN50-(AP50+AR50) -> 0 | AU50: =+Y50-AT50 -> 0
A51: REYES ZARRABAL CRISTOPHER | B51: JIOBANI MARIN BUENDIA BARCENAS | C51: 1 | D51: 10 Pdvs 20 y 21 Jun | E51: Aumento de productividad | G51: Estable | H51: 2091864 | I51: ELEKTRA PROGRESO HIDALGO | J51: MIXQUIHUALA | K51: Elektra | L51: =+IFERROR(M51/N51,0) -> 0 | M51: =SUM(Altas!E48:AI48) -> 0 | N51: =VLOOKUP(H51,Cuota!$D:$DU,119,0) -> 1.6351545 | O51: =+M51-N51 -> -1.6351545 | P51: =+IFERROR(Q51/R51,0) -> 0 | Q51: =+SUM(Altas!E95:AI95) -> 0 | R51: =VLOOKUP(H51,Tabla2[[#All],[IDPV]:[PP VOZ]],120,0) -> 0.96380871 | S51: =+Q51-R51 -> -0.96380871 | T51: =+IFERROR(U51/V51,0) -> 0 | U51: =+SUM(Altas!E142:AI142) -> 0 | V51: =VLOOKUP(H51,Tabla2[[#All],[IDPV]:[PP VOZ]],121,0) -> 0.120598 | W51: =+U51-V51 -> -0.120598 | X51: =+IFERROR(Y51/Z51,0) -> 0 | Y51: =+M51-(Q51+U51) -> 0 | Z51: =VLOOKUP(H51,Tabla2[[#All],[IDPV]:[PP VOZ]],122,0) -> 0.55074783 | AA51: =+Y51-Z51 -> -0.55074783 | AB51: =+M51/$F$3 -> 0 | AC51: =+N51/$F$3 -> 1.6351545 | AD51: =+AB51-AC51 -> -1.6351545 | AE51: =+Q51/$F$3 -> 0 | AF51: =+R51/$F$3 -> 0.96380871 | AG51: =+AE51-AF51 -> -0.96380871 | AH51: =+U51/$F$3 -> 0 | AI51: =+V51/$F$3 -> 0.120598 | AJ51: =+AH51-AI51 -> -0.120598 | AK51: =+Y51/#REF! -> #REF! | AL51: =+Z51/#REF! -> #REF! | AM51: =+AK51-AL51 -> #REF! | AN51: =+COUNTIFS(FieldWy!A:A,H51,FieldWy!F:F,"<>") -> 0 | AO51: =+M51-AN51 -> 0 | AP51: =+COUNTIFS(FieldWy!A:A,H51,FieldWy!F:F,"<>",FieldWy!AA:AA,"true") -> 0 | AQ51: =+Q51-AP51 -> 0 | AR51: =+COUNTIFS(FieldWy!A:A,H51,FieldWy!F:F,"<>",FieldWy!X:X,"PORTABILIDAD") -> 0 | AS51: =+U51+AR51 -> 0 | AT51: =+AN51-(AP51+AR51) -> 0 | AU51: =+Y51-AT51 -> 0
A52: REYES ZARRABAL CRISTOPHER | B52: JIOBANI MARIN BUENDIA BARCENAS | C52: 1 | D52: 10 Pdvs 20 y 21 Jun | E52: Mejorar cobertura | G52: Estable | H52: 2091869 | I52: COPPEL ZAPATA | J52: MIXQUIHUALA | K52: Coppel | L52: =+IFERROR(M52/N52,0) -> 0 | M52: =SUM(Altas!E49:AI49) -> 0 | N52: =VLOOKUP(H52,Cuota!$D:$DU,119,0) -> 1.3597806 | O52: =+M52-N52 -> -1.3597806 | P52: =+IFERROR(Q52/R52,0) -> 0 | Q52: =+SUM(Altas!E96:AI96) -> 0 | R52: =VLOOKUP(H52,Tabla2[[#All],[IDPV]:[PP VOZ]],120,0) -> 0.68843479 | S52: =+Q52-R52 -> -0.68843479 | T52: =+IFERROR(U52/V52,0) -> 0 | U52: =+SUM(Altas!E143:AI143) -> 0 | V52: =VLOOKUP(H52,Tabla2[[#All],[IDPV]:[PP VOZ]],121,0) -> 0.120598 | W52: =+U52-V52 -> -0.120598 | X52: =+IFERROR(Y52/Z52,0) -> 0 | Y52: =+M52-(Q52+U52) -> 0 | Z52: =VLOOKUP(H52,Tabla2[[#All],[IDPV]:[PP VOZ]],122,0) -> 0.55074783 | AA52: =+Y52-Z52 -> -0.55074783 | AB52: =+M52/$F$3 -> 0 | AC52: =+N52/$F$3 -> 1.3597806 | AD52: =+AB52-AC52 -> -1.3597806 | AE52: =+Q52/$F$3 -> 0 | AF52: =+R52/$F$3 -> 0.68843479 | AG52: =+AE52-AF52 -> -0.68843479 | AH52: =+U52/$F$3 -> 0 | AI52: =+V52/$F$3 -> 0.120598 | AJ52: =+AH52-AI52 -> -0.120598 | AK52: =+Y52/#REF! -> #REF! | AL52: =+Z52/#REF! -> #REF! | AM52: =+AK52-AL52 -> #REF! | AN52: =+COUNTIFS(FieldWy!A:A,H52,FieldWy!F:F,"<>") -> 0 | AO52: =+M52-AN52 -> 0 | AP52: =+COUNTIFS(FieldWy!A:A,H52,FieldWy!F:F,"<>",FieldWy!AA:AA,"true") -> 0 | AQ52: =+Q52-AP52 -> 0 | AR52: =+COUNTIFS(FieldWy!A:A,H52,FieldWy!F:F,"<>",FieldWy!X:X,"PORTABILIDAD") -> 0 | AS52: =+U52+AR52 -> 0 | AT52: =+AN52-(AP52+AR52) -> 0 | AU52: =+Y52-AT52 -> 0
A53: CALDERON GRACIAN ISRAEL | B53: ERIK ALEJANDRO GARCIA | C53: 1 | H53: 2091896 | I53: EKT SAN PEDRO TOTOLTEPEC | J53: Toluca de Lerdo | K53: ELEKTRA | L53: =+IFERROR(M53/N53,0) -> 0 | M53: =SUM(Altas!E50:AI50) -> 0 | N53: =VLOOKUP(H53,Cuota!$D:$DU,119,0) -> 1.2391826 | O53: =+M53-N53 -> -1.2391826 | P53: =+IFERROR(Q53/R53,0) -> 0 | Q53: =+SUM(Altas!E97:AI97) -> 0 | R53: =VLOOKUP(H53,Tabla2[[#All],[IDPV]:[PP VOZ]],120,0) -> 0.27537392 | S53: =+Q53-R53 -> -0.27537392 | T53: =+IFERROR(U53/V53,0) -> 0 | U53: =+SUM(Altas!E144:AI144) -> 0 | V53: =VLOOKUP(H53,Tabla2[[#All],[IDPV]:[PP VOZ]],121,0) -> 0 | W53: =+U53-V53 -> 0 | X53: =+IFERROR(Y53/Z53,0) -> 0 | Y53: =+M53-(Q53+U53) -> 0 | Z53: =VLOOKUP(H53,Tabla2[[#All],[IDPV]:[PP VOZ]],122,0) -> 0.96380871 | AA53: =+Y53-Z53 -> -0.96380871 | AB53: =+M53/$F$3 -> 0 | AC53: =+N53/$F$3 -> 1.2391826 | AD53: =+AB53-AC53 -> -1.2391826 | AE53: =+Q53/$F$3 -> 0 | AF53: =+R53/$F$3 -> 0.27537392 | AG53: =+AE53-AF53 -> -0.27537392 | AH53: =+U53/$F$3 -> 0 | AI53: =+V53/$F$3 -> 0 | AJ53: =+AH53-AI53 -> 0 | AN53: =+COUNTIFS(FieldWy!A:A,H53,FieldWy!F:F,"<>") -> 0 | AO53: =+M53-AN53 -> 0 | AP53: =+COUNTIFS(FieldWy!A:A,H53,FieldWy!F:F,"<>",FieldWy!AA:AA,"true") -> 0 | AQ53: =+Q53-AP53 -> 0 | AR53: =+COUNTIFS(FieldWy!A:A,H53,FieldWy!F:F,"<>",FieldWy!X:X,"PORTABILIDAD") -> 0 | AS53: =+U53+AR53 -> 0 | AT53: =+AN53-(AP53+AR53) -> 0 | AU53: =+Y53-AT53 -> 0
A54: REYES ZARRABAL CRISTOPHER | B54: DANIEL BENJAMIN MARQUEZ BACA | C54: 1 | D54: Gestion con Marcas | G54: Estable | H54: 2092138 | I54: BA EKT TIZAYUCA | J54: TIZAYUCA | K54: Elektra | L54: =+IFERROR(M54/N54,0) -> 0 | M54: =SUM(Altas!E51:AI51) -> 0 | N54: =VLOOKUP(H54,Cuota!$D:$DU,119,0) -> 1.3597806 | O54: =+M54-N54 -> -1.3597806 | P54: =+IFERROR(Q54/R54,0) -> 0 | Q54: =+SUM(Altas!E98:AI98) -> 0 | R54: =VLOOKUP(H54,Tabla2[[#All],[IDPV]:[PP VOZ]],120,0) -> 0.67134583 | S54: =+Q54-R54 -> -0.67134583 | T54: =+IFERROR(U54/V54,0) -> 0 | U54: =+SUM(Altas!E145:AI145) -> 0 | V54: =VLOOKUP(H54,Tabla2[[#All],[IDPV]:[PP VOZ]],121,0) -> 0.120598 | W54: =+U54-V54 -> -0.120598 | X54: =+IFERROR(Y54/Z54,0) -> 0 | Y54: =+M54-(Q54+U54) -> 0 | Z54: =VLOOKUP(H54,Tabla2[[#All],[IDPV]:[PP VOZ]],122,0) -> 0.56783679 | AA54: =+Y54-Z54 -> -0.56783679 | AB54: =+M54/$F$3 -> 0 | AC54: =+N54/$F$3 -> 1.3597806 | AD54: =+AB54-AC54 -> -1.3597806 | AE54: =+Q54/$F$3 -> 0 | AF54: =+R54/$F$3 -> 0.67134583 | AG54: =+AE54-AF54 -> -0.67134583 | AH54: =+U54/$F$3 -> 0 | AI54: =+V54/$F$3 -> 0.120598 | AJ54: =+AH54-AI54 -> -0.120598 | AK54: =+Y54/#REF! -> #REF! | AL54: =+Z54/#REF! -> #REF! | AM54: =+AK54-AL54 -> #REF! | AN54: =+COUNTIFS(FieldWy!A:A,H54,FieldWy!F:F,"<>") -> 0 | AO54: =+M54-AN54 -> 0 | AP54: =+COUNTIFS(FieldWy!A:A,H54,FieldWy!F:F,"<>",FieldWy!AA:AA,"true") -> 0 | AQ54: =+Q54-AP54 -> 0 | AR54: =+COUNTIFS(FieldWy!A:A,H54,FieldWy!F:F,"<>",FieldWy!X:X,"PORTABILIDAD") -> 0 | AS54: =+U54+AR54 -> 0 | AT54: =+AN54-(AP54+AR54) -> 0 | AU54: =+Y54-AT54 -> 0
A55: SANCHEZ MEZA JOB | B55: ERIK ALEJANDRO GARCIA | C55: 1 | H55: 2092175 | I55: EKT TOLUCA PLAZA SANTINI | J55: Toluca de Lerdo | K55: ELEKTRA | L55: =+IFERROR(M55/N55,0) -> 0 | M55: =SUM(Altas!E52:AI52) -> 0 | N55: =VLOOKUP(H55,Cuota!$D:$DU,119,0) -> 1.3597806 | O55: =+M55-N55 -> -1.3597806 | P55: =+IFERROR(Q55/R55,0) -> 0 | Q55: =+SUM(Altas!E99:AI99) -> 0 | R55: =VLOOKUP(H55,Tabla2[[#All],[IDPV]:[PP VOZ]],120,0) -> 0.82612175 | S55: =+Q55-R55 -> -0.82612175 | T55: =+IFERROR(U55/V55,0) -> 0 | U55: =+SUM(Altas!E146:AI146) -> 0 | V55: =VLOOKUP(H55,Tabla2[[#All],[IDPV]:[PP VOZ]],121,0) -> 0.120598 | W55: =+U55-V55 -> -0.120598 | X55: =+IFERROR(Y55/Z55,0) -> 0 | Y55: =+M55-(Q55+U55) -> 0 | Z55: =VLOOKUP(H55,Tabla2[[#All],[IDPV]:[PP VOZ]],122,0) -> 0.41306088 | AA55: =+Y55-Z55 -> -0.41306088 | AB55: =+M55/$F$3 -> 0 | AC55: =+N55/$F$3 -> 1.3597806 | AD55: =+AB55-AC55 -> -1.3597806 | AE55: =+Q55/$F$3 -> 0 | AF55: =+R55/$F$3 -> 0.82612175 | AG55: =+AE55-AF55 -> -0.82612175 | AH55: =+U55/$F$3 -> 0 | AI55: =+V55/$F$3 -> 0.120598 | AJ55: =+AH55-AI55 -> -0.120598 | AN55: =+COUNTIFS(FieldWy!A:A,H55,FieldWy!F:F,"<>") -> 0 | AO55: =+M55-AN55 -> 0 | AP55: =+COUNTIFS(FieldWy!A:A,H55,FieldWy!F:F,"<>",FieldWy!AA:AA,"true") -> 0 | AQ55: =+Q55-AP55 -> 0 | AR55: =+COUNTIFS(FieldWy!A:A,H55,FieldWy!F:F,"<>",FieldWy!X:X,"PORTABILIDAD") -> 0 | AS55: =+U55+AR55 -> 0 | AT55: =+AN55-(AP55+AR55) -> 0 | AU55: =+Y55-AT55 -> 0
A56: HERNANDEZ HERNANDEZ KARINA | B56: DANIEL BENJAMIN MARQUEZ BACA | C56: 1 | D56: Tiendas criticas | G56: Vacante | H56: 2092192 | I56: SUBURBIA PACHUCA | J56: PACHUCA | K56: Suburbia | L56: =+IFERROR(M56/N56,0) -> 0 | M56: =SUM(Altas!E53:AI53) -> 0 | N56: =VLOOKUP(H56,Cuota!$D:$DU,119,0) -> 2.0482154 | O56: =+M56-N56 -> -2.0482154 | P56: =+IFERROR(Q56/R56,0) -> 0 | Q56: =+SUM(Altas!E100:AI100) -> 0 | R56: =VLOOKUP(H56,Tabla2[[#All],[IDPV]:[PP VOZ]],120,0) -> 0.96380871 | S56: =+Q56-R56 -> -0.96380871 | T56: =+IFERROR(U56/V56,0) -> 0 | U56: =+SUM(Altas!E147:AI147) -> 0 | V56: =VLOOKUP(H56,Tabla2[[#All],[IDPV]:[PP VOZ]],121,0) -> 0.120598 | W56: =+U56-V56 -> -0.120598 | X56: =+IFERROR(Y56/Z56,0) -> 0 | Y56: =+M56-(Q56+U56) -> 0 | Z56: =VLOOKUP(H56,Tabla2[[#All],[IDPV]:[PP VOZ]],122,0) -> 0.96380871 | AA56: =+Y56-Z56 -> -0.96380871 | AB56: =+M56/$F$3 -> 0 | AC56: =+N56/$F$3 -> 2.0482154 | AD56: =+AB56-AC56 -> -2.0482154 | AE56: =+Q56/$F$3 -> 0 | AF56: =+R56/$F$3 -> 0.96380871 | AG56: =+AE56-AF56 -> -0.96380871 | AH56: =+U56/$F$3 -> 0 | AI56: =+V56/$F$3 -> 0.120598 | AJ56: =+AH56-AI56 -> -0.120598 | AK56: =+Y56/#REF! -> #REF! | AL56: =+Z56/#REF! -> #REF! | AM56: =+AK56-AL56 -> #REF! | AN56: =+COUNTIFS(FieldWy!A:A,H56,FieldWy!F:F,"<>") -> 0 | AO56: =+M56-AN56 -> 0 | AP56: =+COUNTIFS(FieldWy!A:A,H56,FieldWy!F:F,"<>",FieldWy!AA:AA,"true") -> 0 | AQ56: =+Q56-AP56 -> 0 | AR56: =+COUNTIFS(FieldWy!A:A,H56,FieldWy!F:F,"<>",FieldWy!X:X,"PORTABILIDAD") -> 0 | AS56: =+U56+AR56 -> 0 | AT56: =+AN56-(AP56+AR56) -> 0 | AU56: =+Y56-AT56 -> 0
A57: SANCHEZ MEZA JOB | B57: EDGAR RAUL HERNANDEZ CERVANTES | C57: 1 | H57: 2092219 | I57: Suburbia Alfredo del Mazo | J57: Toluca de Lerdo | K57: SUBURBIA | L57: =+IFERROR(M57/N57,0) -> 0 | M57: =SUM(Altas!E54:AI54) -> 0 | N57: =VLOOKUP(H57,Cuota!$D:$DU,119,0) -> 1.3597806 | O57: =+M57-N57 -> -1.3597806 | P57: =+IFERROR(Q57/R57,0) -> 0 | Q57: =+SUM(Altas!E101:AI101) -> 0 | R57: =VLOOKUP(H57,Tabla2[[#All],[IDPV]:[PP VOZ]],120,0) -> 0.53365888 | S57: =+Q57-R57 -> -0.53365888 | T57: =+IFERROR(U57/V57,0) -> 0 | U57: =+SUM(Altas!E148:AI148) -> 0 | V57: =VLOOKUP(H57,Tabla2[[#All],[IDPV]:[PP VOZ]],121,0) -> 0.120598 | W57: =+U57-V57 -> -0.120598 | X57: =+IFERROR(Y57/Z57,0) -> 0 | Y57: =+M57-(Q57+U57) -> 0 | Z57: =VLOOKUP(H57,Tabla2[[#All],[IDPV]:[PP VOZ]],122,0) -> 0.70552375 | AA57: =+Y57-Z57 -> -0.70552375 | AB57: =+M57/$F$3 -> 0 | AC57: =+N57/$F$3 -> 1.3597806 | AD57: =+AB57-AC57 -> -1.3597806 | AE57: =+Q57/$F$3 -> 0 | AF57: =+R57/$F$3 -> 0.53365888 | AG57: =+AE57-AF57 -> -0.53365888 | AH57: =+U57/$F$3 -> 0 | AI57: =+V57/$F$3 -> 0.120598 | AJ57: =+AH57-AI57 -> -0.120598 | AN57: =+COUNTIFS(FieldWy!A:A,H57,FieldWy!F:F,"<>") -> 0 | AO57: =+M57-AN57 -> 0 | AP57: =+COUNTIFS(FieldWy!A:A,H57,FieldWy!F:F,"<>",FieldWy!AA:AA,"true") -> 0 | AQ57: =+Q57-AP57 -> 0 | AR57: =+COUNTIFS(FieldWy!A:A,H57,FieldWy!F:F,"<>",FieldWy!X:X,"PORTABILIDAD") -> 0 | AS57: =+U57+AR57 -> 0 | AT57: =+AN57-(AP57+AR57) -> 0 | AU57: =+Y57-AT57 -> 0
A58: SANCHEZ MEZA JOB | B58: ERIK ALEJANDRO GARCIA | C58: 1 | H58: 2092308 | I58: ELEKTRA OCOYOACAC EDO. MEX | J58: Ocoyoacac | K58: ELEKTRA | L58: =+IFERROR(M58/N58,0) -> 0 | M58: =SUM(Altas!E55:AI55) -> 0 | N58: =VLOOKUP(H58,Cuota!$D:$DU,119,0) -> 1.3597806 | O58: =+M58-N58 -> -1.3597806 | P58: =+IFERROR(Q58/R58,0) -> 0 | Q58: =+SUM(Altas!E102:AI102) -> 0 | R58: =VLOOKUP(H58,Tabla2[[#All],[IDPV]:[PP VOZ]],120,0) -> 0.27537392 | S58: =+Q58-R58 -> -0.27537392 | T58: =+IFERROR(U58/V58,0) -> 0 | U58: =+SUM(Altas!E149:AI149) -> 0 | V58: =VLOOKUP(H58,Tabla2[[#All],[IDPV]:[PP VOZ]],121,0) -> 0.120598 | W58: =+U58-V58 -> -0.120598 | X58: =+IFERROR(Y58/Z58,0) -> 0 | Y58: =+M58-(Q58+U58) -> 0 | Z58: =VLOOKUP(H58,Tabla2[[#All],[IDPV]:[PP VOZ]],122,0) -> 0.96380871 | AA58: =+Y58-Z58 -> -0.96380871 | AB58: =+M58/$F$3 -> 0 | AC58: =+N58/$F$3 -> 1.3597806 | AD58: =+AB58-AC58 -> -1.3597806 | AE58: =+Q58/$F$3 -> 0 | AF58: =+R58/$F$3 -> 0.27537392 | AG58: =+AE58-AF58 -> -0.27537392 | AH58: =+U58/$F$3 -> 0 | AI58: =+V58/$F$3 -> 0.120598 | AJ58: =+AH58-AI58 -> -0.120598 | AN58: =+COUNTIFS(FieldWy!A:A,H58,FieldWy!F:F,"<>") -> 0 | AO58: =+M58-AN58 -> 0 | AP58: =+COUNTIFS(FieldWy!A:A,H58,FieldWy!F:F,"<>",FieldWy!AA:AA,"true") -> 0 | AQ58: =+Q58-AP58 -> 0 | AR58: =+COUNTIFS(FieldWy!A:A,H58,FieldWy!F:F,"<>",FieldWy!X:X,"PORTABILIDAD") -> 0 | AS58: =+U58+AR58 -> 0 | AT58: =+AN58-(AP58+AR58) -> 0 | AU58: =+Y58-AT58 -> 0
A59: SANCHEZ MEZA JOB | B59: EDGAR RAUL HERNANDEZ CERVANTES | C59: 1 | H59: 2092309 | I59: ELEKTRA MEGA TOLUCA MERCADO JUAREZ | J59: Almoloya de Juarez | K59: ELEKTRA | L59: =+IFERROR(M59/N59,0) -> 0 | M59: =SUM(Altas!E56:AI56) -> 0 | N59: =VLOOKUP(H59,Cuota!$D:$DU,119,0) -> 1.4974676 | O59: =+M59-N59 -> -1.4974676 | P59: =+IFERROR(Q59/R59,0) -> 0 | Q59: =+SUM(Altas!E103:AI103) -> 0 | R59: =VLOOKUP(H59,Tabla2[[#All],[IDPV]:[PP VOZ]],120,0) -> 0.82612175 | S59: =+Q59-R59 -> -0.82612175 | T59: =+IFERROR(U59/V59,0) -> 0 | U59: =+SUM(Altas!E150:AI150) -> 0 | V59: =VLOOKUP(H59,Tabla2[[#All],[IDPV]:[PP VOZ]],121,0) -> 0.120598 | W59: =+U59-V59 -> -0.120598 | X59: =+IFERROR(Y59/Z59,0) -> 0 | Y59: =+M59-(Q59+U59) -> 0 | Z59: =VLOOKUP(H59,Tabla2[[#All],[IDPV]:[PP VOZ]],122,0) -> 0.55074783 | AA59: =+Y59-Z59 -> -0.55074783 | AB59: =+M59/$F$3 -> 0 | AC59: =+N59/$F$3 -> 1.4974676 | AD59: =+AB59-AC59 -> -1.4974676 | AE59: =+Q59/$F$3 -> 0 | AF59: =+R59/$F$3 -> 0.82612175 | AG59: =+AE59-AF59 -> -0.82612175 | AH59: =+U59/$F$3 -> 0 | AI59: =+V59/$F$3 -> 0.120598 | AJ59: =+AH59-AI59 -> -0.120598 | AN59: =+COUNTIFS(FieldWy!A:A,H59,FieldWy!F:F,"<>") -> 0 | AO59: =+M59-AN59 -> 0 | AP59: =+COUNTIFS(FieldWy!A:A,H59,FieldWy!F:F,"<>",FieldWy!AA:AA,"true") -> 0 | AQ59: =+Q59-AP59 -> 0 | AR59: =+COUNTIFS(FieldWy!A:A,H59,FieldWy!F:F,"<>",FieldWy!X:X,"PORTABILIDAD") -> 0 | AS59: =+U59+AR59 -> 0 | AT59: =+AN59-(AP59+AR59) -> 0 | AU59: =+Y59-AT59 -> 0
A60: SANCHEZ MEZA JOB | B60: EDSON FERREYRA FFLORES | C60: 1 | H60: 2092310 | I60: ELEKTRA MEGA TENANFO DEL VALLE | J60: Tenango Del Valle | K60: ELEKTRA | L60: =+IFERROR(M60/N60,0) -> 0 | M60: =SUM(Altas!E57:AI57) -> 0 | N60: =VLOOKUP(H60,Cuota!$D:$DU,119,0) -> 1.3597806 | O60: =+M60-N60 -> -1.3597806 | P60: =+IFERROR(Q60/R60,0) -> 0 | Q60: =+SUM(Altas!E104:AI104) -> 0 | R60: =VLOOKUP(H60,Tabla2[[#All],[IDPV]:[PP VOZ]],120,0) -> 0.68843479 | S60: =+Q60-R60 -> -0.68843479 | T60: =+IFERROR(U60/V60,0) -> 0 | U60: =+SUM(Altas!E151:AI151) -> 0 | V60: =VLOOKUP(H60,Tabla2[[#All],[IDPV]:[PP VOZ]],121,0) -> 0.120598 | W60: =+U60-V60 -> -0.120598 | X60: =+IFERROR(Y60/Z60,0) -> 0 | Y60: =+M60-(Q60+U60) -> 0 | Z60: =VLOOKUP(H60,Tabla2[[#All],[IDPV]:[PP VOZ]],122,0) -> 0.55074783 | AA60: =+Y60-Z60 -> -0.55074783 | AB60: =+M60/$F$3 -> 0 | AC60: =+N60/$F$3 -> 1.3597806 | AD60: =+AB60-AC60 -> -1.3597806 | AE60: =+Q60/$F$3 -> 0 | AF60: =+R60/$F$3 -> 0.68843479 | AG60: =+AE60-AF60 -> -0.68843479 | AH60: =+U60/$F$3 -> 0 | AI60: =+V60/$F$3 -> 0.120598 | AJ60: =+AH60-AI60 -> -0.120598 | AN60: =+COUNTIFS(FieldWy!A:A,H60,FieldWy!F:F,"<>") -> 0 | AO60: =+M60-AN60 -> 0 | AP60: =+COUNTIFS(FieldWy!A:A,H60,FieldWy!F:F,"<>",FieldWy!AA:AA,"true") -> 0 | AQ60: =+Q60-AP60 -> 0 | AR60: =+COUNTIFS(FieldWy!A:A,H60,FieldWy!F:F,"<>",FieldWy!X:X,"PORTABILIDAD") -> 0 | AS60: =+U60+AR60 -> 0 | AT60: =+AN60-(AP60+AR60) -> 0 | AU60: =+Y60-AT60 -> 0
A61: HERNANDEZ HERNANDEZ KARINA | B61: DANIEL BENJAMIN MARQUEZ BACA | C61: 1 | D61: 10 Pdvs 20 y 21 Jun | E61: Arranque rapido | G61: Estable | H61: 2092359 | I61: EKT TULIPANES (8290) | J61: PACHUCA | K61: Elektra | L61: =+IFERROR(M61/N61,0) -> 0 | M61: =SUM(Altas!E58:AI58) -> 0 | N61: =VLOOKUP(H61,Cuota!$D:$DU,119,0) -> 1.3597806 | O61: =+M61-N61 -> -1.3597806 | P61: =+IFERROR(Q61/R61,0) -> 0 | Q61: =+SUM(Altas!E105:AI105) -> 0 | R61: =VLOOKUP(H61,Tabla2[[#All],[IDPV]:[PP VOZ]],120,0) -> 0.68843479 | S61: =+Q61-R61 -> -0.68843479 | T61: =+IFERROR(U61/V61,0) -> 0 | U61: =+SUM(Altas!E152:AI152) -> 0 | V61: =VLOOKUP(H61,Tabla2[[#All],[IDPV]:[PP VOZ]],121,0) -> 0.120598 | W61: =+U61-V61 -> -0.120598 | X61: =+IFERROR(Y61/Z61,0) -> 0 | Y61: =+M61-(Q61+U61) -> 0 | Z61: =VLOOKUP(H61,Tabla2[[#All],[IDPV]:[PP VOZ]],122,0) -> 0.55074783 | AA61: =+Y61-Z61 -> -0.55074783 | AB61: =+M61/$F$3 -> 0 | AC61: =+N61/$F$3 -> 1.3597806 | AD61: =+AB61-AC61 -> -1.3597806 | AE61: =+Q61/$F$3 -> 0 | AF61: =+R61/$F$3 -> 0.68843479 | AG61: =+AE61-AF61 -> -0.68843479 | AH61: =+U61/$F$3 -> 0 | AI61: =+V61/$F$3 -> 0.120598 | AJ61: =+AH61-AI61 -> -0.120598 | AK61: =+Y61/#REF! -> #REF! | AL61: =+Z61/#REF! -> #REF! | AM61: =+AK61-AL61 -> #REF! | AN61: =+COUNTIFS(FieldWy!A:A,H61,FieldWy!F:F,"<>") -> 0 | AO61: =+M61-AN61 -> 0 | AP61: =+COUNTIFS(FieldWy!A:A,H61,FieldWy!F:F,"<>",FieldWy!AA:AA,"true") -> 0 | AQ61: =+Q61-AP61 -> 0 | AR61: =+COUNTIFS(FieldWy!A:A,H61,FieldWy!F:F,"<>",FieldWy!X:X,"PORTABILIDAD") -> 0 | AS61: =+U61+AR61 -> 0 | AT61: =+AN61-(AP61+AR61) -> 0 | AU61: =+Y61-AT61 -> 0
A62: REYES ZARRABAL CRISTOPHER | B62: CESAR GARRIDO BADILLO | C62: 1 | G62: Estable | H62: 2092361 | I62: MINI ELEKTRA SAHAGUN | J62: CD SAHAGUN | K62: Elektra | L62: =+IFERROR(M62/N62,0) -> 0 | M62: =SUM(Altas!E59:AI59) -> 0 | N62: =VLOOKUP(H62,Cuota!$D:$DU,119,0) -> 1.3597806 | O62: =+M62-N62 -> -1.3597806 | P62: =+IFERROR(Q62/R62,0) -> 0 | Q62: =+SUM(Altas!E106:AI106) -> 0 | R62: =VLOOKUP(H62,Tabla2[[#All],[IDPV]:[PP VOZ]],120,0) -> 0.68843479 | S62: =+Q62-R62 -> -0.68843479 | T62: =+IFERROR(U62/V62,0) -> 0 | U62: =+SUM(Altas!E153:AI153) -> 0 | V62: =VLOOKUP(H62,Tabla2[[#All],[IDPV]:[PP VOZ]],121,0) -> 0.120598 | W62: =+U62-V62 -> -0.120598 | X62: =+IFERROR(Y62/Z62,0) -> 0 | Y62: =+M62-(Q62+U62) -> 0 | Z62: =VLOOKUP(H62,Tabla2[[#All],[IDPV]:[PP VOZ]],122,0) -> 0.55074783 | AA62: =+Y62-Z62 -> -0.55074783 | AB62: =+M62/$F$3 -> 0 | AC62: =+N62/$F$3 -> 1.3597806 | AD62: =+AB62-AC62 -> -1.3597806 | AE62: =+Q62/$F$3 -> 0 | AF62: =+R62/$F$3 -> 0.68843479 | AG62: =+AE62-AF62 -> -0.68843479 | AH62: =+U62/$F$3 -> 0 | AI62: =+V62/$F$3 -> 0.120598 | AJ62: =+AH62-AI62 -> -0.120598 | AK62: =+Y62/#REF! -> #REF! | AL62: =+Z62/#REF! -> #REF! | AM62: =+AK62-AL62 -> #REF! | AN62: =+COUNTIFS(FieldWy!A:A,H62,FieldWy!F:F,"<>") -> 0 | AO62: =+M62-AN62 -> 0 | AP62: =+COUNTIFS(FieldWy!A:A,H62,FieldWy!F:F,"<>",FieldWy!AA:AA,"true") -> 0 | AQ62: =+Q62-AP62 -> 0 | AR62: =+COUNTIFS(FieldWy!A:A,H62,FieldWy!F:F,"<>",FieldWy!X:X,"PORTABILIDAD") -> 0 | AS62: =+U62+AR62 -> 0 | AT62: =+AN62-(AP62+AR62) -> 0 | AU62: =+Y62-AT62 -> 0
A63: REYES ZARRABAL CRISTOPHER | B63: CESAR GARRIDO BADILLO | C63: 1 | G63: Estable | H63: 2092362 | I63: ELEKTRA TULANCINGO CUAUHTEMOC | J63: TULANCINGO DE BRAVO | K63: Elektra | L63: =+IFERROR(M63/N63,0) -> 0 | M63: =SUM(Altas!E60:AI60) -> 0 | N63: =VLOOKUP(H63,Cuota!$D:$DU,119,0) -> 0.94671975 | O63: =+M63-N63 -> -0.94671975 | P63: =+IFERROR(Q63/R63,0) -> 0 | Q63: =+SUM(Altas!E107:AI107) -> 0 | R63: =VLOOKUP(H63,Tabla2[[#All],[IDPV]:[PP VOZ]],120,0) -> 0.41306088 | S63: =+Q63-R63 -> -0.41306088 | T63: =+IFERROR(U63/V63,0) -> 0 | U63: =+SUM(Altas!E154:AI154) -> 0 | V63: =VLOOKUP(H63,Tabla2[[#All],[IDPV]:[PP VOZ]],121,0) -> 0.120598 | W63: =+U63-V63 -> -0.120598 | X63: =+IFERROR(Y63/Z63,0) -> 0 | Y63: =+M63-(Q63+U63) -> 0 | Z63: =VLOOKUP(H63,Tabla2[[#All],[IDPV]:[PP VOZ]],122,0) -> 0.41306088 | AA63: =+Y63-Z63 -> -0.41306088 | AB63: =+M63/$F$3 -> 0 | AC63: =+N63/$F$3 -> 0.94671975 | AD63: =+AB63-AC63 -> -0.94671975 | AE63: =+Q63/$F$3 -> 0 | AF63: =+R63/$F$3 -> 0.41306088 | AG63: =+AE63-AF63 -> -0.41306088 | AH63: =+U63/$F$3 -> 0 | AI63: =+V63/$F$3 -> 0.120598 | AJ63: =+AH63-AI63 -> -0.120598 | AK63: =+Y63/#REF! -> #REF! | AL63: =+Z63/#REF! -> #REF! | AM63: =+AK63-AL63 -> #REF! | AN63: =+COUNTIFS(FieldWy!A:A,H63,FieldWy!F:F,"<>") -> 0 | AO63: =+M63-AN63 -> 0 | AP63: =+COUNTIFS(FieldWy!A:A,H63,FieldWy!F:F,"<>",FieldWy!AA:AA,"true") -> 0 | AQ63: =+Q63-AP63 -> 0 | AR63: =+COUNTIFS(FieldWy!A:A,H63,FieldWy!F:F,"<>",FieldWy!X:X,"PORTABILIDAD") -> 0 | AS63: =+U63+AR63 -> 0 | AT63: =+AN63-(AP63+AR63) -> 0 | AU63: =+Y63-AT63 -> 0
A64: HERNANDEZ HERNANDEZ KARINA | B64: CESAR GARRIDO BADILLO | C64: 1 | D64: 10 tiendas 90 al 100% | G64: Estable | H64: 2092363 | I64: ELEKTRA TULANCINGO | J64: TULANCINGO DE BRAVO | K64: Elektra | L64: =+IFERROR(M64/N64,0) -> 0 | M64: =SUM(Altas!E61:AI61) -> 0 | N64: =VLOOKUP(H64,Cuota!$D:$DU,119,0) -> 1.3597806 | O64: =+M64-N64 -> -1.3597806 | P64: =+IFERROR(Q64/R64,0) -> 0 | Q64: =+SUM(Altas!E108:AI108) -> 0 | R64: =VLOOKUP(H64,Tabla2[[#All],[IDPV]:[PP VOZ]],120,0) -> 0.68843479 | S64: =+Q64-R64 -> -0.68843479 | T64: =+IFERROR(U64/V64,0) -> 0 | U64: =+SUM(Altas!E155:AI155) -> 0 | V64: =VLOOKUP(H64,Tabla2[[#All],[IDPV]:[PP VOZ]],121,0) -> 0.120598 | W64: =+U64-V64 -> -0.120598 | X64: =+IFERROR(Y64/Z64,0) -> 0 | Y64: =+M64-(Q64+U64) -> 0 | Z64: =VLOOKUP(H64,Tabla2[[#All],[IDPV]:[PP VOZ]],122,0) -> 0.55074783 | AA64: =+Y64-Z64 -> -0.55074783 | AB64: =+M64/$F$3 -> 0 | AC64: =+N64/$F$3 -> 1.3597806 | AD64: =+AB64-AC64 -> -1.3597806 | AE64: =+Q64/$F$3 -> 0 | AF64: =+R64/$F$3 -> 0.68843479 | AG64: =+AE64-AF64 -> -0.68843479 | AH64: =+U64/$F$3 -> 0 | AI64: =+V64/$F$3 -> 0.120598 | AJ64: =+AH64-AI64 -> -0.120598 | AK64: =+Y64/#REF! -> #REF! | AL64: =+Z64/#REF! -> #REF! | AM64: =+AK64-AL64 -> #REF! | AN64: =+COUNTIFS(FieldWy!A:A,H64,FieldWy!F:F,"<>") -> 0 | AO64: =+M64-AN64 -> 0 | AP64: =+COUNTIFS(FieldWy!A:A,H64,FieldWy!F:F,"<>",FieldWy!AA:AA,"true") -> 0 | AQ64: =+Q64-AP64 -> 0 | AR64: =+COUNTIFS(FieldWy!A:A,H64,FieldWy!F:F,"<>",FieldWy!X:X,"PORTABILIDAD") -> 0 | AS64: =+U64+AR64 -> 0 | AT64: =+AN64-(AP64+AR64) -> 0 | AU64: =+Y64-AT64 -> 0
A65: REYES ZARRABAL CRISTOPHER | B65: JIOBANI MARIN BUENDIA BARCENAS | C65: 1 | D65: Tiendas criticas | G65: Nuevo promotor | H65: 2092366 | I65: EKT TULA CALZADA | J65: TULA DE ALLENDE | K65: Elektra | L65: =+IFERROR(M65/N65,0) -> 0 | M65: =SUM(Altas!E62:AI62) -> 0 | N65: =VLOOKUP(H65,Cuota!$D:$DU,119,0) -> 0.94671975 | O65: =+M65-N65 -> -0.94671975 | P65: =+IFERROR(Q65/R65,0) -> 0 | Q65: =+SUM(Altas!E109:AI109) -> 0 | R65: =VLOOKUP(H65,Tabla2[[#All],[IDPV]:[PP VOZ]],120,0) -> 0.41306088 | S65: =+Q65-R65 -> -0.41306088 | T65: =+IFERROR(U65/V65,0) -> 0 | U65: =+SUM(Altas!E156:AI156) -> 0 | V65: =VLOOKUP(H65,Tabla2[[#All],[IDPV]:[PP VOZ]],121,0) -> 0.120598 | W65: =+U65-V65 -> -0.120598 | X65: =+IFERROR(Y65/Z65,0) -> 0 | Y65: =+M65-(Q65+U65) -> 0 | Z65: =VLOOKUP(H65,Tabla2[[#All],[IDPV]:[PP VOZ]],122,0) -> 0.41306088 | AA65: =+Y65-Z65 -> -0.41306088 | AB65: =+M65/$F$3 -> 0 | AC65: =+N65/$F$3 -> 0.94671975 | AD65: =+AB65-AC65 -> -0.94671975 | AE65: =+Q65/$F$3 -> 0 | AF65: =+R65/$F$3 -> 0.41306088 | AG65: =+AE65-AF65 -> -0.41306088 | AH65: =+U65/$F$3 -> 0 | AI65: =+V65/$F$3 -> 0.120598 | AJ65: =+AH65-AI65 -> -0.120598 | AK65: =+Y65/#REF! -> #REF! | AL65: =+Z65/#REF! -> #REF! | AM65: =+AK65-AL65 -> #REF! | AN65: =+COUNTIFS(FieldWy!A:A,H65,FieldWy!F:F,"<>") -> 0 | AO65: =+M65-AN65 -> 0 | AP65: =+COUNTIFS(FieldWy!A:A,H65,FieldWy!F:F,"<>",FieldWy!AA:AA,"true") -> 0 | AQ65: =+Q65-AP65 -> 0 | AR65: =+COUNTIFS(FieldWy!A:A,H65,FieldWy!F:F,"<>",FieldWy!X:X,"PORTABILIDAD") -> 0 | AS65: =+U65+AR65 -> 0 | AT65: =+AN65-(AP65+AR65) -> 0 | AU65: =+Y65-AT65 -> 0
A66: REYES ZARRABAL CRISTOPHER | B66: JIOBANI MARIN BUENDIA BARCENAS | C66: 1 | D66: Tiendas criticas | G66: Vacante | H66: 2092367 | I66: ELEKTRA TEPEJI DEL RIO | J66: TULA DE ALLENDE | K66: Elektra | L66: =+IFERROR(M66/N66,0) -> 0 | M66: =SUM(Altas!E63:AI63) -> 0 | N66: =VLOOKUP(H66,Cuota!$D:$DU,119,0) -> 1.0844067 | O66: =+M66-N66 -> -1.0844067 | P66: =+IFERROR(Q66/R66,0) -> 0 | Q66: =+SUM(Altas!E110:AI110) -> 0 | R66: =VLOOKUP(H66,Tabla2[[#All],[IDPV]:[PP VOZ]],120,0) -> 0.41306088 | S66: =+Q66-R66 -> -0.41306088 | T66: =+IFERROR(U66/V66,0) -> 0 | U66: =+SUM(Altas!E157:AI157) -> 0 | V66: =VLOOKUP(H66,Tabla2[[#All],[IDPV]:[PP VOZ]],121,0) -> 0.120598 | W66: =+U66-V66 -> -0.120598 | X66: =+IFERROR(Y66/Z66,0) -> 0 | Y66: =+M66-(Q66+U66) -> 0 | Z66: =VLOOKUP(H66,Tabla2[[#All],[IDPV]:[PP VOZ]],122,0) -> 0.55074783 | AA66: =+Y66-Z66 -> -0.55074783 | AB66: =+M66/$F$3 -> 0 | AC66: =+N66/$F$3 -> 1.0844067 | AD66: =+AB66-AC66 -> -1.0844067 | AE66: =+Q66/$F$3 -> 0 | AF66: =+R66/$F$3 -> 0.41306088 | AG66: =+AE66-AF66 -> -0.41306088 | AH66: =+U66/$F$3 -> 0 | AI66: =+V66/$F$3 -> 0.120598 | AJ66: =+AH66-AI66 -> -0.120598 | AK66: =+Y66/#REF! -> #REF! | AL66: =+Z66/#REF! -> #REF! | AM66: =+AK66-AL66 -> #REF! | AN66: =+COUNTIFS(FieldWy!A:A,H66,FieldWy!F:F,"<>") -> 0 | AO66: =+M66-AN66 -> 0 | AP66: =+COUNTIFS(FieldWy!A:A,H66,FieldWy!F:F,"<>",FieldWy!AA:AA,"true") -> 0 | AQ66: =+Q66-AP66 -> 0 | AR66: =+COUNTIFS(FieldWy!A:A,H66,FieldWy!F:F,"<>",FieldWy!X:X,"PORTABILIDAD") -> 0 | AS66: =+U66+AR66 -> 0 | AT66: =+AN66-(AP66+AR66) -> 0 | AU66: =+Y66-AT66 -> 0
A67: REYES ZARRABAL CRISTOPHER | B67: JIOBANI MARIN BUENDIA BARCENAS | C67: 1 | G67: Nuevo promotor | H67: 2092437 | I67: ELEKTRA TLAXCOAPAN | J67: TLAXCOAPAN | K67: Elektra | L67: =+IFERROR(M67/N67,0) -> 0 | M67: =SUM(Altas!E64:AI64) -> 0 | N67: =VLOOKUP(H67,Cuota!$D:$DU,119,0) -> 0.94671975 | O67: =+M67-N67 -> -0.94671975 | P67: =+IFERROR(Q67/R67,0) -> 1200.7915 | Q67: =+SUM(Altas!E111:AI111) -> 496 | R67: =VLOOKUP(H67,Tabla2[[#All],[IDPV]:[PP VOZ]],120,0) -> 0.41306088 | S67: =+Q67-R67 -> 495.58694 | T67: =+IFERROR(U67/V67,0) -> 0 | U67: =+SUM(Altas!E158:AI158) -> 0 | V67: =VLOOKUP(H67,Tabla2[[#All],[IDPV]:[PP VOZ]],121,0) -> 0.120598 | W67: =+U67-V67 -> -0.120598 | X67: =+IFERROR(Y67/Z67,0) -> -1200.7915 | Y67: =+M67-(Q67+U67) -> -496 | Z67: =VLOOKUP(H67,Tabla2[[#All],[IDPV]:[PP VOZ]],122,0) -> 0.41306088 | AA67: =+Y67-Z67 -> -496.41306 | AB67: =+M67/$F$3 -> 0 | AC67: =+N67/$F$3 -> 0.94671975 | AD67: =+AB67-AC67 -> -0.94671975 | AE67: =+Q67/$F$3 -> 496 | AF67: =+R67/$F$3 -> 0.41306088 | AG67: =+AE67-AF67 -> 495.58694 | AH67: =+U67/$F$3 -> 0 | AI67: =+V67/$F$3 -> 0.120598 | AJ67: =+AH67-AI67 -> -0.120598 | AK67: =+Y67/#REF! -> #REF! | AL67: =+Z67/#REF! -> #REF! | AM67: =+AK67-AL67 -> #REF! | AN67: =+COUNTIFS(FieldWy!A:A,H67,FieldWy!F:F,"<>") -> 0 | AO67: =+M67-AN67 -> 0 | AP67: =+COUNTIFS(FieldWy!A:A,H67,FieldWy!F:F,"<>",FieldWy!AA:AA,"true") -> 0 | AQ67: =+Q67-AP67 -> 496 | AR67: =+COUNTIFS(FieldWy!A:A,H67,FieldWy!F:F,"<>",FieldWy!X:X,"PORTABILIDAD") -> 0 | AS67: =+U67+AR67 -> 0 | AT67: =+AN67-(AP67+AR67) -> 0 | AU67: =+Y67-AT67 -> -496
A68: SANCHEZ MEZA JOB | B68: ERIK ALEJANDRO GARCIA | C68: 1 | H68: 2092446 | I68: EKT TEMOAYA EDO. MEXICO | J68: Temoaya | K68: ELEKTRA | L68: =+IFERROR(M68/N68,0) -> 0 | M68: =SUM(Altas!E65:AI65) -> 0 | N68: =VLOOKUP(H68,Cuota!$D:$DU,119,0) -> 1.3597806 | O68: =+M68-N68 -> -1.3597806 | P68: =+IFERROR(Q68/R68,0) -> 0 | Q68: =+SUM(Altas!E112:AI112) -> 0 | R68: =VLOOKUP(H68,Tabla2[[#All],[IDPV]:[PP VOZ]],120,0) -> 0.41306088 | S68: =+Q68-R68 -> -0.41306088 | T68: =+IFERROR(U68/V68,0) -> 0 | U68: =+SUM(Altas!E159:AI159) -> 0 | V68: =VLOOKUP(H68,Tabla2[[#All],[IDPV]:[PP VOZ]],121,0) -> 0.120598 | W68: =+U68-V68 -> -0.120598 | X68: =+IFERROR(Y68/Z68,0) -> 0 | Y68: =+M68-(Q68+U68) -> 0 | Z68: =VLOOKUP(H68,Tabla2[[#All],[IDPV]:[PP VOZ]],122,0) -> 0.82612175 | AA68: =+Y68-Z68 -> -0.82612175 | AB68: =+M68/$F$3 -> 0 | AC68: =+N68/$F$3 -> 1.3597806 | AD68: =+AB68-AC68 -> -1.3597806 | AE68: =+Q68/$F$3 -> 0 | AF68: =+R68/$F$3 -> 0.41306088 | AG68: =+AE68-AF68 -> -0.41306088 | AH68: =+U68/$F$3 -> 0 | AI68: =+V68/$F$3 -> 0.120598 | AJ68: =+AH68-AI68 -> -0.120598 | AN68: =+COUNTIFS(FieldWy!A:A,H68,FieldWy!F:F,"<>") -> 0 | AO68: =+M68-AN68 -> 0 | AP68: =+COUNTIFS(FieldWy!A:A,H68,FieldWy!F:F,"<>",FieldWy!AA:AA,"true") -> 0 | AQ68: =+Q68-AP68 -> 0 | AR68: =+COUNTIFS(FieldWy!A:A,H68,FieldWy!F:F,"<>",FieldWy!X:X,"PORTABILIDAD") -> 0 | AS68: =+U68+AR68 -> 0 | AT68: =+AN68-(AP68+AR68) -> 0 | AU68: =+Y68-AT68 -> 0
A69: SANCHEZ MEZA JOB | B69: EDGAR RAUL HERNANDEZ CERVANTES | C69: 1 | H69: 2092447 | I69: EKT Mega Valle De Bravo | J69: Valle de Bravo | K69: ELEKTRA | L69: =+IFERROR(M69/N69,0) -> 0 | M69: =SUM(Altas!E66:AI66) -> 0 | N69: =VLOOKUP(H69,Cuota!$D:$DU,119,0) -> 1.3597806 | O69: =+M69-N69 -> -1.3597806 | P69: =+IFERROR(Q69/R69,0) -> 0 | Q69: =+SUM(Altas!E113:AI113) -> 0 | R69: =VLOOKUP(H69,Tabla2[[#All],[IDPV]:[PP VOZ]],120,0) -> 0.55074783 | S69: =+Q69-R69 -> -0.55074783 | T69: =+IFERROR(U69/V69,0) -> 0 | U69: =+SUM(Altas!E160:AI160) -> 0 | V69: =VLOOKUP(H69,Tabla2[[#All],[IDPV]:[PP VOZ]],121,0) -> 0.120598 | W69: =+U69-V69 -> -0.120598 | X69: =+IFERROR(Y69/Z69,0) -> 0 | Y69: =+M69-(Q69+U69) -> 0 | Z69: =VLOOKUP(H69,Tabla2[[#All],[IDPV]:[PP VOZ]],122,0) -> 0.68843479 | AA69: =+Y69-Z69 -> -0.68843479 | AB69: =+M69/$F$3 -> 0 | AC69: =+N69/$F$3 -> 1.3597806 | AD69: =+AB69-AC69 -> -1.3597806 | AE69: =+Q69/$F$3 -> 0 | AF69: =+R69/$F$3 -> 0.55074783 | AG69: =+AE69-AF69 -> -0.55074783 | AH69: =+U69/$F$3 -> 0 | AI69: =+V69/$F$3 -> 0.120598 | AJ69: =+AH69-AI69 -> -0.120598 | AN69: =+COUNTIFS(FieldWy!A:A,H69,FieldWy!F:F,"<>") -> 0 | AO69: =+M69-AN69 -> 0 | AP69: =+COUNTIFS(FieldWy!A:A,H69,FieldWy!F:F,"<>",FieldWy!AA:AA,"true") -> 0 | AQ69: =+Q69-AP69 -> 0 | AR69: =+COUNTIFS(FieldWy!A:A,H69,FieldWy!F:F,"<>",FieldWy!X:X,"PORTABILIDAD") -> 0 | AS69: =+U69+AR69 -> 0 | AT69: =+AN69-(AP69+AR69) -> 0 | AU69: =+Y69-AT69 -> 0
A70: OLIVARES HUERTA LUIS FERNANDO | B70: EDSON FERREYRA FFLORES | C70: 1 | H70: 2092457 | I70: EKT MEGA TENANCINGO EDO DE MEX | J70: Tenancingo | K70: ELEKTRA | L70: =+IFERROR(M70/N70,0) -> 0 | M70: =SUM(Altas!E67:AI67) -> 0 | N70: =VLOOKUP(H70,Cuota!$D:$DU,119,0) -> 1.4974676 | O70: =+M70-N70 -> -1.4974676 | P70: =+IFERROR(Q70/R70,0) -> 0 | Q70: =+SUM(Altas!E114:AI114) -> 0 | R70: =VLOOKUP(H70,Tabla2[[#All],[IDPV]:[PP VOZ]],120,0) -> 0.82612175 | S70: =+Q70-R70 -> -0.82612175 | T70: =+IFERROR(U70/V70,0) -> 0 | U70: =+SUM(Altas!E161:AI161) -> 0 | V70: =VLOOKUP(H70,Tabla2[[#All],[IDPV]:[PP VOZ]],121,0) -> 0.120598 | W70: =+U70-V70 -> -0.120598 | X70: =+IFERROR(Y70/Z70,0) -> 0 | Y70: =+M70-(Q70+U70) -> 0 | Z70: =VLOOKUP(H70,Tabla2[[#All],[IDPV]:[PP VOZ]],122,0) -> 0.55074783 | AA70: =+Y70-Z70 -> -0.55074783 | AB70: =+M70/$F$3 -> 0 | AC70: =+N70/$F$3 -> 1.4974676 | AD70: =+AB70-AC70 -> -1.4974676 | AE70: =+Q70/$F$3 -> 0 | AF70: =+R70/$F$3 -> 0.82612175 | AG70: =+AE70-AF70 -> -0.82612175 | AH70: =+U70/$F$3 -> 0 | AI70: =+V70/$F$3 -> 0.120598 | AJ70: =+AH70-AI70 -> -0.120598 | AN70: =+COUNTIFS(FieldWy!A:A,H70,FieldWy!F:F,"<>") -> 0 | AO70: =+M70-AN70 -> 0 | AP70: =+COUNTIFS(FieldWy!A:A,H70,FieldWy!F:F,"<>",FieldWy!AA:AA,"true") -> 0 | AQ70: =+Q70-AP70 -> 0 | AR70: =+COUNTIFS(FieldWy!A:A,H70,FieldWy!F:F,"<>",FieldWy!X:X,"PORTABILIDAD") -> 0 | AS70: =+U70+AR70 -> 0 | AT70: =+AN70-(AP70+AR70) -> 0 | AU70: =+Y70-AT70 -> 0
A71: SANCHEZ MEZA JOB | B71: ERIK ALEJANDRO GARCIA | C71: 1 | H71: 2092781 | I71: EKT XONACATLAN | J71: Xonacatlan | K71: ELEKTRA | L71: =+IFERROR(M71/N71,0) -> 0 | M71: =SUM(Altas!E68:AI68) -> 0 | N71: =VLOOKUP(H71,Cuota!$D:$DU,119,0) -> 1.2220937 | O71: =+M71-N71 -> -1.2220937 | P71: =+IFERROR(Q71/R71,0) -> 0 | Q71: =+SUM(Altas!E115:AI115) -> 0 | R71: =VLOOKUP(H71,Tabla2[[#All],[IDPV]:[PP VOZ]],120,0) -> 0.55074783 | S71: =+Q71-R71 -> -0.55074783 | T71: =+IFERROR(U71/V71,0) -> 0 | U71: =+SUM(Altas!E162:AI162) -> 0 | V71: =VLOOKUP(H71,Tabla2[[#All],[IDPV]:[PP VOZ]],121,0) -> 0.120598 | W71: =+U71-V71 -> -0.120598 | X71: =+IFERROR(Y71/Z71,0) -> 0 | Y71: =+M71-(Q71+U71) -> 0 | Z71: =VLOOKUP(H71,Tabla2[[#All],[IDPV]:[PP VOZ]],122,0) -> 0.55074783 | AA71: =+Y71-Z71 -> -0.55074783 | AB71: =+M71/$F$3 -> 0 | AC71: =+N71/$F$3 -> 1.2220937 | AD71: =+AB71-AC71 -> -1.2220937 | AE71: =+Q71/$F$3 -> 0 | AF71: =+R71/$F$3 -> 0.55074783 | AG71: =+AE71-AF71 -> -0.55074783 | AH71: =+U71/$F$3 -> 0 | AI71: =+V71/$F$3 -> 0.120598 | AJ71: =+AH71-AI71 -> -0.120598 | AN71: =+COUNTIFS(FieldWy!A:A,H71,FieldWy!F:F,"<>") -> 0 | AO71: =+M71-AN71 -> 0 | AP71: =+COUNTIFS(FieldWy!A:A,H71,FieldWy!F:F,"<>",FieldWy!AA:AA,"true") -> 0 | AQ71: =+Q71-AP71 -> 0 | AR71: =+COUNTIFS(FieldWy!A:A,H71,FieldWy!F:F,"<>",FieldWy!X:X,"PORTABILIDAD") -> 0 | AS71: =+U71+AR71 -> 0 | AT71: =+AN71-(AP71+AR71) -> 0 | AU71: =+Y71-AT71 -> 0
A72: GARCIA GUZMAN JESUS | B72: JOSE JAEN OSORIO PAGUIA | C72: 1 | H72: 2092784 | I72: MINIEKT ALMOLOYA DE JUAREZ | J72: Almoloya de Juarez | K72: ELEKTRA | L72: =+IFERROR(M72/N72,0) -> 0 | M72: =SUM(Altas!E69:AI69) -> 0 | N72: =VLOOKUP(H72,Cuota!$D:$DU,119,0) -> 1.1014957 | O72: =+M72-N72 -> -1.1014957 | P72: =+IFERROR(Q72/R72,0) -> 0 | Q72: =+SUM(Altas!E116:AI116) -> 0 | R72: =VLOOKUP(H72,Tabla2[[#All],[IDPV]:[PP VOZ]],120,0) -> 0.13768696 | S72: =+Q72-R72 -> -0.13768696 | T72: =+IFERROR(U72/V72,0) -> 0 | U72: =+SUM(Altas!E163:AI163) -> 0 | V72: =VLOOKUP(H72,Tabla2[[#All],[IDPV]:[PP VOZ]],121,0) -> 0 | W72: =+U72-V72 -> 0 | X72: =+IFERROR(Y72/Z72,0) -> 0 | Y72: =+M72-(Q72+U72) -> 0 | Z72: =VLOOKUP(H72,Tabla2[[#All],[IDPV]:[PP VOZ]],122,0) -> 0.96380871 | AA72: =+Y72-Z72 -> -0.96380871 | AB72: =+M72/$F$3 -> 0 | AC72: =+N72/$F$3 -> 1.1014957 | AD72: =+AB72-AC72 -> -1.1014957 | AE72: =+Q72/$F$3 -> 0 | AF72: =+R72/$F$3 -> 0.13768696 | AG72: =+AE72-AF72 -> -0.13768696 | AH72: =+U72/$F$3 -> 0 | AI72: =+V72/$F$3 -> 0 | AJ72: =+AH72-AI72 -> 0 | AN72: =+COUNTIFS(FieldWy!A:A,H72,FieldWy!F:F,"<>") -> 0 | AO72: =+M72-AN72 -> 0 | AP72: =+COUNTIFS(FieldWy!A:A,H72,FieldWy!F:F,"<>",FieldWy!AA:AA,"true") -> 0 | AQ72: =+Q72-AP72 -> 0 | AR72: =+COUNTIFS(FieldWy!A:A,H72,FieldWy!F:F,"<>",FieldWy!X:X,"PORTABILIDAD") -> 0 | AS72: =+U72+AR72 -> 0 | AT72: =+AN72-(AP72+AR72) -> 0 | AU72: =+Y72-AT72 -> 0
A73: OLIVARES HUERTA LUIS FERNANDO | B73: EDSON FERREYRA FFLORES | C73: 1 | H73: 2092790 | I73: COPPEL TENANCINGO | J73: Tenancingo | K73: COPPEL | L73: =+IFERROR(M73/N73,0) -> 0 | M73: =SUM(Altas!E70:AI70) -> 0 | N73: =VLOOKUP(H73,Cuota!$D:$DU,119,0) -> 4.8019546 | O73: =+M73-N73 -> -4.8019546 | P73: =+IFERROR(Q73/R73,0) -> 0 | Q73: =+SUM(Altas!E117:AI117) -> 0 | R73: =VLOOKUP(H73,Tabla2[[#All],[IDPV]:[PP VOZ]],120,0) -> 3.8552348 | S73: =+Q73-R73 -> -3.8552348 | T73: =+IFERROR(U73/V73,0) -> 0 | U73: =+SUM(Altas!E164:AI164) -> 0 | V73: =VLOOKUP(H73,Tabla2[[#All],[IDPV]:[PP VOZ]],121,0) -> 0.120598 | W73: =+U73-V73 -> -0.120598 | X73: =+IFERROR(Y73/Z73,0) -> 0 | Y73: =+M73-(Q73+U73) -> 0 | Z73: =VLOOKUP(H73,Tabla2[[#All],[IDPV]:[PP VOZ]],122,0) -> 0.82612175 | AA73: =+Y73-Z73 -> -0.82612175 | AB73: =+M73/$F$3 -> 0 | AC73: =+N73/$F$3 -> 4.8019546 | AD73: =+AB73-AC73 -> -4.8019546 | AE73: =+Q73/$F$3 -> 0 | AF73: =+R73/$F$3 -> 3.8552348 | AG73: =+AE73-AF73 -> -3.8552348 | AH73: =+U73/$F$3 -> 0 | AI73: =+V73/$F$3 -> 0.120598 | AJ73: =+AH73-AI73 -> -0.120598 | AN73: =+COUNTIFS(FieldWy!A:A,H73,FieldWy!F:F,"<>") -> 0 | AO73: =+M73-AN73 -> 0 | AP73: =+COUNTIFS(FieldWy!A:A,H73,FieldWy!F:F,"<>",FieldWy!AA:AA,"true") -> 0 | AQ73: =+Q73-AP73 -> 0 | AR73: =+COUNTIFS(FieldWy!A:A,H73,FieldWy!F:F,"<>",FieldWy!X:X,"PORTABILIDAD") -> 0 | AS73: =+U73+AR73 -> 0 | AT73: =+AN73-(AP73+AR73) -> 0 | AU73: =+Y73-AT73 -> 0
A74: OLIVARES HUERTA LUIS FERNANDO | B74: EDSON FERREYRA FFLORES | C74: 1 | H74: 2092797 | I74: COPPEL CANADA INDEPENDENCIA | J74: Ixtapan de La Sal | K74: COPPEL | L74: =+IFERROR(M74/N74,0) -> 0 | M74: =SUM(Altas!E71:AI71) -> 0 | N74: =VLOOKUP(H74,Cuota!$D:$DU,119,0) -> 3.9929218 | O74: =+M74-N74 -> -3.9929218 | P74: =+IFERROR(Q74/R74,0) -> 0 | Q74: =+SUM(Altas!E118:AI118) -> 0 | R74: =VLOOKUP(H74,Tabla2[[#All],[IDPV]:[PP VOZ]],120,0) -> 2.6160522 | S74: =+Q74-R74 -> -2.6160522 | T74: =+IFERROR(U74/V74,0) -> 0 | U74: =+SUM(Altas!E165:AI165) -> 0 | V74: =VLOOKUP(H74,Tabla2[[#All],[IDPV]:[PP VOZ]],121,0) -> 0 | W74: =+U74-V74 -> 0 | X74: =+IFERROR(Y74/Z74,0) -> 0 | Y74: =+M74-(Q74+U74) -> 0 | Z74: =VLOOKUP(H74,Tabla2[[#All],[IDPV]:[PP VOZ]],122,0) -> 1.3768696 | AA74: =+Y74-Z74 -> -1.3768696 | AB74: =+M74/$F$3 -> 0 | AC74: =+N74/$F$3 -> 3.9929218 | AD74: =+AB74-AC74 -> -3.9929218 | AE74: =+Q74/$F$3 -> 0 | AF74: =+R74/$F$3 -> 2.6160522 | AG74: =+AE74-AF74 -> -2.6160522 | AH74: =+U74/$F$3 -> 0 | AI74: =+V74/$F$3 -> 0 | AJ74: =+AH74-AI74 -> 0 | AN74: =+COUNTIFS(FieldWy!A:A,H74,FieldWy!F:F,"<>") -> 0 | AO74: =+M74-AN74 -> 0 | AP74: =+COUNTIFS(FieldWy!A:A,H74,FieldWy!F:F,"<>",FieldWy!AA:AA,"true") -> 0 | AQ74: =+Q74-AP74 -> 0 | AR74: =+COUNTIFS(FieldWy!A:A,H74,FieldWy!F:F,"<>",FieldWy!X:X,"PORTABILIDAD") -> 0 | AS74: =+U74+AR74 -> 0 | AT74: =+AN74-(AP74+AR74) -> 0 | AU74: =+Y74-AT74 -> 0
A75: SANCHEZ MEZA JOB | B75: EDGAR RAUL HERNANDEZ CERVANTES | C75: 1 | H75: 2092923 | I75: COPPEL CANADA CARDENAS (1104) | J75: Villa Victoria | K75: COPPEL | L75: =+IFERROR(M75/N75,0) -> 0 | M75: =SUM(Altas!E72:AI72) -> 0 | N75: =VLOOKUP(H75,Cuota!$D:$DU,119,0) -> 1.9105285 | O75: =+M75-N75 -> -1.9105285 | P75: =+IFERROR(Q75/R75,0) -> 0 | Q75: =+SUM(Altas!E119:AI119) -> 0 | R75: =VLOOKUP(H75,Tabla2[[#All],[IDPV]:[PP VOZ]],120,0) -> 0.96380871 | S75: =+Q75-R75 -> -0.96380871 | T75: =+IFERROR(U75/V75,0) -> 0 | U75: =+SUM(Altas!E166:AI166) -> 0 | V75: =VLOOKUP(H75,Tabla2[[#All],[IDPV]:[PP VOZ]],121,0) -> 0.120598 | W75: =+U75-V75 -> -0.120598 | X75: =+IFERROR(Y75/Z75,0) -> 0 | Y75: =+M75-(Q75+U75) -> 0 | Z75: =VLOOKUP(H75,Tabla2[[#All],[IDPV]:[PP VOZ]],122,0) -> 0.82612175 | AA75: =+Y75-Z75 -> -0.82612175 | AB75: =+M75/$F$3 -> 0 | AC75: =+N75/$F$3 -> 1.9105285 | AD75: =+AB75-AC75 -> -1.9105285 | AE75: =+Q75/$F$3 -> 0 | AF75: =+R75/$F$3 -> 0.96380871 | AG75: =+AE75-AF75 -> -0.96380871 | AH75: =+U75/$F$3 -> 0 | AI75: =+V75/$F$3 -> 0.120598 | AJ75: =+AH75-AI75 -> -0.120598 | AN75: =+COUNTIFS(FieldWy!A:A,H75,FieldWy!F:F,"<>") -> 0 | AO75: =+M75-AN75 -> 0 | AP75: =+COUNTIFS(FieldWy!A:A,H75,FieldWy!F:F,"<>",FieldWy!AA:AA,"true") -> 0 | AQ75: =+Q75-AP75 -> 0 | AR75: =+COUNTIFS(FieldWy!A:A,H75,FieldWy!F:F,"<>",FieldWy!X:X,"PORTABILIDAD") -> 0 | AS75: =+U75+AR75 -> 0 | AT75: =+AN75-(AP75+AR75) -> 0 | AU75: =+Y75-AT75 -> 0
A76: REYES ZARRABAL CRISTOPHER | B76: JIOBANI MARIN BUENDIA BARCENAS | C76: 1 | D76: Tiendas criticas | G76: Vacante | H76: 2092936 | I76: EKT IXMIQUILPAN | J76: IXMIQUILPAN | K76: Elektra | L76: =+IFERROR(M76/N76,0) -> 0 | M76: =SUM(Altas!E73:AI73) -> 0 | N76: =VLOOKUP(H76,Cuota!$D:$DU,119,0) -> 0.94671975 | O76: =+M76-N76 -> -0.94671975 | P76: =+IFERROR(Q76/R76,0) -> 0 | Q76: =+SUM(Altas!E120:AI120) -> 0 | R76: =VLOOKUP(H76,Tabla2[[#All],[IDPV]:[PP VOZ]],120,0) -> 0.41306088 | S76: =+Q76-R76 -> -0.41306088 | T76: =+IFERROR(U76/V76,0) -> 0 | U76: =+SUM(Altas!E167:AI167) -> 0 | V76: =VLOOKUP(H76,Tabla2[[#All],[IDPV]:[PP VOZ]],121,0) -> 0.120598 | W76: =+U76-V76 -> -0.120598 | X76: =+IFERROR(Y76/Z76,0) -> 0 | Y76: =+M76-(Q76+U76) -> 0 | Z76: =VLOOKUP(H76,Tabla2[[#All],[IDPV]:[PP VOZ]],122,0) -> 0.41306088 | AA76: =+Y76-Z76 -> -0.41306088 | AB76: =+M76/$F$3 -> 0 | AC76: =+N76/$F$3 -> 0.94671975 | AD76: =+AB76-AC76 -> -0.94671975 | AE76: =+Q76/$F$3 -> 0 | AF76: =+R76/$F$3 -> 0.41306088 | AG76: =+AE76-AF76 -> -0.41306088 | AH76: =+U76/$F$3 -> 0 | AI76: =+V76/$F$3 -> 0.120598 | AJ76: =+AH76-AI76 -> -0.120598 | AK76: =+Y76/#REF! -> #REF! | AL76: =+Z76/#REF! -> #REF! | AM76: =+AK76-AL76 -> #REF! | AN76: =+COUNTIFS(FieldWy!A:A,H76,FieldWy!F:F,"<>") -> 0 | AO76: =+M76-AN76 -> 0 | AP76: =+COUNTIFS(FieldWy!A:A,H76,FieldWy!F:F,"<>",FieldWy!AA:AA,"true") -> 0 | AQ76: =+Q76-AP76 -> 0 | AR76: =+COUNTIFS(FieldWy!A:A,H76,FieldWy!F:F,"<>",FieldWy!X:X,"PORTABILIDAD") -> 0 | AS76: =+U76+AR76 -> 0 | AT76: =+AN76-(AP76+AR76) -> 0 | AU76: =+Y76-AT76 -> 0
A77: SANCHEZ MEZA JOB | B77: EDSON FERREYRA FFLORES | C77: 1 | H77: 2092975 | I77: COPPEL -CANADACOLÓN | J77: Toluca de Lerdo | K77: COPPEL | L77: =+IFERROR(M77/N77,0) -> 0 | M77: =SUM(Altas!E74:AI74) -> 0 | N77: =VLOOKUP(H77,Cuota!$D:$DU,119,0) -> 1.7728415 | O77: =+M77-N77 -> -1.7728415 | P77: =+IFERROR(Q77/R77,0) -> 0 | Q77: =+SUM(Altas!E121:AI121) -> 0 | R77: =VLOOKUP(H77,Tabla2[[#All],[IDPV]:[PP VOZ]],120,0) -> 0.96380871 | S77: =+Q77-R77 -> -0.96380871 | T77: =+IFERROR(U77/V77,0) -> 0 | U77: =+SUM(Altas!E168:AI168) -> 0 | V77: =VLOOKUP(H77,Tabla2[[#All],[IDPV]:[PP VOZ]],121,0) -> 0.120598 | W77: =+U77-V77 -> -0.120598 | X77: =+IFERROR(Y77/Z77,0) -> 0 | Y77: =+M77-(Q77+U77) -> 0 | Z77: =VLOOKUP(H77,Tabla2[[#All],[IDPV]:[PP VOZ]],122,0) -> 0.68843479 | AA77: =+Y77-Z77 -> -0.68843479 | AB77: =+M77/$F$3 -> 0 | AC77: =+N77/$F$3 -> 1.7728415 | AD77: =+AB77-AC77 -> -1.7728415 | AE77: =+Q77/$F$3 -> 0 | AF77: =+R77/$F$3 -> 0.96380871 | AG77: =+AE77-AF77 -> -0.96380871 | AH77: =+U77/$F$3 -> 0 | AI77: =+V77/$F$3 -> 0.120598 | AJ77: =+AH77-AI77 -> -0.120598 | AN77: =+COUNTIFS(FieldWy!A:A,H77,FieldWy!F:F,"<>") -> 0 | AO77: =+M77-AN77 -> 0 | AP77: =+COUNTIFS(FieldWy!A:A,H77,FieldWy!F:F,"<>",FieldWy!AA:AA,"true") -> 0 | AQ77: =+Q77-AP77 -> 0 | AR77: =+COUNTIFS(FieldWy!A:A,H77,FieldWy!F:F,"<>",FieldWy!X:X,"PORTABILIDAD") -> 0 | AS77: =+U77+AR77 -> 0 | AT77: =+AN77-(AP77+AR77) -> 0 | AU77: =+Y77-AT77 -> 0
A78: OLIVARES HUERTA LUIS FERNANDO | B78: EDSON FERREYRA FFLORES | C78: 1 | H78: 2092982 | I78: COPPEL VILLA GUERRERO | J78: Villa Guerrero | K78: COPPEL | L78: =+IFERROR(M78/N78,0) -> 0 | M78: =SUM(Altas!E75:AI75) -> 0 | N78: =VLOOKUP(H78,Cuota!$D:$DU,119,0) -> 1.7899305 | O78: =+M78-N78 -> -1.7899305 | P78: =+IFERROR(Q78/R78,0) -> 0 | Q78: =+SUM(Altas!E122:AI122) -> 0 | R78: =VLOOKUP(H78,Tabla2[[#All],[IDPV]:[PP VOZ]],120,0) -> 1.1014957 | S78: =+Q78-R78 -> -1.1014957 | T78: =+IFERROR(U78/V78,0) -> 0 | U78: =+SUM(Altas!E169:AI169) -> 0 | V78: =VLOOKUP(H78,Tabla2[[#All],[IDPV]:[PP VOZ]],121,0) -> 0 | W78: =+U78-V78 -> 0 | X78: =+IFERROR(Y78/Z78,0) -> 0 | Y78: =+M78-(Q78+U78) -> 0 | Z78: =VLOOKUP(H78,Tabla2[[#All],[IDPV]:[PP VOZ]],122,0) -> 0.68843479 | AA78: =+Y78-Z78 -> -0.68843479 | AB78: =+M78/$F$3 -> 0 | AC78: =+N78/$F$3 -> 1.7899305 | AD78: =+AB78-AC78 -> -1.7899305 | AE78: =+Q78/$F$3 -> 0 | AF78: =+R78/$F$3 -> 1.1014957 | AG78: =+AE78-AF78 -> -1.1014957 | AH78: =+U78/$F$3 -> 0 | AI78: =+V78/$F$3 -> 0 | AJ78: =+AH78-AI78 -> 0 | AN78: =+COUNTIFS(FieldWy!A:A,H78,FieldWy!F:F,"<>") -> 0 | AO78: =+M78-AN78 -> 0 | AP78: =+COUNTIFS(FieldWy!A:A,H78,FieldWy!F:F,"<>",FieldWy!AA:AA,"true") -> 0 | AQ78: =+Q78-AP78 -> 0 | AR78: =+COUNTIFS(FieldWy!A:A,H78,FieldWy!F:F,"<>",FieldWy!X:X,"PORTABILIDAD") -> 0 | AS78: =+U78+AR78 -> 0 | AT78: =+AN78-(AP78+AR78) -> 0 | AU78: =+Y78-AT78 -> 0
A79: REYES ZARRABAL CRISTOPHER | B79: CESAR GARRIDO BADILLO | C79: 1 | G79: Nuevo promotor | H79: 2093011 | I79: COPPEL PATIO TULANCINGO | J79: TULANCINGO DE BRAVO | K79: Coppel | L79: =+IFERROR(M79/N79,0) -> 0 | M79: =SUM(Altas!E76:AI76) -> 0 | N79: =VLOOKUP(H79,Cuota!$D:$DU,119,0) -> 1.0844067 | O79: =+M79-N79 -> -1.0844067 | P79: =+IFERROR(Q79/R79,0) -> 0 | Q79: =+SUM(Altas!E123:AI123) -> 0 | R79: =VLOOKUP(H79,Tabla2[[#All],[IDPV]:[PP VOZ]],120,0) -> 0.68843479 | S79: =+Q79-R79 -> -0.68843479 | T79: =+IFERROR(U79/V79,0) -> 0 | U79: =+SUM(Altas!E170:AI170) -> 0 | V79: =VLOOKUP(H79,Tabla2[[#All],[IDPV]:[PP VOZ]],121,0) -> 0.120598 | W79: =+U79-V79 -> -0.120598 | X79: =+IFERROR(Y79/Z79,0) -> 0 | Y79: =+M79-(Q79+U79) -> 0 | Z79: =VLOOKUP(H79,Tabla2[[#All],[IDPV]:[PP VOZ]],122,0) -> 0.27537392 | AA79: =+Y79-Z79 -> -0.27537392 | AB79: =+M79/$F$3 -> 0 | AC79: =+N79/$F$3 -> 1.0844067 | AD79: =+AB79-AC79 -> -1.0844067 | AE79: =+Q79/$F$3 -> 0 | AF79: =+R79/$F$3 -> 0.68843479 | AG79: =+AE79-AF79 -> -0.68843479 | AH79: =+U79/$F$3 -> 0 | AI79: =+V79/$F$3 -> 0.120598 | AJ79: =+AH79-AI79 -> -0.120598 | AK79: =+Y79/#REF! -> #REF! | AL79: =+Z79/#REF! -> #REF! | AM79: =+AK79-AL79 -> #REF! | AN79: =+COUNTIFS(FieldWy!A:A,H79,FieldWy!F:F,"<>") -> 0 | AO79: =+M79-AN79 -> 0 | AP79: =+COUNTIFS(FieldWy!A:A,H79,FieldWy!F:F,"<>",FieldWy!AA:AA,"true") -> 0 | AQ79: =+Q79-AP79 -> 0 | AR79: =+COUNTIFS(FieldWy!A:A,H79,FieldWy!F:F,"<>",FieldWy!X:X,"PORTABILIDAD") -> 0 | AS79: =+U79+AR79 -> 0 | AT79: =+AN79-(AP79+AR79) -> 0 | AU79: =+Y79-AT79 -> 0
A80: REYES ZARRABAL CRISTOPHER | B80: DANIEL BENJAMIN MARQUEZ BACA | C80: 1 | D80: 10 Pdvs 20 y 21 Jun | E80: Aumento de productividad | F80: Mas de 100 dias Inv | G80: Estable | H80: 2093014 | I80: COPPEL GRAN PATIO | J80: PACHUCA | K80: Coppel | L80: =+IFERROR(M80/N80,0) -> 0 | M80: =SUM(Altas!E77:AI77) -> 0 | N80: =VLOOKUP(H80,Cuota!$D:$DU,119,0) -> 1.3597806 | O80: =+M80-N80 -> -1.3597806 | P80: =+IFERROR(Q80/R80,0) -> 0 | Q80: =+SUM(Altas!E124:AI124) -> 0 | R80: =VLOOKUP(H80,Tabla2[[#All],[IDPV]:[PP VOZ]],120,0) -> 0.68843479 | S80: =+Q80-R80 -> -0.68843479 | T80: =+IFERROR(U80/V80,0) -> 0 | U80: =+SUM(Altas!E171:AI171) -> 0 | V80: =VLOOKUP(H80,Tabla2[[#All],[IDPV]:[PP VOZ]],121,0) -> 0.120598 | W80: =+U80-V80 -> -0.120598 | X80: =+IFERROR(Y80/Z80,0) -> 0 | Y80: =+M80-(Q80+U80) -> 0 | Z80: =VLOOKUP(H80,Tabla2[[#All],[IDPV]:[PP VOZ]],122,0) -> 0.55074783 | AA80: =+Y80-Z80 -> -0.55074783 | AB80: =+M80/$F$3 -> 0 | AC80: =+N80/$F$3 -> 1.3597806 | AD80: =+AB80-AC80 -> -1.3597806 | AE80: =+Q80/$F$3 -> 0 | AF80: =+R80/$F$3 -> 0.68843479 | AG80: =+AE80-AF80 -> -0.68843479 | AH80: =+U80/$F$3 -> 0 | AI80: =+V80/$F$3 -> 0.120598 | AJ80: =+AH80-AI80 -> -0.120598 | AK80: =+Y80/#REF! -> #REF! | AL80: =+Z80/#REF! -> #REF! | AM80: =+AK80-AL80 -> #REF! | AN80: =+COUNTIFS(FieldWy!A:A,H80,FieldWy!F:F,"<>") -> 0 | AO80: =+M80-AN80 -> 0 | AP80: =+COUNTIFS(FieldWy!A:A,H80,FieldWy!F:F,"<>",FieldWy!AA:AA,"true") -> 0 | AQ80: =+Q80-AP80 -> 0 | AR80: =+COUNTIFS(FieldWy!A:A,H80,FieldWy!F:F,"<>",FieldWy!X:X,"PORTABILIDAD") -> 0 | AS80: =+U80+AR80 -> 0 | AT80: =+AN80-(AP80+AR80) -> 0 | AU80: =+Y80-AT80 -> 0
A81: HERNANDEZ HERNANDEZ KARINA | B81: DANIEL BENJAMIN MARQUEZ BACA | C81: 1 | D81: 10 tiendas 90 al 100% | G81: Estable | H81: 2093017 | I81: COPPEL PLAZA BELLA | J81: PACHUCA | K81: Coppel | L81: =+IFERROR(M81/N81,0) -> 0 | M81: =SUM(Altas!E78:AI78) -> 0 | N81: =VLOOKUP(H81,Cuota!$D:$DU,119,0) -> 1.6351545 | O81: =+M81-N81 -> -1.6351545 | P81: =+IFERROR(Q81/R81,0) -> 0 | Q81: =+SUM(Altas!E125:AI125) -> 0 | R81: =VLOOKUP(H81,Tabla2[[#All],[IDPV]:[PP VOZ]],120,0) -> 0.68843479 | S81: =+Q81-R81 -> -0.68843479 | T81: =+IFERROR(U81/V81,0) -> 0 | U81: =+SUM(Altas!E172:AI172) -> 0 | V81: =VLOOKUP(H81,Tabla2[[#All],[IDPV]:[PP VOZ]],121,0) -> 0.120598 | W81: =+U81-V81 -> -0.120598 | X81: =+IFERROR(Y81/Z81,0) -> 0 | Y81: =+M81-(Q81+U81) -> 0 | Z81: =VLOOKUP(H81,Tabla2[[#All],[IDPV]:[PP VOZ]],122,0) -> 0.82612175 | AA81: =+Y81-Z81 -> -0.82612175 | AB81: =+M81/$F$3 -> 0 | AC81: =+N81/$F$3 -> 1.6351545 | AD81: =+AB81-AC81 -> -1.6351545 | AE81: =+Q81/$F$3 -> 0 | AF81: =+R81/$F$3 -> 0.68843479 | AG81: =+AE81-AF81 -> -0.68843479 | AH81: =+U81/$F$3 -> 0 | AI81: =+V81/$F$3 -> 0.120598 | AJ81: =+AH81-AI81 -> -0.120598 | AK81: =+Y81/#REF! -> #REF! | AL81: =+Z81/#REF! -> #REF! | AM81: =+AK81-AL81 -> #REF! | AN81: =+COUNTIFS(FieldWy!A:A,H81,FieldWy!F:F,"<>") -> 0 | AO81: =+M81-AN81 -> 0 | AP81: =+COUNTIFS(FieldWy!A:A,H81,FieldWy!F:F,"<>",FieldWy!AA:AA,"true") -> 0 | AQ81: =+Q81-AP81 -> 0 | AR81: =+COUNTIFS(FieldWy!A:A,H81,FieldWy!F:F,"<>",FieldWy!X:X,"PORTABILIDAD") -> 0 | AS81: =+U81+AR81 -> 0 | AT81: =+AN81-(AP81+AR81) -> 0 | AU81: =+Y81-AT81 -> 0
A82: SANCHEZ MEZA JOB | B82: EDGAR RAUL HERNANDEZ CERVANTES | C82: 1 | H82: 2093034 | I82: COPPEL TOLLOACAN | J82: Toluca de Lerdo | K82: COPPEL | L82: =+IFERROR(M82/N82,0) -> 0 | M82: =SUM(Altas!E79:AI79) -> 0 | N82: =VLOOKUP(H82,Cuota!$D:$DU,119,0) -> 1.7728415 | O82: =+M82-N82 -> -1.7728415 | P82: =+IFERROR(Q82/R82,0) -> 0 | Q82: =+SUM(Altas!E126:AI126) -> 0 | R82: =VLOOKUP(H82,Tabla2[[#All],[IDPV]:[PP VOZ]],120,0) -> 0.82612175 | S82: =+Q82-R82 -> -0.82612175 | T82: =+IFERROR(U82/V82,0) -> 0 | U82: =+SUM(Altas!E173:AI173) -> 0 | V82: =VLOOKUP(H82,Tabla2[[#All],[IDPV]:[PP VOZ]],121,0) -> 0.120598 | W82: =+U82-V82 -> -0.120598 | X82: =+IFERROR(Y82/Z82,0) -> 0 | Y82: =+M82-(Q82+U82) -> 0 | Z82: =VLOOKUP(H82,Tabla2[[#All],[IDPV]:[PP VOZ]],122,0) -> 0.82612175 | AA82: =+Y82-Z82 -> -0.82612175 | AB82: =+M82/$F$3 -> 0 | AC82: =+N82/$F$3 -> 1.7728415 | AD82: =+AB82-AC82 -> -1.7728415 | AE82: =+Q82/$F$3 -> 0 | AF82: =+R82/$F$3 -> 0.82612175 | AG82: =+AE82-AF82 -> -0.82612175 | AH82: =+U82/$F$3 -> 0 | AI82: =+V82/$F$3 -> 0.120598 | AJ82: =+AH82-AI82 -> -0.120598 | AN82: =+COUNTIFS(FieldWy!A:A,H82,FieldWy!F:F,"<>") -> 0 | AO82: =+M82-AN82 -> 0 | AP82: =+COUNTIFS(FieldWy!A:A,H82,FieldWy!F:F,"<>",FieldWy!AA:AA,"true") -> 0 | AQ82: =+Q82-AP82 -> 0 | AR82: =+COUNTIFS(FieldWy!A:A,H82,FieldWy!F:F,"<>",FieldWy!X:X,"PORTABILIDAD") -> 0 | AS82: =+U82+AR82 -> 0 | AT82: =+AN82-(AP82+AR82) -> 0 | AU82: =+Y82-AT82 -> 0
A83: CUEVAS OCAÑA ALMA ROSA | B83: JOSE JAEN OSORIO PAGUIA | C83: 1 | H83: 2093041 | I83: Coppel Nicolás Bravo Atlacomulco | J83: Atlacomulco | K83: COPPEL | L83: =+IFERROR(M83/N83,0) -> 0 | M83: =SUM(Altas!E80:AI80) -> 0 | N83: =VLOOKUP(H83,Cuota!$D:$DU,119,0) -> 3.0291131 | O83: =+M83-N83 -> -3.0291131 | P83: =+IFERROR(Q83/R83,0) -> 0 | Q83: =+SUM(Altas!E127:AI127) -> 0 | R83: =VLOOKUP(H83,Tabla2[[#All],[IDPV]:[PP VOZ]],120,0) -> 1.6522435 | S83: =+Q83-R83 -> -1.6522435 | T83: =+IFERROR(U83/V83,0) -> 0 | U83: =+SUM(Altas!E174:AI174) -> 0 | V83: =VLOOKUP(H83,Tabla2[[#All],[IDPV]:[PP VOZ]],121,0) -> 0 | W83: =+U83-V83 -> 0 | X83: =+IFERROR(Y83/Z83,0) -> 0 | Y83: =+M83-(Q83+U83) -> 0 | Z83: =VLOOKUP(H83,Tabla2[[#All],[IDPV]:[PP VOZ]],122,0) -> 1.3768696 | AA83: =+Y83-Z83 -> -1.3768696 | AB83: =+M83/$F$3 -> 0 | AC83: =+N83/$F$3 -> 3.0291131 | AD83: =+AB83-AC83 -> -3.0291131 | AE83: =+Q83/$F$3 -> 0 | AF83: =+R83/$F$3 -> 1.6522435 | AG83: =+AE83-AF83 -> -1.6522435 | AH83: =+U83/$F$3 -> 0 | AI83: =+V83/$F$3 -> 0 | AJ83: =+AH83-AI83 -> 0 | AN83: =+COUNTIFS(FieldWy!A:A,H83,FieldWy!F:F,"<>") -> 0 | AO83: =+M83-AN83 -> 0 | AP83: =+COUNTIFS(FieldWy!A:A,H83,FieldWy!F:F,"<>",FieldWy!AA:AA,"true") -> 0 | AQ83: =+Q83-AP83 -> 0 | AR83: =+COUNTIFS(FieldWy!A:A,H83,FieldWy!F:F,"<>",FieldWy!X:X,"PORTABILIDAD") -> 0 | AS83: =+U83+AR83 -> 0 | AT83: =+AN83-(AP83+AR83) -> 0 | AU83: =+Y83-AT83 -> 0
A84: CUEVAS OCAÑA ALMA ROSA | B84: JOSE JAEN OSORIO PAGUIA | C84: 1 | H84: 2093092 | I84: EKT ACAMBAY EDO DE MEX | J84: Acambay | K84: ELEKTRA | L84: =+IFERROR(M84/N84,0) -> 0 | M84: =SUM(Altas!E81:AI81) -> 0 | N84: =VLOOKUP(H84,Cuota!$D:$DU,119,0) -> 1.3597806 | O84: =+M84-N84 -> -1.3597806 | P84: =+IFERROR(Q84/R84,0) -> 0 | Q84: =+SUM(Altas!E128:AI128) -> 0 | R84: =VLOOKUP(H84,Tabla2[[#All],[IDPV]:[PP VOZ]],120,0) -> 0.55074783 | S84: =+Q84-R84 -> -0.55074783 | T84: =+IFERROR(U84/V84,0) -> 0 | U84: =+SUM(Altas!E175:AI175) -> 0 | V84: =VLOOKUP(H84,Tabla2[[#All],[IDPV]:[PP VOZ]],121,0) -> 0.120598 | W84: =+U84-V84 -> -0.120598 | X84: =+IFERROR(Y84/Z84,0) -> 0 | Y84: =+M84-(Q84+U84) -> 0 | Z84: =VLOOKUP(H84,Tabla2[[#All],[IDPV]:[PP VOZ]],122,0) -> 0.68843479 | AA84: =+Y84-Z84 -> -0.68843479 | AB84: =+M84/$F$3 -> 0 | AC84: =+N84/$F$3 -> 1.3597806 | AD84: =+AB84-AC84 -> -1.3597806 | AE84: =+Q84/$F$3 -> 0 | AF84: =+R84/$F$3 -> 0.55074783 | AG84: =+AE84-AF84 -> -0.55074783 | AH84: =+U84/$F$3 -> 0 | AI84: =+V84/$F$3 -> 0.120598 | AJ84: =+AH84-AI84 -> -0.120598 | AN84: =+COUNTIFS(FieldWy!A:A,H84,FieldWy!F:F,"<>") -> 0 | AO84: =+M84-AN84 -> 0 | AP84: =+COUNTIFS(FieldWy!A:A,H84,FieldWy!F:F,"<>",FieldWy!AA:AA,"true") -> 0 | AQ84: =+Q84-AP84 -> 0 | AR84: =+COUNTIFS(FieldWy!A:A,H84,FieldWy!F:F,"<>",FieldWy!X:X,"PORTABILIDAD") -> 0 | AS84: =+U84+AR84 -> 0 | AT84: =+AN84-(AP84+AR84) -> 0 | AU84: =+Y84-AT84 -> 0
A85: REYES ZARRABAL CRISTOPHER | B85: CESAR GARRIDO BADILLO | C85: 1 | D85: 10 tiendas 90 al 100% | G85: Estable | H85: 2093110 | I85: COPPEL JUAREZ | J85: AYUTLA DE LOS LIBRES | K85: Coppel | L85: =+IFERROR(M85/N85,0) -> 0 | M85: =SUM(Altas!E82:AI82) -> 0 | N85: =VLOOKUP(H85,Cuota!$D:$DU,119,0) -> 2.0482154 | O85: =+M85-N85 -> -2.0482154 | P85: =+IFERROR(Q85/R85,0) -> 0 | Q85: =+SUM(Altas!E129:AI129) -> 0 | R85: =VLOOKUP(H85,Tabla2[[#All],[IDPV]:[PP VOZ]],120,0) -> 1.1014957 | S85: =+Q85-R85 -> -1.1014957 | T85: =+IFERROR(U85/V85,0) -> 0 | U85: =+SUM(Altas!E176:AI176) -> 0 | V85: =VLOOKUP(H85,Tabla2[[#All],[IDPV]:[PP VOZ]],121,0) -> 0.120598 | W85: =+U85-V85 -> -0.120598 | X85: =+IFERROR(Y85/Z85,0) -> 0 | Y85: =+M85-(Q85+U85) -> 0 | Z85: =VLOOKUP(H85,Tabla2[[#All],[IDPV]:[PP VOZ]],122,0) -> 0.82612175 | AA85: =+Y85-Z85 -> -0.82612175 | AB85: =+M85/$F$3 -> 0 | AC85: =+N85/$F$3 -> 2.0482154 | AD85: =+AB85-AC85 -> -2.0482154 | AE85: =+Q85/$F$3 -> 0 | AF85: =+R85/$F$3 -> 1.1014957 | AG85: =+AE85-AF85 -> -1.1014957 | AH85: =+U85/$F$3 -> 0 | AI85: =+V85/$F$3 -> 0.120598 | AJ85: =+AH85-AI85 -> -0.120598 | AK85: =+Y85/#REF! -> #REF! | AL85: =+Z85/#REF! -> #REF! | AM85: =+AK85-AL85 -> #REF! | AN85: =+COUNTIFS(FieldWy!A:A,H85,FieldWy!F:F,"<>") -> 0 | AO85: =+M85-AN85 -> 0 | AP85: =+COUNTIFS(FieldWy!A:A,H85,FieldWy!F:F,"<>",FieldWy!AA:AA,"true") -> 0 | AQ85: =+Q85-AP85 -> 0 | AR85: =+COUNTIFS(FieldWy!A:A,H85,FieldWy!F:F,"<>",FieldWy!X:X,"PORTABILIDAD") -> 0 | AS85: =+U85+AR85 -> 0 | AT85: =+AN85-(AP85+AR85) -> 0 | AU85: =+Y85-AT85 -> 0
A86: SANCHEZ MEZA JOB | B86: EDGAR RAUL HERNANDEZ CERVANTES | C86: 1 | H86: 2093123 | I86: COPPEL OJUELOS | J86: Toluca de Lerdo | K86: COPPEL | L86: =+IFERROR(M86/N86,0) -> 0 | M86: =SUM(Altas!E83:AI83) -> 0 | N86: =VLOOKUP(H86,Cuota!$D:$DU,119,0) -> 1.7728415 | O86: =+M86-N86 -> -1.7728415 | P86: =+IFERROR(Q86/R86,0) -> 0 | Q86: =+SUM(Altas!E130:AI130) -> 0 | R86: =VLOOKUP(H86,Tabla2[[#All],[IDPV]:[PP VOZ]],120,0) -> 0.96380871 | S86: =+Q86-R86 -> -0.96380871 | T86: =+IFERROR(U86/V86,0) -> 0 | U86: =+SUM(Altas!E177:AI177) -> 0 | V86: =VLOOKUP(H86,Tabla2[[#All],[IDPV]:[PP VOZ]],121,0) -> 0.120598 | W86: =+U86-V86 -> -0.120598 | X86: =+IFERROR(Y86/Z86,0) -> 0 | Y86: =+M86-(Q86+U86) -> 0 | Z86: =VLOOKUP(H86,Tabla2[[#All],[IDPV]:[PP VOZ]],122,0) -> 0.68843479 | AA86: =+Y86-Z86 -> -0.68843479 | AB86: =+M86/$F$3 -> 0 | AC86: =+N86/$F$3 -> 1.7728415 | AD86: =+AB86-AC86 -> -1.7728415 | AE86: =+Q86/$F$3 -> 0 | AF86: =+R86/$F$3 -> 0.96380871 | AG86: =+AE86-AF86 -> -0.96380871 | AH86: =+U86/$F$3 -> 0 | AI86: =+V86/$F$3 -> 0.120598 | AJ86: =+AH86-AI86 -> -0.120598 | AN86: =+COUNTIFS(FieldWy!A:A,H86,FieldWy!F:F,"<>") -> 0 | AO86: =+M86-AN86 -> 0 | AP86: =+COUNTIFS(FieldWy!A:A,H86,FieldWy!F:F,"<>",FieldWy!AA:AA,"true") -> 0 | AQ86: =+Q86-AP86 -> 0 | AR86: =+COUNTIFS(FieldWy!A:A,H86,FieldWy!F:F,"<>",FieldWy!X:X,"PORTABILIDAD") -> 0 | AS86: =+U86+AR86 -> 0 | AT86: =+AN86-(AP86+AR86) -> 0 | AU86: =+Y86-AT86 -> 0
A87: SANCHEZ MEZA JOB | B87: EDGAR RAUL HERNANDEZ CERVANTES | C87: 1 | H87: 2093130 | I87: EKT Villa Victoria | J87: Villa Victoria | K87: ELEKTRA | L87: =+IFERROR(M87/N87,0) -> 0 | M87: =SUM(Altas!E84:AI84) -> 0 | N87: =VLOOKUP(H87,Cuota!$D:$DU,119,0) -> 1.2220937 | O87: =+M87-N87 -> -1.2220937 | P87: =+IFERROR(Q87/R87,0) -> 0 | Q87: =+SUM(Altas!E131:AI131) -> 0 | R87: =VLOOKUP(H87,Tabla2[[#All],[IDPV]:[PP VOZ]],120,0) -> 0.53365888 | S87: =+Q87-R87 -> -0.53365888 | T87: =+IFERROR(U87/V87,0) -> 0 | U87: =+SUM(Altas!E178:AI178) -> 0 | V87: =VLOOKUP(H87,Tabla2[[#All],[IDPV]:[PP VOZ]],121,0) -> 0.120598 | W87: =+U87-V87 -> -0.120598 | X87: =+IFERROR(Y87/Z87,0) -> 0 | Y87: =+M87-(Q87+U87) -> 0 | Z87: =VLOOKUP(H87,Tabla2[[#All],[IDPV]:[PP VOZ]],122,0) -> 0.56783679 | AA87: =+Y87-Z87 -> -0.56783679 | AB87: =+M87/$F$3 -> 0 | AC87: =+N87/$F$3 -> 1.2220937 | AD87: =+AB87-AC87 -> -1.2220937 | AE87: =+Q87/$F$3 -> 0 | AF87: =+R87/$F$3 -> 0.53365888 | AG87: =+AE87-AF87 -> -0.53365888 | AH87: =+U87/$F$3 -> 0 | AI87: =+V87/$F$3 -> 0.120598 | AJ87: =+AH87-AI87 -> -0.120598 | AN87: =+COUNTIFS(FieldWy!A:A,H87,FieldWy!F:F,"<>") -> 0 | AO87: =+M87-AN87 -> 0 | AP87: =+COUNTIFS(FieldWy!A:A,H87,FieldWy!F:F,"<>",FieldWy!AA:AA,"true") -> 0 | AQ87: =+Q87-AP87 -> 0 | AR87: =+COUNTIFS(FieldWy!A:A,H87,FieldWy!F:F,"<>",FieldWy!X:X,"PORTABILIDAD") -> 0 | AS87: =+U87+AR87 -> 0 | AT87: =+AN87-(AP87+AR87) -> 0 | AU87: =+Y87-AT87 -> 0
A88: CALDERON GRACIAN ISRAEL | B88: ERIK ALEJANDRO GARCIA | C88: 1 | H88: 2093137 | I88: MEGA ELEKTRA PLAZA LA PILA (METEPEC) | J88: Metepec | K88: ELEKTRA | L88: =+IFERROR(M88/N88,0) -> 0 | M88: =SUM(Altas!E85:AI85) -> 0 | N88: =VLOOKUP(H88,Cuota!$D:$DU,119,0) -> 1.3768696 | O88: =+M88-N88 -> -1.3768696 | P88: =+IFERROR(Q88/R88,0) -> 0 | Q88: =+SUM(Altas!E132:AI132) -> 0 | R88: =VLOOKUP(H88,Tabla2[[#All],[IDPV]:[PP VOZ]],120,0) -> 0.68843479 | S88: =+Q88-R88 -> -0.68843479 | T88: =+IFERROR(U88/V88,0) -> 0 | U88: =+SUM(Altas!E179:AI179) -> 0 | V88: =VLOOKUP(H88,Tabla2[[#All],[IDPV]:[PP VOZ]],121,0) -> 0 | W88: =+U88-V88 -> 0 | X88: =+IFERROR(Y88/Z88,0) -> 0 | Y88: =+M88-(Q88+U88) -> 0 | Z88: =VLOOKUP(H88,Tabla2[[#All],[IDPV]:[PP VOZ]],122,0) -> 0.68843479 | AA88: =+Y88-Z88 -> -0.68843479 | AB88: =+M88/$F$3 -> 0 | AC88: =+N88/$F$3 -> 1.3768696 | AD88: =+AB88-AC88 -> -1.3768696 | AE88: =+Q88/$F$3 -> 0 | AF88: =+R88/$F$3 -> 0.68843479 | AG88: =+AE88-AF88 -> -0.68843479 | AH88: =+U88/$F$3 -> 0 | AI88: =+V88/$F$3 -> 0 | AJ88: =+AH88-AI88 -> 0 | AN88: =+COUNTIFS(FieldWy!A:A,H88,FieldWy!F:F,"<>") -> 0 | AO88: =+M88-AN88 -> 0 | AP88: =+COUNTIFS(FieldWy!A:A,H88,FieldWy!F:F,"<>",FieldWy!AA:AA,"true") -> 0 | AQ88: =+Q88-AP88 -> 0 | AR88: =+COUNTIFS(FieldWy!A:A,H88,FieldWy!F:F,"<>",FieldWy!X:X,"PORTABILIDAD") -> 0 | AS88: =+U88+AR88 -> 0 | AT88: =+AN88-(AP88+AR88) -> 0 | AU88: =+Y88-AT88 -> 0
A89: REYES ZARRABAL CRISTOPHER | B89: CESAR GARRIDO BADILLO | C89: 1 | G89: Estable | H89: 2093223 | I89: MEGA ELEKTRA 21 DE MARZO TULANCINGO | J89: TULANCINGO DE BRAVO | K89: Elektra | L89: =+IFERROR(M89/N89,0) -> 0 | M89: =SUM(Altas!E86:AI86) -> 0 | N89: =VLOOKUP(H89,Cuota!$D:$DU,119,0) -> 0.94671975 | O89: =+M89-N89 -> -0.94671975 | P89: =+IFERROR(Q89/R89,0) -> 0 | Q89: =+SUM(Altas!E133:AI133) -> 0 | R89: =VLOOKUP(H89,Tabla2[[#All],[IDPV]:[PP VOZ]],120,0) -> 0.41306088 | S89: =+Q89-R89 -> -0.41306088 | T89: =+IFERROR(U89/V89,0) -> 0 | U89: =+SUM(Altas!E180:AI180) -> 0 | V89: =VLOOKUP(H89,Tabla2[[#All],[IDPV]:[PP VOZ]],121,0) -> 0.120598 | W89: =+U89-V89 -> -0.120598 | X89: =+IFERROR(Y89/Z89,0) -> 0 | Y89: =+M89-(Q89+U89) -> 0 | Z89: =VLOOKUP(H89,Tabla2[[#All],[IDPV]:[PP VOZ]],122,0) -> 0.41306088 | AA89: =+Y89-Z89 -> -0.41306088 | AB89: =+M89/$F$3 -> 0 | AC89: =+N89/$F$3 -> 0.94671975 | AD89: =+AB89-AC89 -> -0.94671975 | AE89: =+Q89/$F$3 -> 0 | AF89: =+R89/$F$3 -> 0.41306088 | AG89: =+AE89-AF89 -> -0.41306088 | AH89: =+U89/$F$3 -> 0 | AI89: =+V89/$F$3 -> 0.120598 | AJ89: =+AH89-AI89 -> -0.120598 | AK89: =+Y89/#REF! -> #REF! | AL89: =+Z89/#REF! -> #REF! | AM89: =+AK89-AL89 -> #REF! | AN89: =+COUNTIFS(FieldWy!A:A,H89,FieldWy!F:F,"<>") -> 0 | AO89: =+M89-AN89 -> 0 | AP89: =+COUNTIFS(FieldWy!A:A,H89,FieldWy!F:F,"<>",FieldWy!AA:AA,"true") -> 0 | AQ89: =+Q89-AP89 -> 0 | AR89: =+COUNTIFS(FieldWy!A:A,H89,FieldWy!F:F,"<>",FieldWy!X:X,"PORTABILIDAD") -> 0 | AS89: =+U89+AR89 -> 0 | AT89: =+AN89-(AP89+AR89) -> 0 | AU89: =+Y89-AT89 -> 0
A90: GARCIA GUZMAN JESUS | B90: JOSE JAEN OSORIO PAGUIA | C90: 1 | H90: 2093259 | I90: COPPEL CANADA SOR JUANA | J90: Almoloya de Juarez | K90: COPPEL | L90: =+IFERROR(M90/N90,0) -> 0 | M90: =SUM(Altas!E87:AI87) -> 0 | N90: =VLOOKUP(H90,Cuota!$D:$DU,119,0) -> 4.2512068 | O90: =+M90-N90 -> -4.2512068 | P90: =+IFERROR(Q90/R90,0) -> 0 | Q90: =+SUM(Altas!E134:AI134) -> 0 | R90: =VLOOKUP(H90,Tabla2[[#All],[IDPV]:[PP VOZ]],120,0) -> 3.442174 | S90: =+Q90-R90 -> -3.442174 | T90: =+IFERROR(U90/V90,0) -> 0 | U90: =+SUM(Altas!E181:AI181) -> 0 | V90: =VLOOKUP(H90,Tabla2[[#All],[IDPV]:[PP VOZ]],121,0) -> 0.120598 | W90: =+U90-V90 -> -0.120598 | X90: =+IFERROR(Y90/Z90,0) -> 0 | Y90: =+M90-(Q90+U90) -> 0 | Z90: =VLOOKUP(H90,Tabla2[[#All],[IDPV]:[PP VOZ]],122,0) -> 0.68843479 | AA90: =+Y90-Z90 -> -0.68843479 | AB90: =+M90/$F$3 -> 0 | AC90: =+N90/$F$3 -> 4.2512068 | AD90: =+AB90-AC90 -> -4.2512068 | AE90: =+Q90/$F$3 -> 0 | AF90: =+R90/$F$3 -> 3.442174 | AG90: =+AE90-AF90 -> -3.442174 | AH90: =+U90/$F$3 -> 0 | AI90: =+V90/$F$3 -> 0.120598 | AJ90: =+AH90-AI90 -> -0.120598 | AN90: =+COUNTIFS(FieldWy!A:A,H90,FieldWy!F:F,"<>") -> 0 | AO90: =+M90-AN90 -> 0 | AP90: =+COUNTIFS(FieldWy!A:A,H90,FieldWy!F:F,"<>",FieldWy!AA:AA,"true") -> 0 | AQ90: =+Q90-AP90 -> 0 | AR90: =+COUNTIFS(FieldWy!A:A,H90,FieldWy!F:F,"<>",FieldWy!X:X,"PORTABILIDAD") -> 0 | AS90: =+U90+AR90 -> 0 | AT90: =+AN90-(AP90+AR90) -> 0 | AU90: =+Y90-AT90 -> 0
A91: REYES ZARRABAL CRISTOPHER | B91: CESAR GARRIDO BADILLO | C91: 1 | D91: Tiendas criticas | F91: Mas de 100 dias Inv | G91: Vacante | H91: 2093373 | I91: COPPEL SAHAGUN | J91: CD SAHAGUN | K91: Coppel | L91: =+IFERROR(M91/N91,0) -> 0 | M91: =SUM(Altas!E88:AI88) -> 0 | N91: =VLOOKUP(H91,Cuota!$D:$DU,119,0) -> 2.9949352 | O91: =+M91-N91 -> -2.9949352 | P91: =+IFERROR(Q91/R91,0) -> 0 | Q91: =+SUM(Altas!E135:AI135) -> 0 | R91: =VLOOKUP(H91,Tabla2[[#All],[IDPV]:[PP VOZ]],120,0) -> 1.3597806 | S91: =+Q91-R91 -> -1.3597806 | T91: =+IFERROR(U91/V91,0) -> 0 | U91: =+SUM(Altas!E182:AI182) -> 0 | V91: =VLOOKUP(H91,Tabla2[[#All],[IDPV]:[PP VOZ]],121,0) -> 0.241196 | W91: =+U91-V91 -> -0.241196 | X91: =+IFERROR(Y91/Z91,0) -> 0 | Y91: =+M91-(Q91+U91) -> 0 | Z91: =VLOOKUP(H91,Tabla2[[#All],[IDPV]:[PP VOZ]],122,0) -> 1.3939585 | AA91: =+Y91-Z91 -> -1.3939585 | AB91: =+M91/$F$3 -> 0 | AC91: =+N91/$F$3 -> 2.9949352 | AD91: =+AB91-AC91 -> -2.9949352 | AE91: =+Q91/$F$3 -> 0 | AF91: =+R91/$F$3 -> 1.3597806 | AG91: =+AE91-AF91 -> -1.3597806 | AH91: =+U91/$F$3 -> 0 | AI91: =+V91/$F$3 -> 0.241196 | AJ91: =+AH91-AI91 -> -0.241196 | AK91: =+Y91/#REF! -> #REF! | AL91: =+Z91/#REF! -> #REF! | AM91: =+AK91-AL91 -> #REF! | AN91: =+COUNTIFS(FieldWy!A:A,H91,FieldWy!F:F,"<>") -> 0 | AO91: =+M91-AN91 -> 0 | AP91: =+COUNTIFS(FieldWy!A:A,H91,FieldWy!F:F,"<>",FieldWy!AA:AA,"true") -> 0 | AQ91: =+Q91-AP91 -> 0 | AR91: =+COUNTIFS(FieldWy!A:A,H91,FieldWy!F:F,"<>",FieldWy!X:X,"PORTABILIDAD") -> 0 | AS91: =+U91+AR91 -> 0 | AT91: =+AN91-(AP91+AR91) -> 0 | AU91: =+Y91-AT91 -> 0
A92: SANCHEZ MEZA JOB | B92: EDGAR RAUL HERNANDEZ CERVANTES | C92: 1 | H92: 2093375 | I92: COPPEL GRAN PATIO | J92: Almoloya de Juarez | K92: COPPEL | L92: =+IFERROR(M92/N92,0) -> 0 | M92: =SUM(Altas!E89:AI89) -> 0 | N92: =VLOOKUP(H92,Cuota!$D:$DU,119,0) -> 2.4612763 | O92: =+M92-N92 -> -2.4612763 | P92: =+IFERROR(Q92/R92,0) -> 0 | Q92: =+SUM(Altas!E136:AI136) -> 0 | R92: =VLOOKUP(H92,Tabla2[[#All],[IDPV]:[PP VOZ]],120,0) -> 1.7899305 | S92: =+Q92-R92 -> -1.7899305 | T92: =+IFERROR(U92/V92,0) -> 0 | U92: =+SUM(Altas!E183:AI183) -> 0 | V92: =VLOOKUP(H92,Tabla2[[#All],[IDPV]:[PP VOZ]],121,0) -> 0.120598 | W92: =+U92-V92 -> -0.120598 | X92: =+IFERROR(Y92/Z92,0) -> 0 | Y92: =+M92-(Q92+U92) -> 0 | Z92: =VLOOKUP(H92,Tabla2[[#All],[IDPV]:[PP VOZ]],122,0) -> 0.55074783 | AA92: =+Y92-Z92 -> -0.55074783 | AB92: =+M92/$F$3 -> 0 | AC92: =+N92/$F$3 -> 2.4612763 | AD92: =+AB92-AC92 -> -2.4612763 | AE92: =+Q92/$F$3 -> 0 | AF92: =+R92/$F$3 -> 1.7899305 | AG92: =+AE92-AF92 -> -1.7899305 | AH92: =+U92/$F$3 -> 0 | AI92: =+V92/$F$3 -> 0.120598 | AJ92: =+AH92-AI92 -> -0.120598 | AN92: =+COUNTIFS(FieldWy!A:A,H92,FieldWy!F:F,"<>") -> 0 | AO92: =+M92-AN92 -> 0 | AP92: =+COUNTIFS(FieldWy!A:A,H92,FieldWy!F:F,"<>",FieldWy!AA:AA,"true") -> 0 | AQ92: =+Q92-AP92 -> 0 | AR92: =+COUNTIFS(FieldWy!A:A,H92,FieldWy!F:F,"<>",FieldWy!X:X,"PORTABILIDAD") -> 0 | AS92: =+U92+AR92 -> 0 | AT92: =+AN92-(AP92+AR92) -> 0 | AU92: =+Y92-AT92 -> 0
A93: GARCIA GUZMAN JESUS | B93: JOSE JAEN OSORIO PAGUIA | C93: 1 | H93: 2093377 | I93: SB ATLACOMULCO | J93: Atlacomulco | K93: SUBURBIA | L93: =+IFERROR(M93/N93,0) -> 0 | M93: =SUM(Altas!E90:AI90) -> 0 | N93: =VLOOKUP(H93,Cuota!$D:$DU,119,0) -> 1.2391826 | O93: =+M93-N93 -> -1.2391826 | P93: =+IFERROR(Q93/R93,0) -> 0 | Q93: =+SUM(Altas!E137:AI137) -> 0 | R93: =VLOOKUP(H93,Tabla2[[#All],[IDPV]:[PP VOZ]],120,0) -> 0.82612175 | S93: =+Q93-R93 -> -0.82612175 | T93: =+IFERROR(U93/V93,0) -> 0 | U93: =+SUM(Altas!E184:AI184) -> 0 | V93: =VLOOKUP(H93,Tabla2[[#All],[IDPV]:[PP VOZ]],121,0) -> 0 | W93: =+U93-V93 -> 0 | X93: =+IFERROR(Y93/Z93,0) -> 0 | Y93: =+M93-(Q93+U93) -> 0 | Z93: =VLOOKUP(H93,Tabla2[[#All],[IDPV]:[PP VOZ]],122,0) -> 0.41306088 | AA93: =+Y93-Z93 -> -0.41306088 | AB93: =+M93/$F$3 -> 0 | AC93: =+N93/$F$3 -> 1.2391826 | AD93: =+AB93-AC93 -> -1.2391826 | AE93: =+Q93/$F$3 -> 0 | AF93: =+R93/$F$3 -> 0.82612175 | AG93: =+AE93-AF93 -> -0.82612175 | AH93: =+U93/$F$3 -> 0 | AI93: =+V93/$F$3 -> 0 | AJ93: =+AH93-AI93 -> 0 | AN93: =+COUNTIFS(FieldWy!A:A,H93,FieldWy!F:F,"<>") -> 0 | AO93: =+M93-AN93 -> 0 | AP93: =+COUNTIFS(FieldWy!A:A,H93,FieldWy!F:F,"<>",FieldWy!AA:AA,"true") -> 0 | AQ93: =+Q93-AP93 -> 0 | AR93: =+COUNTIFS(FieldWy!A:A,H93,FieldWy!F:F,"<>",FieldWy!X:X,"PORTABILIDAD") -> 0 | AS93: =+U93+AR93 -> 0 | AT93: =+AN93-(AP93+AR93) -> 0 | AU93: =+Y93-AT93 -> 0
A94: REYES ZARRABAL CRISTOPHER | B94: DANIEL BENJAMIN MARQUEZ BACA | C94: 1 | D94: 10 Pdvs 20 y 21 Jun | E94: Arranque rapido | G94: Nuevo promotor | H94: 2093389 | I94: MEGA ELEKTRA AV. JUAREZ TIZAYUCA | J94: TIZAYUCA | K94: Elektra | L94: =+IFERROR(M94/N94,0) -> 0 | M94: =SUM(Altas!E91:AI91) -> 0 | N94: =VLOOKUP(H94,Cuota!$D:$DU,119,0) -> 0.94671975 | O94: =+M94-N94 -> -0.94671975 | P94: =+IFERROR(Q94/R94,0) -> 0 | Q94: =+SUM(Altas!E138:AI138) -> 0 | R94: =VLOOKUP(H94,Tabla2[[#All],[IDPV]:[PP VOZ]],120,0) -> 0.41306088 | S94: =+Q94-R94 -> -0.41306088 | T94: =+IFERROR(U94/V94,0) -> 0 | U94: =+SUM(Altas!E185:AI185) -> 0 | V94: =VLOOKUP(H94,Tabla2[[#All],[IDPV]:[PP VOZ]],121,0) -> 0.120598 | W94: =+U94-V94 -> -0.120598 | X94: =+IFERROR(Y94/Z94,0) -> 0 | Y94: =+M94-(Q94+U94) -> 0 | Z94: =VLOOKUP(H94,Tabla2[[#All],[IDPV]:[PP VOZ]],122,0) -> 0.41306088 | AA94: =+Y94-Z94 -> -0.41306088 | AB94: =+M94/$F$3 -> 0 | AC94: =+N94/$F$3 -> 0.94671975 | AD94: =+AB94-AC94 -> -0.94671975 | AE94: =+Q94/$F$3 -> 0 | AF94: =+R94/$F$3 -> 0.41306088 | AG94: =+AE94-AF94 -> -0.41306088 | AH94: =+U94/$F$3 -> 0 | AI94: =+V94/$F$3 -> 0.120598 | AJ94: =+AH94-AI94 -> -0.120598 | AK94: =+Y94/#REF! -> #REF! | AL94: =+Z94/#REF! -> #REF! | AM94: =+AK94-AL94 -> #REF! | AN94: =+COUNTIFS(FieldWy!A:A,H94,FieldWy!F:F,"<>") -> 0 | AO94: =+M94-AN94 -> 0 | AP94: =+COUNTIFS(FieldWy!A:A,H94,FieldWy!F:F,"<>",FieldWy!AA:AA,"true") -> 0 | AQ94: =+Q94-AP94 -> 0 | AR94: =+COUNTIFS(FieldWy!A:A,H94,FieldWy!F:F,"<>",FieldWy!X:X,"PORTABILIDAD") -> 0 | AS94: =+U94+AR94 -> 0 | AT94: =+AN94-(AP94+AR94) -> 0 | AU94: =+Y94-AT94 -> 0
A95: BARRIENTOS CONTRERAS ILEANA | B95: DANIEL BENJAMIN MARQUEZ BACA | C95: 1 | D95: Tiendas criticas | E95: Aumento de productividad | G95: Vacante | H95: 2093457 | I95: MEGA PLAZA LA JOYA PACHUCA | J95: PACHUCA | K95: Elektra | L95: =+IFERROR(M95/N95,0) -> 0 | M95: =SUM(Altas!E92:AI92) -> 0 | N95: =VLOOKUP(H95,Cuota!$D:$DU,119,0) -> 0.94671975 | O95: =+M95-N95 -> -0.94671975 | P95: =+IFERROR(Q95/R95,0) -> 0 | Q95: =+SUM(Altas!E139:AI139) -> 0 | R95: =VLOOKUP(H95,Tabla2[[#All],[IDPV]:[PP VOZ]],120,0) -> 0.41306088 | S95: =+Q95-R95 -> -0.41306088 | T95: =+IFERROR(U95/V95,0) -> 0 | U95: =+SUM(Altas!E186:AI186) -> 0 | V95: =VLOOKUP(H95,Tabla2[[#All],[IDPV]:[PP VOZ]],121,0) -> 0.120598 | W95: =+U95-V95 -> -0.120598 | X95: =+IFERROR(Y95/Z95,0) -> 0 | Y95: =+M95-(Q95+U95) -> 0 | Z95: =VLOOKUP(H95,Tabla2[[#All],[IDPV]:[PP VOZ]],122,0) -> 0.41306088 | AA95: =+Y95-Z95 -> -0.41306088 | AB95: =+M95/$F$3 -> 0 | AC95: =+N95/$F$3 -> 0.94671975 | AD95: =+AB95-AC95 -> -0.94671975 | AE95: =+Q95/$F$3 -> 0 | AF95: =+R95/$F$3 -> 0.41306088 | AG95: =+AE95-AF95 -> -0.41306088 | AH95: =+U95/$F$3 -> 0 | AI95: =+V95/$F$3 -> 0.120598 | AJ95: =+AH95-AI95 -> -0.120598 | AK95: =+Y95/#REF! -> #REF! | AL95: =+Z95/#REF! -> #REF! | AM95: =+AK95-AL95 -> #REF! | AN95: =+COUNTIFS(FieldWy!A:A,H95,FieldWy!F:F,"<>") -> 0 | AO95: =+M95-AN95 -> 0 | AP95: =+COUNTIFS(FieldWy!A:A,H95,FieldWy!F:F,"<>",FieldWy!AA:AA,"true") -> 0 | AQ95: =+Q95-AP95 -> 0 | AR95: =+COUNTIFS(FieldWy!A:A,H95,FieldWy!F:F,"<>",FieldWy!X:X,"PORTABILIDAD") -> 0 | AS95: =+U95+AR95 -> 0 | AT95: =+AN95-(AP95+AR95) -> 0 | AU95: =+Y95-AT95 -> 0
A96: REYES ZARRABAL CRISTOPHER | B96: CESAR GARRIDO BADILLO | C96: 1 | D96: Tiendas criticas | G96: Nuevo promotor | H96: 2093564 | I96: MEGA ELEKTRA CD SAHAGUN 2 | J96: CD SAHAGUN | K96: Elektra | L96: =+IFERROR(M96/N96,0) -> 0 | M96: =SUM(Altas!E93:AI93) -> 0 | N96: =VLOOKUP(H96,Cuota!$D:$DU,119,0) -> 0.94671975 | O96: =+M96-N96 -> -0.94671975 | P96: =+IFERROR(Q96/R96,0) -> 0 | Q96: =+SUM(Altas!E140:AI140) -> 0 | R96: =VLOOKUP(H96,Tabla2[[#All],[IDPV]:[PP VOZ]],120,0) -> 0.41306088 | S96: =+Q96-R96 -> -0.41306088 | T96: =+IFERROR(U96/V96,0) -> 0 | U96: =+SUM(Altas!E187:AI187) -> 0 | V96: =VLOOKUP(H96,Tabla2[[#All],[IDPV]:[PP VOZ]],121,0) -> 0.120598 | W96: =+U96-V96 -> -0.120598 | X96: =+IFERROR(Y96/Z96,0) -> 0 | Y96: =+M96-(Q96+U96) -> 0 | Z96: =VLOOKUP(H96,Tabla2[[#All],[IDPV]:[PP VOZ]],122,0) -> 0.41306088 | AA96: =+Y96-Z96 -> -0.41306088 | AB96: =+M96/$F$3 -> 0 | AC96: =+N96/$F$3 -> 0.94671975 | AD96: =+AB96-AC96 -> -0.94671975 | AE96: =+Q96/$F$3 -> 0 | AF96: =+R96/$F$3 -> 0.41306088 | AG96: =+AE96-AF96 -> -0.41306088 | AH96: =+U96/$F$3 -> 0 | AI96: =+V96/$F$3 -> 0.120598 | AJ96: =+AH96-AI96 -> -0.120598 | AK96: =+Y96/#REF! -> #REF! | AL96: =+Z96/#REF! -> #REF! | AM96: =+AK96-AL96 -> #REF! | AN96: =+COUNTIFS(FieldWy!A:A,H96,FieldWy!F:F,"<>") -> 0 | AO96: =+M96-AN96 -> 0 | AP96: =+COUNTIFS(FieldWy!A:A,H96,FieldWy!F:F,"<>",FieldWy!AA:AA,"true") -> 0 | AQ96: =+Q96-AP96 -> 0 | AR96: =+COUNTIFS(FieldWy!A:A,H96,FieldWy!F:F,"<>",FieldWy!X:X,"PORTABILIDAD") -> 0 | AS96: =+U96+AR96 -> 0 | AT96: =+AN96-(AP96+AR96) -> 0 | AU96: =+Y96-AT96 -> 0
A97: REYES ZARRABAL CRISTOPHER | B97: JIOBANI MARIN BUENDIA BARCENAS | C97: 1 | D97: 10 tiendas 90 al 100% | E97: Oppo | G97: Estable | H97: 2093570 | I97: EKT MEGA ATITALAQUIA, HIDALGO | J97: TLAXCOAPAN | K97: Elektra | L97: =+IFERROR(M97/N97,0) -> 0 | M97: =SUM(Altas!E94:AI94) -> 0 | N97: =VLOOKUP(H97,Cuota!$D:$DU,119,0) -> 0.94671975 | O97: =+M97-N97 -> -0.94671975 | P97: =+IFERROR(Q97/R97,0) -> 0 | Q97: =+SUM(Altas!E141:AI141) -> 0 | R97: =VLOOKUP(H97,Tabla2[[#All],[IDPV]:[PP VOZ]],120,0) -> 0.41306088 | S97: =+Q97-R97 -> -0.41306088 | T97: =+IFERROR(U97/V97,0) -> 0 | U97: =+SUM(Altas!E188:AI188) -> 0 | V97: =VLOOKUP(H97,Tabla2[[#All],[IDPV]:[PP VOZ]],121,0) -> 0.120598 | W97: =+U97-V97 -> -0.120598 | X97: =+IFERROR(Y97/Z97,0) -> 0 | Y97: =+M97-(Q97+U97) -> 0 | Z97: =VLOOKUP(H97,Tabla2[[#All],[IDPV]:[PP VOZ]],122,0) -> 0.41306088 | AA97: =+Y97-Z97 -> -0.41306088 | AB97: =+M97/$F$3 -> 0 | AC97: =+N97/$F$3 -> 0.94671975 | AD97: =+AB97-AC97 -> -0.94671975 | AE97: =+Q97/$F$3 -> 0 | AF97: =+R97/$F$3 -> 0.41306088 | AG97: =+AE97-AF97 -> -0.41306088 | AH97: =+U97/$F$3 -> 0 | AI97: =+V97/$F$3 -> 0.120598 | AJ97: =+AH97-AI97 -> -0.120598 | AK97: =+Y97/#REF! -> #REF! | AL97: =+Z97/#REF! -> #REF! | AM97: =+AK97-AL97 -> #REF! | AN97: =+COUNTIFS(FieldWy!A:A,H97,FieldWy!F:F,"<>") -> 0 | AO97: =+M97-AN97 -> 0 | AP97: =+COUNTIFS(FieldWy!A:A,H97,FieldWy!F:F,"<>",FieldWy!AA:AA,"true") -> 0 | AQ97: =+Q97-AP97 -> 0 | AR97: =+COUNTIFS(FieldWy!A:A,H97,FieldWy!F:F,"<>",FieldWy!X:X,"PORTABILIDAD") -> 0 | AS97: =+U97+AR97 -> 0 | AT97: =+AN97-(AP97+AR97) -> 0 | AU97: =+Y97-AT97 -> 0
A98: BARRIENTOS CONTRERAS ILEANA | B98: DANIEL BENJAMIN MARQUEZ BACA | C98: 1 | F98: Mas de 100 dias Inv | G98: Estable | H98: 2093669 | I98: COPPEL EXPLANADA | J98: PACHUCA | K98: Coppel | L98: =+IFERROR(M98/N98,0) -> 0 | M98: =SUM(Altas!E95:AI95) -> 0 | N98: =VLOOKUP(H98,Cuota!$D:$DU,119,0) -> 0.94671975 | O98: =+M98-N98 -> -0.94671975 | P98: =+IFERROR(Q98/R98,0) -> 0 | Q98: =+SUM(Altas!E142:AI142) -> 0 | R98: =VLOOKUP(H98,Tabla2[[#All],[IDPV]:[PP VOZ]],120,0) -> 0.55074783 | S98: =+Q98-R98 -> -0.55074783 | T98: =+IFERROR(U98/V98,0) -> 0 | U98: =+SUM(Altas!E189:AI189) -> 0 | V98: =VLOOKUP(H98,Tabla2[[#All],[IDPV]:[PP VOZ]],121,0) -> 0.120598 | W98: =+U98-V98 -> -0.120598 | X98: =+IFERROR(Y98/Z98,0) -> 0 | Y98: =+M98-(Q98+U98) -> 0 | Z98: =VLOOKUP(H98,Tabla2[[#All],[IDPV]:[PP VOZ]],122,0) -> 0.27537392 | AA98: =+Y98-Z98 -> -0.27537392 | AB98: =+M98/$F$3 -> 0 | AC98: =+N98/$F$3 -> 0.94671975 | AD98: =+AB98-AC98 -> -0.94671975 | AE98: =+Q98/$F$3 -> 0 | AF98: =+R98/$F$3 -> 0.55074783 | AG98: =+AE98-AF98 -> -0.55074783 | AH98: =+U98/$F$3 -> 0 | AI98: =+V98/$F$3 -> 0.120598 | AJ98: =+AH98-AI98 -> -0.120598 | AK98: =+Y98/#REF! -> #REF! | AL98: =+Z98/#REF! -> #REF! | AM98: =+AK98-AL98 -> #REF! | AN98: =+COUNTIFS(FieldWy!A:A,H98,FieldWy!F:F,"<>") -> 0 | AO98: =+M98-AN98 -> 0 | AP98: =+COUNTIFS(FieldWy!A:A,H98,FieldWy!F:F,"<>",FieldWy!AA:AA,"true") -> 0 | AQ98: =+Q98-AP98 -> 0 | AR98: =+COUNTIFS(FieldWy!A:A,H98,FieldWy!F:F,"<>",FieldWy!X:X,"PORTABILIDAD") -> 0 | AS98: =+U98+AR98 -> 0 | AT98: =+AN98-(AP98+AR98) -> 0 | AU98: =+Y98-AT98 -> 0
